{"features": [{"geometry": {"coordinates": [54.04327, 37.02772], "type": "Point"}, "properties": {"arBW": "Abaskun", "arTitle": "\u0622\u0628\u0633\u0643\u0648\u0646", "arTitleOther": "\u0622\u0628\u0633\u0643\u0648\u0646", "lat": "37.02772", "lon": "54.04327", "region": "Daylam", "searchNames": "Abaskun", "topType": "towns", "topTypeAlt": "cite/port", "topURI": "ABASKUN_540E370N_S_DAYL", "translitTitle": "\u0100bask\u016bn", "translitTitleOther": "\u0100bask\u016bn"}, "type": "Feature"}], "type": "FeatureCollection"}