{"features": [{"geometry": {"coordinates": [31.7988, 26.47449], "type": "Point"}, "properties": {"arBW": "Abshaya", "arTitle": "\u0623\u0628\u0634\u0627\u064a\u0629", "arTitleOther": "\u0623\u0628\u0634\u0627\u064a\u0629", "lat": "26.47449", "lon": "31.79880", "region": "Egypt", "searchNames": "Abshaya", "topType": "villages", "topTypeAlt": "localite", "topURI": "ABSHAYA_317E264N_S_EGYP", "translitTitle": "Ab\u0161\u0101ya\u0167", "translitTitleOther": "Ab\u0161\u0101ya\u0167"}, "type": "Feature"}], "type": "FeatureCollection"}