{"features": [{"geometry": {"coordinates": [63.528, 35.24882], "type": "Point"}, "properties": {"arBW": "Abshin", "arTitle": "\u0623\u0628\u0634\u064a\u0646", "arTitleOther": "\u0623\u0628\u0634\u064a\u0646", "lat": "35.24882", "lon": "63.52800", "region": "Khurasan", "searchNames": "Abshin", "topType": "towns", "topTypeAlt": "cite", "topURI": "ABSHIN_635E352N_S_KHUR", "translitTitle": "Ab\u0161\u012bn", "translitTitleOther": "Ab\u0161\u012bn"}, "type": "Feature"}], "type": "FeatureCollection"}