{"features": [{"geometry": {"coordinates": [42.45438, 31.86163], "type": "Point"}, "properties": {"arBW": "al-Abyad", "arTitle": "\ufb50\u0644\u0623\u0628\u064a\u0636", "arTitleOther": "\ufb50\u0644\u0623\u0628\u064a\u0636", "lat": "31.86163", "lon": "42.45438", "region": "Badiyat al-Arab", "searchNames": "al-Abyad", "topType": "waystations", "topTypeAlt": "etape", "topURI": "ABYAD_424E318N_S_BADI", "translitTitle": "al-Abya\u1e0d", "translitTitleOther": "al-Abya\u1e0d"}, "type": "Feature"}], "type": "FeatureCollection"}