{"features": [{"geometry": {"coordinates": [45.03942, 12.79365], "type": "Point"}, "properties": {"arBW": "Adan", "arTitle": "\u0639\u062f\u0646", "arTitleOther": "\u0639\u062f\u0646", "lat": "12.79365", "lon": "45.03942", "region": "Yemen", "searchNames": "Adan", "topType": "towns", "topTypeAlt": "cite/port", "topURI": "ADAN_450E127N_S_YEME", "translitTitle": "\u02bfAdan", "translitTitleOther": "\u02bfAdan"}, "type": "Feature"}], "type": "FeatureCollection"}