{"features": [{"geometry": {"coordinates": [48.69059, 31.32986], "type": "Point"}, "properties": {"arBW": "al-Ahwaz, Suq al-Ahwaz", "arTitle": "\ufb50\u0644\u0623\u0647\u0648\u0627\u0632", "arTitleOther": "\ufb50\u0644\u0623\u0647\u0648\u0627\u0632\u060c \u0633\u0648\u0642 \ufb50\u0644\u0623\u0647\u0648\u0627\u0632", "lat": "31.32986", "lon": "48.69059", "region": "Khuzistan", "searchNames": "al-Ahwaz, Suq al-Ahwaz", "topType": "metropoles", "topTypeAlt": "metropole", "topURI": "AHWAZ_486E313N_S_KHUZ", "translitTitle": "al-Ahw\u0101z", "translitTitleOther": "al-Ahw\u0101z, S\u016bq al-Ahw\u0101z"}, "type": "Feature"}], "type": "FeatureCollection"}