{"features": [{"geometry": {"coordinates": [46.61972, 13.56967], "type": "Point"}, "properties": {"arBW": "Ahwar", "arTitle": "\u0623\u062d\u0648\u0631", "arTitleOther": "\u0623\u062d\u0648\u0631", "lat": "13.56967", "lon": "46.61972", "region": "Jazirat al-Arab", "searchNames": "Ahwar", "topType": "towns", "topTypeAlt": "cite", "topURI": "AHWAR_466E135N_S_JAZI", "translitTitle": "A\u1e25war", "translitTitleOther": "A\u1e25war"}, "type": "Feature"}], "type": "FeatureCollection"}