{"features": [{"geometry": {"coordinates": [42.97781, 27.44255], "type": "Point"}, "properties": {"arBW": "al-Ajfur", "arTitle": "\ufb50\u0644\u0623\u062c\u0641\u0631", "arTitleOther": "\ufb50\u0644\u0623\u062c\u0641\u0631", "lat": "27.44255", "lon": "42.97781", "region": "Badiyat al-Arab", "searchNames": "al-Ajfur", "topType": "waystations", "topTypeAlt": "etape", "topURI": "AJFUR_429E274N_S_BADI", "translitTitle": "al-A\u01e7fur", "translitTitleOther": "al-A\u01e7fur"}, "type": "Feature"}], "type": "FeatureCollection"}