{"features": [{"geometry": {"coordinates": [45.17945, 13.2032], "type": "Point"}, "properties": {"arBW": "Akhilla", "arTitle": "\u0623\u062e\u0644\u0629", "arTitleOther": "\u0623\u062e\u0644\u0629", "lat": "13.20320", "lon": "45.17945", "region": "Yemen", "searchNames": "Akhilla", "topType": "regions", "topTypeAlt": "region", "topURI": "AKHILLA_451E132N_R_YEME", "translitTitle": "A\u1e2billa\u0167", "translitTitleOther": "A\u1e2billa\u0167"}, "type": "Feature"}], "type": "FeatureCollection"}