{"features": [{"geometry": {"coordinates": [42.51044, 38.76551], "type": "Point"}, "properties": {"arBW": "Akhlat, Khilat", "arTitle": "\u0623\u062e\u0644\u0627\u0637", "arTitleOther": "\u0623\u062e\u0644\u0627\u0637\u060c \u062e\u0644\u0627\u0637", "lat": "38.76551", "lon": "42.51044", "region": "Rihab", "searchNames": "Akhlat, Khilat", "topType": "towns", "topTypeAlt": "cite", "topURI": "AKHLAT_425E387N_S_RIHA", "translitTitle": "A\u1e2bl\u0101\u1e6d", "translitTitleOther": "A\u1e2bl\u0101\u1e6d, \u1e2ail\u0101\u1e6d"}, "type": "Feature"}], "type": "FeatureCollection"}