{"features": [{"geometry": {"coordinates": [40.21323, 37.9151], "type": "Point"}, "properties": {"arBW": "Amid", "arTitle": "\u0622\u0645\u062f", "arTitleOther": "\u0622\u0645\u062f", "lat": "37.91510", "lon": "40.21323", "region": "Aqur", "searchNames": "Amid", "topType": "capitals", "topTypeAlt": "capitale", "topURI": "AMID_402E379N_S_AQUR", "translitTitle": "\u0100mid", "translitTitleOther": "\u0100mid"}, "type": "Feature"}], "type": "FeatureCollection"}