{"features": [{"geometry": {"coordinates": [41.95904, 34.43481], "type": "Point"}, "properties": {"arBW": "Ana", "arTitle": "\u0639\u0627\u0646\u0629", "arTitleOther": "\u0639\u0627\u0646\u0629", "lat": "34.43481", "lon": "41.95904", "region": "Aqur", "searchNames": "Ana", "topType": "towns", "topTypeAlt": "cite", "topURI": "ANA_419E344N_S_AQUR", "translitTitle": "\u02bf\u0100na\u0167", "translitTitleOther": "\u02bf\u0100na\u0167"}, "type": "Feature"}], "type": "FeatureCollection"}