{"features": [{"geometry": {"coordinates": [36.18418, 36.19718], "type": "Point"}, "properties": {"arBW": "Antakiyya", "arTitle": "\u0623\u0646\u0637\u0627\u0643\u064a\u0629", "arTitleOther": "\u0623\u0646\u0637\u0627\u0643\u064a\u0629", "lat": "36.19718", "lon": "36.18418", "region": "Sham", "searchNames": "Antakiyya", "topType": "towns", "topTypeAlt": "cite", "topURI": "ANTAKIYYA_361E361N_S_SHAM", "translitTitle": "An\u1e6d\u0101kiyya\u0167", "translitTitleOther": "An\u1e6d\u0101kiyya\u0167"}, "type": "Feature"}], "type": "FeatureCollection"}