{"features": [{"geometry": {"coordinates": [35.90356, 34.89985], "type": "Point"}, "properties": {"arBW": "Antartus, Antarsus, Tartus", "arTitle": "\u0623\u0646\u0637\u0631\u0637\u0648\u0633", "arTitleOther": "\u0623\u0646\u0637\u0631\u0637\u0648\u0633\u060c \u0623\u0646\u0637\u0631\u0633\u0648\u0633\u060c \u0637\u0631\u0637\u0648\u0633", "lat": "34.89985", "lon": "35.90356", "region": "Sham", "searchNames": "Antartus, Antarsus, Tartus", "topType": "towns", "topTypeAlt": "cite", "topURI": "ANTARTUS_359E348N_S_SHAM", "translitTitle": "An\u1e6dar\u1e6d\u016bs", "translitTitleOther": "An\u1e6dar\u1e6d\u016bs, An\u1e6dars\u016bs, \u1e6car\u1e6d\u016bs"}, "type": "Feature"}], "type": "FeatureCollection"}