{"features": [{"geometry": {"coordinates": [25.18308, 31.42889], "type": "Point"}, "properties": {"arBW": "al-Aqaba", "arTitle": "\ufb50\u0644\u0639\u0642\u0628\u0629", "arTitleOther": "\ufb50\u0644\u0639\u0642\u0628\u0629", "lat": "31.42889", "lon": "25.18308", "region": "Barqa", "searchNames": "al-Aqaba", "topType": "waystations", "topTypeAlt": "etape", "topURI": "AQABA_251E314N_S_BARQ", "translitTitle": "al-\u02bfAqaba\u0167", "translitTitleOther": "al-\u02bfAqaba\u0167"}, "type": "Feature"}], "type": "FeatureCollection"}