{"features": [{"geometry": {"coordinates": [40.69403, 36.05814], "type": "Point"}, "properties": {"arBW": "Araban", "arTitle": "\u0639\u0631\u0628\u0627\u0646", "arTitleOther": "\u0639\u0631\u0628\u0627\u0646", "lat": "36.05814", "lon": "40.69403", "region": "Aqur", "searchNames": "Araban", "topType": "capitals", "topTypeAlt": "capitale", "topURI": "ARABAN_406E360N_S_AQUR", "translitTitle": "\u02bfArab\u0101n", "translitTitleOther": "\u02bfArab\u0101n"}, "type": "Feature"}], "type": "FeatureCollection"}