{"features": [{"geometry": {"coordinates": [60.25053, 42.19314], "type": "Point"}, "properties": {"arBW": "Ardakhiwah", "arTitle": "\u0623\u0631\u062f\u062e\u064a\u0648\u0647", "arTitleOther": "\u0623\u0631\u062f\u062e\u064a\u0648\u0647", "lat": "42.19314", "lon": "60.25053", "region": "Transoxiana", "searchNames": "Ardakhiwah", "topType": "towns", "topTypeAlt": "cite", "topURI": "ARDAKHIWAH_602E421N_S_TRAN", "translitTitle": "Arda\u1e2b\u012bwah", "translitTitleOther": "Arda\u1e2b\u012bwah"}, "type": "Feature"}], "type": "FeatureCollection"}