{"features": [{"geometry": {"coordinates": [57.0129, 27.93413], "type": "Point"}, "properties": {"arBW": "Ardakan, Surakan", "arTitle": "\u0623\u0631\u062f\u0643\u0627\u0646", "arTitleOther": "\u0623\u0631\u062f\u0643\u0627\u0646\u060c \u0633\u0648\u0631\u0643\u0627\u0646", "lat": "27.93413", "lon": "57.01290", "region": "Kirman", "searchNames": "Ardakan, Surakan", "topType": "towns", "topTypeAlt": "ville", "topURI": "ARDAKAN_570E279N_S_KIRM", "translitTitle": "Ardak\u0101n", "translitTitleOther": "Ardak\u0101n, S\u016brak\u0101n"}, "type": "Feature"}], "type": "FeatureCollection"}