{"features": [{"geometry": {"coordinates": [48.30651, 38.23604], "type": "Point"}, "properties": {"arBW": "Ardabil", "arTitle": "\u0623\u0631\u062f\u0628\u064a\u0644", "arTitleOther": "\u0623\u0631\u062f\u0628\u064a\u0644", "lat": "38.23604", "lon": "48.30651", "region": "Rihab", "searchNames": "Ardabil", "topType": "metropoles", "topTypeAlt": "metropole", "topURI": "ARDABIL_483E382N_S_RIHA", "translitTitle": "Ardab\u012bl", "translitTitleOther": "Ardab\u012bl"}, "type": "Feature"}], "type": "FeatureCollection"}