{"features": [{"geometry": {"coordinates": [41.65964, 37.9789], "type": "Point"}, "properties": {"arBW": "Arzan", "arTitle": "\u0623\u0631\u0632\u0646", "arTitleOther": "\u0623\u0631\u0632\u0646", "lat": "37.97890", "lon": "41.65964", "region": "Aqur", "searchNames": "Arzan", "topType": "villages", "topTypeAlt": "localite", "topURI": "ARZAN_416E379N_S_AQUR", "translitTitle": "Arzan", "translitTitleOther": "Arzan"}, "type": "Feature"}], "type": "FeatureCollection"}