{"features": [{"geometry": {"coordinates": [70.70139, 40.13989], "type": "Point"}, "properties": {"arBW": "Asbara", "arTitle": "\u0623\u0633\u0628\u0631\u0629", "arTitleOther": "\u0623\u0633\u0628\u0631\u0629", "lat": "40.13989", "lon": "70.70139", "region": "Transoxiana", "searchNames": "Asbara", "topType": "villages", "topTypeAlt": "localite", "topURI": "ASBARA_707E401N_S_TRAN", "translitTitle": "Asbara\u0167", "translitTitleOther": "Asbara\u0167"}, "type": "Feature"}], "type": "FeatureCollection"}