{"features": [{"geometry": {"coordinates": [51.18532, 32.13467], "type": "Point"}, "properties": {"arBW": "Asbidh Dasht", "arTitle": "\u0623\u0633\u0628\u064a\u0630 \u062f\u0634\u062a", "arTitleOther": "\u0623\u0633\u0628\u064a\u0630 \u062f\u0634\u062a", "lat": "32.13467", "lon": "51.18532", "region": "Jibal", "searchNames": "Asbidh Dasht", "topType": "waystations", "topTypeAlt": "etape", "topURI": "ASBIDHDASHT_511E321N_S_JIBA", "translitTitle": "Asb\u012b\u1e0f Da\u0161t", "translitTitleOther": "Asb\u012b\u1e0f Da\u0161t"}, "type": "Feature"}], "type": "FeatureCollection"}