{"features": [{"geometry": {"coordinates": [34.55455, 31.66572], "type": "Point"}, "properties": {"arBW": "Asqalan", "arTitle": "\u0639\u0633\u0642\u0644\u0627\u0646", "arTitleOther": "\u0639\u0633\u0642\u0644\u0627\u0646", "lat": "31.66572", "lon": "34.55455", "region": "Sham", "searchNames": "Asqalan", "topType": "towns", "topTypeAlt": "cite/port", "topURI": "ASQALAN_345E316N_S_SHAM", "translitTitle": "\u02bfAsqal\u0101n", "translitTitleOther": "\u02bfAsqal\u0101n"}, "type": "Feature"}], "type": "FeatureCollection"}