{"features": [{"geometry": {"coordinates": [32.87999, 25.01203], "type": "Point"}, "properties": {"arBW": "Atfu", "arTitle": "\u0623\u062a\u0641\u0648", "arTitleOther": "\u0623\u062a\u0641\u0648", "lat": "25.01203", "lon": "32.87999", "region": "Egypt", "searchNames": "Atfu", "topType": "regions", "topTypeAlt": "district", "topURI": "ATFU_328E250N_R_EGYP", "translitTitle": "Atf\u016b", "translitTitleOther": "Atf\u016b"}, "type": "Feature"}], "type": "FeatureCollection"}