{"features": [{"geometry": {"coordinates": [66.5255, 39.82347], "type": "Point"}, "properties": {"arBW": "Awfar", "arTitle": "\u0623\u0648\u0641\u0631", "arTitleOther": "\u0623\u0648\u0641\u0631", "lat": "39.82347", "lon": "66.52550", "region": "Transoxiana", "searchNames": "Awfar", "topType": "regions", "topTypeAlt": "region", "topURI": "AWFAR_665E398N_R_TRAN", "translitTitle": "Awfar", "translitTitleOther": "Awfar"}, "type": "Feature"}], "type": "FeatureCollection"}