{"features": [{"geometry": {"coordinates": [36.92899, 31.64055], "type": "Point"}, "properties": {"arBW": "al-Awnid", "arTitle": "\ufb50\u0644\u0639\u0648\u0646\u064a\u062f", "arTitleOther": "\ufb50\u0644\u0639\u0648\u0646\u064a\u062f", "lat": "31.64055", "lon": "36.92899", "region": "Badiyat al-Arab", "searchNames": "al-Awnid", "topType": "waystations", "topTypeAlt": "etape", "topURI": "AWNID_369E316N_S_BADI", "translitTitle": "al-\u02bfAwn\u012bd", "translitTitleOther": "al-\u02bfAwn\u012bd"}, "type": "Feature"}], "type": "FeatureCollection"}