{"features": [{"geometry": {"coordinates": [44.07861, 25.98495], "type": "Point"}, "properties": {"arBW": "al-Awsaja", "arTitle": "\ufb50\u0644\u0639\u0648\u0633\u062c\u0629", "arTitleOther": "\ufb50\u0644\u0639\u0648\u0633\u062c\u0629", "lat": "25.98495", "lon": "44.07861", "region": "Jazirat al-Arab", "searchNames": "al-Awsaja", "topType": "waystations", "topTypeAlt": "etape", "topURI": "AWSAJA_440E259N_S_JAZI", "translitTitle": "al-\u02bfAwsa\u01e7a\u0167", "translitTitleOther": "al-\u02bfAwsa\u01e7a\u0167"}, "type": "Feature"}], "type": "FeatureCollection"}