{"features": [{"geometry": {"coordinates": [34.66817, 31.79837], "type": "Point"}, "properties": {"arBW": "Azdud, Yazdud", "arTitle": "\u0623\u0632\u062f\u0648\u062f", "arTitleOther": "\u0623\u0632\u062f\u0648\u062f\u060c \u064a\u0632\u062f\u0648\u062f", "lat": "31.79837", "lon": "34.66817", "region": "Sham", "searchNames": "Azdud, Yazdud", "topType": "waystations", "topTypeAlt": "ribat", "topURI": "AZDUD_346E317N_S_SHAM", "translitTitle": "Azd\u016bd", "translitTitleOther": "Azd\u016bd, Yazd\u016bd"}, "type": "Feature"}], "type": "FeatureCollection"}