{"features": [{"geometry": {"coordinates": [62.4787, 34.94152], "type": "Point"}, "properties": {"arBW": "Babna", "arTitle": "\u0628\u0628\u0646\u0629", "arTitleOther": "\u0628\u0628\u0646\u0629", "lat": "34.94152", "lon": "62.47870", "region": "Khurasan", "searchNames": "Babna", "topType": "towns", "topTypeAlt": "cite", "topURI": "BABNA_624E349N_S_KHUR", "translitTitle": "Babna\u0167", "translitTitleOther": "Babna\u0167"}, "type": "Feature"}], "type": "FeatureCollection"}