{"features": [{"geometry": {"coordinates": [30.52845, 30.89835], "type": "Point"}, "properties": {"arBW": "al-Badaqun", "arTitle": "\ufb50\u0644\u0628\u062f\u0642\u0648\u0646", "arTitleOther": "\ufb50\u0644\u0628\u062f\u0642\u0648\u0646", "lat": "30.89835", "lon": "30.52845", "region": "Egypt", "searchNames": "al-Badaqun", "topType": "regions", "topTypeAlt": "region", "topURI": "BADAQUN_305E308N_R_EGYP", "translitTitle": "al-Badaq\u016bn", "translitTitleOther": "al-Badaq\u016bn"}, "type": "Feature"}], "type": "FeatureCollection"}