{"features": [{"geometry": {"coordinates": [70.79525, 37.59609], "type": "Point"}, "properties": {"arBW": "Badhakhshan", "arTitle": "\u0628\u0630\u062e\u0634\u0627\u0646", "arTitleOther": "\u0628\u0630\u062e\u0634\u0627\u0646", "lat": "37.59609", "lon": "70.79525", "region": "Khurasan", "searchNames": "Badhakhshan", "topType": "regions", "topTypeAlt": "region", "topURI": "BADHAKHSHAN_707E375N_R_KHUR", "translitTitle": "Ba\u1e0fa\u1e2b\u0161\u0101n", "translitTitleOther": "Ba\u1e0fa\u1e2b\u0161\u0101n"}, "type": "Feature"}], "type": "FeatureCollection"}