{"features": [{"geometry": {"coordinates": [39.48117, 15.63308], "type": "Point"}, "properties": {"arBW": "Badi", "arTitle": "\u0628\u0627\u0636\u0639", "arTitleOther": "\u0628\u0627\u0636\u0639", "lat": "15.63308", "lon": "39.48117", "region": "Egypt", "searchNames": "Badi", "topType": "towns", "topTypeAlt": "ile/port/cite?", "topURI": "BADI_394E156N_S_EGYP", "translitTitle": "B\u0101\u1e0di\u02bf", "translitTitleOther": "B\u0101\u1e0di\u02bf"}, "type": "Feature"}], "type": "FeatureCollection"}