{"features": [{"geometry": {"coordinates": [30.66449, 28.60073], "type": "Point"}, "properties": {"arBW": "Bahnasa", "arTitle": "\u0628\u0647\u0646\u0633\u0649", "arTitleOther": "\u0628\u0647\u0646\u0633\u0649", "lat": "28.60073", "lon": "30.66449", "region": "Egypt", "searchNames": "Bahnasa", "topType": "regions", "topTypeAlt": "region", "topURI": "BAHNASA_306E286N_R_EGYP", "translitTitle": "Bahnas\u00e1", "translitTitleOther": "Bahnas\u00e1"}, "type": "Feature"}], "type": "FeatureCollection"}