{"features": [{"geometry": {"coordinates": [60.66186, 27.28057], "type": "Point"}, "properties": {"arBW": "al-Bahraj, al-Fahraj, Fahlfahraj", "arTitle": "\ufb50\u0644\u0628\u0647\u0631\u062c", "arTitleOther": "\ufb50\u0644\u0628\u0647\u0631\u062c\u060c \ufb50\u0644\u0641\u0647\u0631\u062c\u060c \u0641\u0647\u0644\u0641\u0647\u0631\u062c", "lat": "27.28057", "lon": "60.66186", "region": "Sind", "searchNames": "al-Bahraj, al-Fahraj, Fahlfahraj", "topType": "towns", "topTypeAlt": "cite", "topURI": "BAHRAJ_606E272N_S_SIND", "translitTitle": "al-Bahra\u01e7", "translitTitleOther": "al-Bahra\u01e7, al-Fahra\u01e7, Fahlfahra\u01e7"}, "type": "Feature"}], "type": "FeatureCollection"}