{"features": [{"geometry": {"coordinates": [31.60503, 19.72554], "type": "Point"}, "properties": {"arBW": "Balad al-Nuba", "arTitle": "\u0628\u0644\u062f \ufb50\u0644\u0646\u0648\u0628\u0629", "arTitleOther": "\u0628\u0644\u062f \ufb50\u0644\u0646\u0648\u0628\u0629", "lat": "19.72554", "lon": "31.60503", "region": "Egypt", "searchNames": "Balad al-Nuba", "topType": "regions", "topTypeAlt": "region", "topURI": "BALADNUBA_316E197N_R_EGYP", "translitTitle": "Balad al-N\u016bba\u0167", "translitTitleOther": "Balad al-N\u016bba\u0167"}, "type": "Feature"}], "type": "FeatureCollection"}