{"features": [{"geometry": {"coordinates": [65.17678, 32.23313], "type": "Point"}, "properties": {"arBW": "Balad Dawar, Bala Dawar, Zamin Dawar", "arTitle": "\u0628\u0644\u062f \u062f\u0627\u0648\u0631", "arTitleOther": "\u0628\u0644\u062f \u062f\u0627\u0648\u0631\u060c \u0628\u0644\u0627 \u062f\u0627\u0648\u0631\u060c \u0632\u0645\u064a\u0646 \u062f\u0627\u0648\u0631", "lat": "32.23313", "lon": "65.17678", "region": "Sijistan", "searchNames": "Balad Dawar, Bala Dawar, Zamin Dawar", "topType": "regions", "topTypeAlt": "region", "topURI": "BALADDAWAR_651E322N_R_SIJI", "translitTitle": "Balad D\u0101war", "translitTitleOther": "Balad D\u0101war, Bal\u0101 D\u0101war, Zam\u012bn D\u0101war"}, "type": "Feature"}], "type": "FeatureCollection"}