{"features": [{"geometry": {"coordinates": [42.7829, 19.20706], "type": "Point"}, "properties": {"arBW": "Banat Jarm, Banat Harm, Banat Harb", "arTitle": "\u0628\u0646\u0627\u062a \u062c\u0631\u0645", "arTitleOther": "\u0628\u0646\u0627\u062a \u062c\u0631\u0645\u060c \u0628\u0646\u0627\u062a \u062d\u0631\u0645\u060c \u0628\u0646\u0627\u062a \u062d\u0631\u0628", "lat": "19.20706", "lon": "42.78290", "region": "Jazirat al-Arab", "searchNames": "Banat Jarm, Banat Harm, Banat Harb", "topType": "sites", "topTypeAlt": "site", "topURI": "BANATJARM_427E192N_O_JAZI", "translitTitle": "Ban\u0101t \u01e6arm", "translitTitleOther": "Ban\u0101t \u01e6arm, Ban\u0101t \u1e24arm, Ban\u0101t \u1e24arb"}, "type": "Feature"}], "type": "FeatureCollection"}