{"features": [{"geometry": {"coordinates": [56.97011, 34.42374], "type": "Point"}, "properties": {"arBW": "Banna, Bunn", "arTitle": "\u0628\u0646\u0629", "arTitleOther": "\u0628\u0646\u0629\u060c \u0628\u0646", "lat": "34.42374", "lon": "56.97011", "region": "Mafaza", "searchNames": "Banna, Bunn", "topType": "waystations", "topTypeAlt": "etape", "topURI": "BANNA_569E344N_S_MAFA", "translitTitle": "Banna\u0167", "translitTitleOther": "Banna\u0167, Bunn"}, "type": "Feature"}], "type": "FeatureCollection"}