{"features": [{"geometry": {"coordinates": [36.54442, 35.6843], "type": "Point"}, "properties": {"arBW": "al-Bara", "arTitle": "\ufb50\u0644\u0628\u0627\u0631\u0629", "arTitleOther": "\ufb50\u0644\u0628\u0627\u0631\u0629", "lat": "35.68430", "lon": "36.54442", "region": "Sham", "searchNames": "al-Bara", "topType": "villages", "topTypeAlt": "localite", "topURI": "BARA_365E356N_S_SHAM", "translitTitle": "al-B\u0101ra\u0167", "translitTitleOther": "al-B\u0101ra\u0167"}, "type": "Feature"}], "type": "FeatureCollection"}