{"features": [{"geometry": {"coordinates": [57.10475, 30.30962], "type": "Point"}, "properties": {"arBW": "Bardasir, Bardashir, Kuwashir", "arTitle": "\u0628\u0631\u062f\u0633\u064a\u0631", "arTitleOther": "\u0628\u0631\u062f\u0633\u064a\u0631\u060c \u0628\u0631\u062f\u0634\u064a\u0631\u060c \u0643\u0648\u0634\u064a\u0631", "lat": "30.30962", "lon": "57.10475", "region": "Kirman", "searchNames": "Bardasir, Bardashir, Kuwashir", "topType": "regions", "topTypeAlt": "circon", "topURI": "BARDASIR_571E303N_R_KIRM", "translitTitle": "Bardas\u012br", "translitTitleOther": "Bardas\u012br, Barda\u0161\u012br, Kuwa\u0161\u012br"}, "type": "Feature"}], "type": "FeatureCollection"}