{"features": [{"geometry": {"coordinates": [43.57361, 35.07982], "type": "Point"}, "properties": {"arBW": "Barimma", "arTitle": "\u0628\u0627\u0631\u0645\u0627", "arTitleOther": "\u0628\u0627\u0631\u0645\u0627", "lat": "35.07982", "lon": "43.57361", "region": "Iraq", "searchNames": "Barimma", "topType": "waystations", "topTypeAlt": "etape", "topURI": "BARIMMA_435E350N_S_IRAQ", "translitTitle": "B\u0101rimm\u0101", "translitTitleOther": "B\u0101rimm\u0101"}, "type": "Feature"}], "type": "FeatureCollection"}