{"features": [{"geometry": {"coordinates": [11.63847, 33.05675], "type": "Point"}, "properties": {"arBW": "Barjamt, Abar Dakht", "arTitle": "\u0628\u0627\u0631\u062c\u0645\u062a", "arTitleOther": "\u0628\u0627\u0631\u062c\u0645\u062a\u060c \u0623\u0628\u0627\u0631 \u062f\u062e\u062a", "lat": "33.05675", "lon": "11.63847", "region": "Barqa", "searchNames": "Barjamt, Abar Dakht", "topType": "waystations", "topTypeAlt": "etape", "topURI": "BARJAMT_116E330N_S_BARQ", "translitTitle": "B\u0101r\u01e7amt", "translitTitleOther": "B\u0101r\u01e7amt, Ab\u0101r Da\u1e2bt"}, "type": "Feature"}], "type": "FeatureCollection"}