{"features": [{"geometry": {"coordinates": [43.75682, 38.98412], "type": "Point"}, "properties": {"arBW": "Barkari, Barkawi", "arTitle": "\u0628\u0631\u0643\u0631\u064a", "arTitleOther": "\u0628\u0631\u0643\u0631\u064a\u060c \u0628\u0631\u0643\u0648\u064a", "lat": "38.98412", "lon": "43.75682", "region": "Rihab", "searchNames": "Barkari, Barkawi", "topType": "towns", "topTypeAlt": "cite", "topURI": "BARKARI_437E389N_S_RIHA", "translitTitle": "Barkar\u012b", "translitTitleOther": "Barkar\u012b, Barkaw\u012b"}, "type": "Feature"}], "type": "FeatureCollection"}