{"features": [{"geometry": {"coordinates": [20.84475, 32.37576], "type": "Point"}, "properties": {"arBW": "Barqa", "arTitle": "\u0628\u0631\u0642\u0629", "arTitleOther": "\u0628\u0631\u0642\u0629", "lat": "32.37576", "lon": "20.84475", "region": "Barqa", "searchNames": "Barqa", "topType": "capitals", "topTypeAlt": "capitale", "topURI": "BARQA_208E323N_S_BARQ", "translitTitle": "Barqa\u0167", "translitTitleOther": "Barqa\u0167"}, "type": "Feature"}], "type": "FeatureCollection"}