{"features": [{"geometry": {"coordinates": [30.29934, 31.08146], "type": "Point"}, "properties": {"arBW": "Barsiq", "arTitle": "\u0628\u0631\u0633\u064a\u0642", "arTitleOther": "\u0628\u0631\u0633\u064a\u0642", "lat": "31.08146", "lon": "30.29934", "region": "Egypt", "searchNames": "Barsiq", "topType": "towns", "topTypeAlt": "cite", "topURI": "BARSIQ_302E310N_S_EGYP", "translitTitle": "Bars\u012bq", "translitTitleOther": "Bars\u012bq"}, "type": "Feature"}], "type": "FeatureCollection"}