{"features": [{"geometry": {"coordinates": [69.25887, 35.17084], "type": "Point"}, "properties": {"arBW": "Barwan, Farwan", "arTitle": "\u0628\u0631\u0648\u0627\u0646", "arTitleOther": "\u0628\u0631\u0648\u0627\u0646\u060c \u0641\u0631\u0648\u0627\u0646", "lat": "35.17084", "lon": "69.25887", "region": "Khurasan", "searchNames": "Barwan, Farwan", "topType": "towns", "topTypeAlt": "canton", "topURI": "BARWAN_692E351N_S_KHUR", "translitTitle": "Barw\u0101n", "translitTitleOther": "Barw\u0101n, Farw\u0101n"}, "type": "Feature"}], "type": "FeatureCollection"}