{"features": [{"geometry": {"coordinates": [48.55981, 37.57057], "type": "Point"}, "properties": {"arBW": "Barwan", "arTitle": "\u0628\u0631\u0648\u0627\u0646", "arTitleOther": "\u0628\u0631\u0648\u0627\u0646", "lat": "37.57057", "lon": "48.55981", "region": "Daylam", "searchNames": "Barwan", "topType": "towns", "topTypeAlt": "cite", "topURI": "BARWAN_485E375N_S_DAYL", "translitTitle": "Barw\u0101n", "translitTitleOther": "Barw\u0101n"}, "type": "Feature"}], "type": "FeatureCollection"}