{"features": [{"geometry": {"coordinates": [48.77033, 30.65916], "type": "Point"}, "properties": {"arBW": "Basiyan", "arTitle": "\u0628\u0627\u0633\u064a\u0627\u0646", "arTitleOther": "\u0628\u0627\u0633\u064a\u0627\u0646", "lat": "30.65916", "lon": "48.77033", "region": "Khuzistan", "searchNames": "Basiyan", "topType": "towns", "topTypeAlt": "cite", "topURI": "BASIYAN_487E306N_S_KHUZ", "translitTitle": "B\u0101siy\u0101n", "translitTitleOther": "B\u0101siy\u0101n"}, "type": "Feature"}], "type": "FeatureCollection"}