{"features": [{"geometry": {"coordinates": [-6.99606, 38.835], "type": "Point"}, "properties": {"arBW": "Batalyus, Batalyuth", "arTitle": "\u0628\u0637\u0644\u064a\u0648\u0633", "arTitleOther": "\u0628\u0637\u0644\u064a\u0648\u0633\u060c \u0628\u0637\u0644\u064a\u0648\u062b", "lat": "38.83500", "lon": "-6.99606", "region": "Andalus", "searchNames": "Batalyus, Batalyuth", "topType": "regions", "topTypeAlt": "region", "topURI": "BATALYUS_069W388N_R_ANDA", "translitTitle": "Ba\u1e6daly\u016bs", "translitTitleOther": "Ba\u1e6daly\u016bs, Ba\u1e6daly\u016b\u1e6f"}, "type": "Feature"}], "type": "FeatureCollection"}