{"features": [{"geometry": {"coordinates": [39.73935, 21.64499], "type": "Point"}, "properties": {"arBW": "Batn Marr", "arTitle": "\u0628\u0637\u0646 \u0645\u0631", "arTitleOther": "\u0628\u0637\u0646 \u0645\u0631", "lat": "21.64499", "lon": "39.73935", "region": "Jazirat al-Arab", "searchNames": "Batn Marr", "topType": "villages", "topTypeAlt": "localite", "topURI": "BATNMARR_397E216N_S_JAZI", "translitTitle": "Ba\u1e6dn Marr", "translitTitleOther": "Ba\u1e6dn Marr"}, "type": "Feature"}], "type": "FeatureCollection"}