{"features": [{"geometry": {"coordinates": [0.57785, 41.83632], "type": "Point"}, "properties": {"arBW": "al-Bayda", "arTitle": "\ufb50\u0644\u0628\u064a\u0636\u0627\u0621", "arTitleOther": "\ufb50\u0644\u0628\u064a\u0636\u0627\u0621", "lat": "41.83632", "lon": "0.57785", "region": "Andalus", "searchNames": "al-Bayda", "topType": "towns", "topTypeAlt": "cite", "topURI": "BAYDA_005E418N_S_ANDA", "translitTitle": "al-Bay\u1e0d\u0101\u02be", "translitTitleOther": "al-Bay\u1e0d\u0101\u02be"}, "type": "Feature"}], "type": "FeatureCollection"}