{"features": [{"geometry": {"coordinates": [52.36712, 30.03958], "type": "Point"}, "properties": {"arBW": "al-Bayda, Nasa", "arTitle": "\ufb50\u0644\u0628\u064a\u0636\u0627\u0621", "arTitleOther": "\ufb50\u0644\u0628\u064a\u0636\u0627\u0621\u060c \u0646\u0633\u0627", "lat": "30.03958", "lon": "52.36712", "region": "Faris", "searchNames": "al-Bayda, Nasa", "topType": "towns", "topTypeAlt": "cite", "topURI": "BAYDA_523E300N_S_FARI", "translitTitle": "al-Bay\u1e0d\u0101\u02be", "translitTitleOther": "al-Bay\u1e0d\u0101\u02be, Nas\u0101"}, "type": "Feature"}], "type": "FeatureCollection"}