{"features": [{"geometry": {"coordinates": [-4.20406, 37.45788], "type": "Point"}, "properties": {"arBW": "Bayghu", "arTitle": "\u0628\u064a\u063a\u0648", "arTitleOther": "\u0628\u064a\u063a\u0648", "lat": "37.45788", "lon": "-4.20406", "region": "Andalus", "searchNames": "Bayghu", "topType": "towns", "topTypeAlt": "cite", "topURI": "BAYGHU_042W374N_S_ANDA", "translitTitle": "Bay\u0121\u016b", "translitTitleOther": "Bay\u0121\u016b"}, "type": "Feature"}], "type": "FeatureCollection"}