{"features": [{"geometry": {"coordinates": [42.53617, 17.37689], "type": "Point"}, "properties": {"arBW": "Baysh", "arTitle": "\u0628\u064a\u0634", "arTitleOther": "\u0628\u064a\u0634", "lat": "17.37689", "lon": "42.53617", "region": "Yemen", "searchNames": "Baysh", "topType": "towns", "topTypeAlt": "cite", "topURI": "BAYSH_425E173N_S_YEME", "translitTitle": "Bay\u0161", "translitTitleOther": "Bay\u0161"}, "type": "Feature"}], "type": "FeatureCollection"}