{"features": [{"geometry": {"coordinates": [35.49256, 32.5], "type": "Point"}, "properties": {"arBW": "Baysan", "arTitle": "\u0628\u064a\u0633\u0627\u0646", "arTitleOther": "\u0628\u064a\u0633\u0627\u0646", "lat": "32.50000", "lon": "35.49256", "region": "Sham", "searchNames": "Baysan", "topType": "towns", "topTypeAlt": "cite", "topURI": "BAYSAN_354E325N_S_SHAM", "translitTitle": "Bays\u0101n", "translitTitleOther": "Bays\u0101n"}, "type": "Feature"}], "type": "FeatureCollection"}