{"features": [{"geometry": {"coordinates": [-3.45773, 37.9998], "type": "Point"}, "properties": {"arBW": "Bayyasa", "arTitle": "\u0628\u064a\u0627\u0633\u0629", "arTitleOther": "\u0628\u064a\u0627\u0633\u0629", "lat": "37.99980", "lon": "-3.45773", "region": "Andalus", "searchNames": "Bayyasa", "topType": "towns", "topTypeAlt": "cite", "topURI": "BAYYASA_034W379N_S_ANDA", "translitTitle": "Bayy\u0101sa\u0167", "translitTitleOther": "Bayy\u0101sa\u0167"}, "type": "Feature"}], "type": "FeatureCollection"}