{"features": [{"geometry": {"coordinates": [65.29357, 39.2921], "type": "Point"}, "properties": {"arBW": "Bir al-Said", "arTitle": "\u0628\u0626\u0631 \ufb50\u0644\u0633\u0639\u064a\u062f", "arTitleOther": "\u0628\u0626\u0631 \ufb50\u0644\u0633\u0639\u064a\u062f", "lat": "39.29210", "lon": "65.29357", "region": "Transoxiana", "searchNames": "Bir al-Said", "topType": "waystations", "topTypeAlt": "etape", "topURI": "BIRSAID_652E392N_S_TRAN", "translitTitle": "Bi\u02ber al-Sa\u02bf\u012bd", "translitTitleOther": "Bi\u02ber al-Sa\u02bf\u012bd"}, "type": "Feature"}], "type": "FeatureCollection"}