{"features": [{"geometry": {"coordinates": [30.78887, 30.62076], "type": "Point"}, "properties": {"arBW": "Bistama", "arTitle": "\u0628\u0633\u062a\u0627\u0645\u0629", "arTitleOther": "\u0628\u0633\u062a\u0627\u0645\u0629", "lat": "30.62076", "lon": "30.78887", "region": "Egypt", "searchNames": "Bistama", "topType": "towns", "topTypeAlt": "cite", "topURI": "BISTAMA_307E306N_S_EGYP", "translitTitle": "Bist\u0101ma\u0167", "translitTitleOther": "Bist\u0101ma\u0167"}, "type": "Feature"}], "type": "FeatureCollection"}