{"features": [{"geometry": {"coordinates": [52.68133, 28.69894], "type": "Point"}, "properties": {"arBW": "Biyabshurab, Dasht Shurab", "arTitle": "\u0628\u064a\u0627\u0628\u0634\u0648\u0631\u0627\u0628", "arTitleOther": "\u0628\u064a\u0627\u0628\u0634\u0648\u0631\u0627\u0628\u060c \u062f\u0634\u062a \u0634\u0648\u0631\u0627\u0628", "lat": "28.69894", "lon": "52.68133", "region": "Faris", "searchNames": "Biyabshurab, Dasht Shurab", "topType": "waystations", "topTypeAlt": "etape", "topURI": "BIYABSHURAB_526E286N_S_FARI", "translitTitle": "Biy\u0101b\u0161\u016br\u0101b", "translitTitleOther": "Biy\u0101b\u0161\u016br\u0101b, Da\u0161t \u0160\u016br\u0101b"}, "type": "Feature"}], "type": "FeatureCollection"}