{"features": [{"geometry": {"coordinates": [55.86992, 36.05824], "type": "Point"}, "properties": {"arBW": "Biyar", "arTitle": "\u0628\u064a\u0627\u0631", "arTitleOther": "\u0628\u064a\u0627\u0631", "lat": "36.05824", "lon": "55.86992", "region": "Daylam", "searchNames": "Biyar", "topType": "towns", "topTypeAlt": "cite", "topURI": "BIYAR_558E360N_S_DAYL", "translitTitle": "Biy\u0101r", "translitTitleOther": "Biy\u0101r"}, "type": "Feature"}], "type": "FeatureCollection"}