{"features": [{"geometry": {"coordinates": [30.80708, 31.4596], "type": "Point"}, "properties": {"arBW": "Buhayra al-Burullus", "arTitle": "\u0628\u062d\u064a\u0631\u0629 \ufb50\u0644\u0628\u0631\u0644\u0633", "arTitleOther": "\u0628\u062d\u064a\u0631\u0629 \ufb50\u0644\u0628\u0631\u0644\u0633", "lat": "31.45960", "lon": "30.80708", "region": "Egypt", "searchNames": "Buhayra al-Burullus", "topType": "waters", "topTypeAlt": "lac", "topURI": "BUHAYRABURULLUS_308E314N_W_EGYP", "translitTitle": "Bu\u1e25ayra\u0167 al-Burullus", "translitTitleOther": "Bu\u1e25ayra\u0167 al-Burullus"}, "type": "Feature"}], "type": "FeatureCollection"}