{"features": [{"geometry": {"coordinates": [-6.48719, 34.55645], "type": "Point"}, "properties": {"arBW": "Buhayra Aryagh, Buhayra al-Righa", "arTitle": "\u0628\u062d\u064a\u0631\u0629 \u0623\u0631\u064a\u0627\u063a", "arTitleOther": "\u0628\u062d\u064a\u0631\u0629 \u0623\u0631\u064a\u0627\u063a\u060c \u0628\u062d\u064a\u0631\u0629 \ufb50\u0644\u0631\u063a\u0629", "lat": "34.55645", "lon": "-6.48719", "region": "Maghrib", "searchNames": "Buhayra Aryagh, Buhayra al-Righa", "topType": "waters", "topTypeAlt": "lac", "topURI": "BUHAYRAARYAGH_064W345N_W_MAGH", "translitTitle": "Bu\u1e25ayra\u0167 Ary\u0101\u0121", "translitTitleOther": "Bu\u1e25ayra\u0167 Ary\u0101\u0121, Bu\u1e25ayra\u0167 al-Ri\u0121a\u0167"}, "type": "Feature"}], "type": "FeatureCollection"}