{"features": [{"geometry": {"coordinates": [61.23634, 31.47449], "type": "Point"}, "properties": {"arBW": "Buhayra Zarah, Buhayra al-Sant", "arTitle": "\u0628\u062d\u064a\u0631\u0629 \u0632\u0631\u0647", "arTitleOther": "\u0628\u062d\u064a\u0631\u0629 \u0632\u0631\u0647\u060c \u0628\u062d\u064a\u0631\u0629 \ufb50\u0644\u0635\u0646\u0637", "lat": "31.47449", "lon": "61.23634", "region": "Sijistan", "searchNames": "Buhayra Zarah, Buhayra al-Sant", "topType": "waters", "topTypeAlt": "lac", "topURI": "BUHAYRAZARAH_612E314N_W_SIJI", "translitTitle": "Bu\u1e25ayra\u0167 Zarah", "translitTitleOther": "Bu\u1e25ayra\u0167 Zarah, Bu\u1e25ayra\u0167 al-\u1e62an\u1e6d"}, "type": "Feature"}], "type": "FeatureCollection"}