{"features": [{"geometry": {"coordinates": [51.67468, 32.78618], "type": "Point"}, "properties": {"arBW": "Burkhuwar", "arTitle": "\u0628\u0631\u062e\u0648\u0627\u0631", "arTitleOther": "\u0628\u0631\u062e\u0648\u0627\u0631", "lat": "32.78618", "lon": "51.67468", "region": "Jibal", "searchNames": "Burkhuwar", "topType": "regions", "topTypeAlt": "region", "topURI": "BURKHUWAR_516E327N_R_JIBA", "translitTitle": "Bur\u1e2buw\u0101r", "translitTitleOther": "Bur\u1e2buw\u0101r"}, "type": "Feature"}], "type": "FeatureCollection"}