{"features": [{"geometry": {"coordinates": [40.07137, 15.69528], "type": "Point"}, "properties": {"arBW": "Dahlak", "arTitle": "\u062f\u0647\u0644\u0643", "arTitleOther": "\u062f\u0647\u0644\u0643", "lat": "15.69528", "lon": "40.07137", "region": "Jazirat al-Arab", "searchNames": "Dahlak", "topType": "regions", "topTypeAlt": "ile", "topURI": "DAHLAK_400E156N_R_JAZI", "translitTitle": "Dahlak", "translitTitleOther": "Dahlak"}, "type": "Feature"}], "type": "FeatureCollection"}