{"features": [{"geometry": {"coordinates": [30.45872, 31.03855], "type": "Point"}, "properties": {"arBW": "Damanhur", "arTitle": "\u062f\u0645\u0646\u0647\u0648\u0631", "arTitleOther": "\u062f\u0645\u0646\u0647\u0648\u0631", "lat": "31.03855", "lon": "30.45872", "region": "Egypt", "searchNames": "Damanhur", "topType": "towns", "topTypeAlt": "cite", "topURI": "DAMANHUR_304E310N_S_EGYP", "translitTitle": "Damanh\u016br", "translitTitleOther": "Damanh\u016br"}, "type": "Feature"}], "type": "FeatureCollection"}