{"features": [{"geometry": {"coordinates": [48.7573, 33.44757], "type": "Point"}, "properties": {"arBW": "Daraqan", "arTitle": "\u062f\u0627\u0631\u0642\u0627\u0646", "arTitleOther": "\u062f\u0627\u0631\u0642\u0627\u0646", "lat": "33.44757", "lon": "48.75730", "region": "Jibal", "searchNames": "Daraqan", "topType": "waystations", "topTypeAlt": "etape", "topURI": "DARAQAN_487E334N_S_JIBA", "translitTitle": "D\u0101raq\u0101n", "translitTitleOther": "D\u0101raq\u0101n"}, "type": "Feature"}], "type": "FeatureCollection"}