{"features": [{"geometry": {"coordinates": [51.54129, 29.66188], "type": "Point"}, "properties": {"arBW": "Dariz", "arTitle": "\u062f\u0631\u064a\u0632", "arTitleOther": "\u062f\u0631\u064a\u0632", "lat": "29.66188", "lon": "51.54129", "region": "Faris", "searchNames": "Dariz", "topType": "towns", "topTypeAlt": "cite", "topURI": "DARIZ_515E296N_S_FARI", "translitTitle": "Dar\u012bz", "translitTitleOther": "Dar\u012bz"}, "type": "Feature"}], "type": "FeatureCollection"}