{"features": [{"geometry": {"coordinates": [45.89739, 13.81354], "type": "Point"}, "properties": {"arBW": "Dathina", "arTitle": "\u062f\u062b\u064a\u0646\u0629", "arTitleOther": "\u062f\u062b\u064a\u0646\u0629", "lat": "13.81354", "lon": "45.89739", "region": "Yemen", "searchNames": "Dathina", "topType": "regions", "topTypeAlt": "region", "topURI": "DATHINA_458E138N_R_YEME", "translitTitle": "Da\u1e6f\u012bna\u0167", "translitTitleOther": "Da\u1e6f\u012bna\u0167"}, "type": "Feature"}], "type": "FeatureCollection"}