{"features": [{"geometry": {"coordinates": [40.42853, 21.62677], "type": "Point"}, "properties": {"arBW": "Dhat Irq", "arTitle": "\u0630\u0627\u062a \u0639\u0631\u0642", "arTitleOther": "\u0630\u0627\u062a \u0639\u0631\u0642", "lat": "21.62677", "lon": "40.42853", "region": "Jazirat al-Arab", "searchNames": "Dhat Irq", "topType": "villages", "topTypeAlt": "localite", "topURI": "DHATIRQ_404E216N_S_JAZI", "translitTitle": "\u1e0e\u0101t \u02bfIrq", "translitTitleOther": "\u1e0e\u0101t \u02bfIrq"}, "type": "Feature"}], "type": "FeatureCollection"}