{"features": [{"geometry": {"coordinates": [44.10309, 13.23247], "type": "Point"}, "properties": {"arBW": "Dhubhan", "arTitle": "\u0630\u0628\u062d\u0627\u0646", "arTitleOther": "\u0630\u0628\u062d\u0627\u0646", "lat": "13.23247", "lon": "44.10309", "region": "Yemen", "searchNames": "Dhubhan", "topType": "regions", "topTypeAlt": "region", "topURI": "DHUBHAN_441E132N_R_YEME", "translitTitle": "\u1e0eub\u1e25\u0101n", "translitTitleOther": "\u1e0eub\u1e25\u0101n"}, "type": "Feature"}], "type": "FeatureCollection"}