{"features": [{"geometry": {"coordinates": [55.70689, 30.31412], "type": "Point"}, "properties": {"arBW": "Dih Ushturan, Qarya al-Jimal", "arTitle": "\u062f\u0647 \u0623\u0634\u062a\u0631\u0627\u0646", "arTitleOther": "\u062f\u0647 \u0623\u0634\u062a\u0631\u0627\u0646\u060c \u0642\u0631\u064a\u0629 \ufb50\u0644\u062c\u0645\u0627\u0644", "lat": "30.31412", "lon": "55.70689", "region": "Faris", "searchNames": "Dih Ushturan, Qarya al-Jimal", "topType": "towns", "topTypeAlt": "cite", "topURI": "DIHUSHTURAN_557E303N_S_FARI", "translitTitle": "Dih U\u0161tur\u0101n", "translitTitleOther": "Dih U\u0161tur\u0101n, Qarya\u0167 al-\u01e6im\u0101l"}, "type": "Feature"}], "type": "FeatureCollection"}