{"features": [{"geometry": {"coordinates": [30.73756, 18.04347], "type": "Point"}, "properties": {"arBW": "Dunqala, Dunqula, Dumqula", "arTitle": "\u062f\u0646\u0642\u0644\u0629", "arTitleOther": "\u062f\u0646\u0642\u0644\u0629\u060c \u062f\u0646\u0642\u0644\u0629\u060c \u062f\u0645\u0642\u0644\u0629", "lat": "18.04347", "lon": "30.73756", "region": "Egypt", "searchNames": "Dunqala, Dunqula, Dumqula", "topType": "towns", "topTypeAlt": "cite", "topURI": "DUNQALA_307E180N_S_EGYP", "translitTitle": "Dunqala\u0167", "translitTitleOther": "Dunqala\u0167, Dunqula\u0167, Dumqula\u0167"}, "type": "Feature"}], "type": "FeatureCollection"}