{"features": [{"geometry": {"coordinates": [32.59811, 31.02282], "type": "Point"}, "properties": {"arBW": "al-Farama", "arTitle": "\ufb50\u0644\u0641\u0631\u0645\u0627", "arTitleOther": "\ufb50\u0644\u0641\u0631\u0645\u0627", "lat": "31.02282", "lon": "32.59811", "region": "Egypt", "searchNames": "al-Farama", "topType": "capitals", "topTypeAlt": "capitale", "topURI": "FARAMA_325E310N_S_EGYP", "translitTitle": "al-Faram\u0101", "translitTitleOther": "al-Faram\u0101"}, "type": "Feature"}], "type": "FeatureCollection"}