{"features": [{"geometry": {"coordinates": [62.29575, 37.39749], "type": "Point"}, "properties": {"arBW": "Faz, Zarq", "arTitle": "\u0641\u0627\u0632", "arTitleOther": "\u0641\u0627\u0632\u060c \u0632\u0631\u0642", "lat": "37.39749", "lon": "62.29575", "region": "Khurasan", "searchNames": "Faz, Zarq", "topType": "villages", "topTypeAlt": "localite", "topURI": "FAZ_622E373N_S_KHUR", "translitTitle": "F\u0101z", "translitTitleOther": "F\u0101z, Zarq"}, "type": "Feature"}], "type": "FeatureCollection"}