{"features": [{"geometry": {"coordinates": [41.28101, 21.44752], "type": "Point"}, "properties": {"arBW": "al-Futuq", "arTitle": "\ufb50\u0644\u0641\u062a\u0642", "arTitleOther": "\ufb50\u0644\u0641\u062a\u0642", "lat": "21.44752", "lon": "41.28101", "region": "Jazirat al-Arab", "searchNames": "al-Futuq", "topType": "waystations", "topTypeAlt": "etape", "topURI": "FUTUQ_412E214N_S_JAZI", "translitTitle": "al-Futuq", "translitTitleOther": "al-Futuq"}, "type": "Feature"}], "type": "FeatureCollection"}