{"features": [{"geometry": {"coordinates": [40.84007, 21.89675], "type": "Point"}, "properties": {"arBW": "al-Ghamra", "arTitle": "\ufb50\u0644\u063a\u0645\u0631\u0629", "arTitleOther": "\ufb50\u0644\u063a\u0645\u0631\u0629", "lat": "21.89675", "lon": "40.84007", "region": "Jazirat al-Arab", "searchNames": "al-Ghamra", "topType": "waystations", "topTypeAlt": "aiguade", "topURI": "GHAMRA_408E218N_S_JAZI", "translitTitle": "al-\u0120amra\u0167", "translitTitleOther": "al-\u0120amra\u0167"}, "type": "Feature"}], "type": "FeatureCollection"}