{"features": [{"geometry": {"coordinates": [56.97972, 29.72844], "type": "Point"}, "properties": {"arBW": "Ghubayra", "arTitle": "\u063a\u0628\u064a\u0631\u0627\u0621", "arTitleOther": "\u063a\u0628\u064a\u0631\u0627\u0621", "lat": "29.72844", "lon": "56.97972", "region": "Kirman", "searchNames": "Ghubayra", "topType": "towns", "topTypeAlt": "cite", "topURI": "GHUBAYRA_569E297N_S_KIRM", "translitTitle": "\u0120ubayr\u0101\u02be", "translitTitleOther": "\u0120ubayr\u0101\u02be"}, "type": "Feature"}], "type": "FeatureCollection"}