{"features": [{"geometry": {"coordinates": [1.09406, 36.11161], "type": "Point"}, "properties": {"arBW": "al-Ghuzza", "arTitle": "\ufb50\u0644\u063a\u0632\u0629", "arTitleOther": "\ufb50\u0644\u063a\u0632\u0629", "lat": "36.11161", "lon": "1.09406", "region": "Maghrib", "searchNames": "al-Ghuzza", "topType": "towns", "topTypeAlt": "cite", "topURI": "GHUZZA_010E361N_S_MAGH", "translitTitle": "al-\u0120uzza\u0167", "translitTitleOther": "al-\u0120uzza\u0167"}, "type": "Feature"}], "type": "FeatureCollection"}