{"features": [{"geometry": {"coordinates": [37.52545, 37.73001], "type": "Point"}, "properties": {"arBW": "al-Hadath", "arTitle": "\ufb50\u0644\u062d\u062f\u062b", "arTitleOther": "\ufb50\u0644\u062d\u062f\u062b", "lat": "37.73001", "lon": "37.52545", "region": "Aqur", "searchNames": "al-Hadath", "topType": "towns", "topTypeAlt": "cite", "topURI": "HADATH_375E377N_S_AQUR", "translitTitle": "al-\u1e24ada\u1e6f", "translitTitleOther": "al-\u1e24ada\u1e6f"}, "type": "Feature"}], "type": "FeatureCollection"}