{"features": [{"geometry": {"coordinates": [42.69628, 35.79513], "type": "Point"}, "properties": {"arBW": "al-Hadr", "arTitle": "\ufb50\u0644\u062d\u0636\u0631", "arTitleOther": "\ufb50\u0644\u062d\u0636\u0631", "lat": "35.79513", "lon": "42.69628", "region": "Aqur", "searchNames": "al-Hadr", "topType": "towns", "topTypeAlt": "cite", "topURI": "HADR_426E357N_S_AQUR", "translitTitle": "al-\u1e24a\u1e0dr", "translitTitleOther": "al-\u1e24a\u1e0dr"}, "type": "Feature"}], "type": "FeatureCollection"}