{"features": [{"geometry": {"coordinates": [42.94727, 16.37831], "type": "Point"}, "properties": {"arBW": "Hakam", "arTitle": "\u062d\u0643\u0645", "arTitleOther": "\u062d\u0643\u0645", "lat": "16.37831", "lon": "42.94727", "region": "Yemen", "searchNames": "Hakam", "topType": "regions", "topTypeAlt": "region", "topURI": "HAKAM_429E163N_R_YEME", "translitTitle": "\u1e24akam", "translitTitleOther": "\u1e24akam"}, "type": "Feature"}], "type": "FeatureCollection"}