{"features": [{"geometry": {"coordinates": [54.41315, 30.11392], "type": "Point"}, "properties": {"arBW": "Hara", "arTitle": "\u0647\u0631\u0627\u0629", "arTitleOther": "\u0647\u0631\u0627\u0629", "lat": "30.11392", "lon": "54.41315", "region": "Faris", "searchNames": "Hara", "topType": "towns", "topTypeAlt": "cite", "topURI": "HARA_544E301N_S_FARI", "translitTitle": "Har\u0101\u0167", "translitTitleOther": "Har\u0101\u0167"}, "type": "Feature"}], "type": "FeatureCollection"}