{"features": [{"geometry": {"coordinates": [67.07594, 37.69255], "type": "Point"}, "properties": {"arBW": "Hashimjird", "arTitle": "\u0647\u0627\u0634\u0645\u062c\u0631\u062f", "arTitleOther": "\u0647\u0627\u0634\u0645\u062c\u0631\u062f", "lat": "37.69255", "lon": "67.07594", "region": "Transoxiana", "searchNames": "Hashimjird", "topType": "towns", "topTypeAlt": "cite", "topURI": "HASHIMJIRD_670E376N_S_TRAN", "translitTitle": "H\u0101\u0161im\u01e7ird", "translitTitleOther": "H\u0101\u0161im\u01e7ird"}, "type": "Feature"}], "type": "FeatureCollection"}