{"features": [{"geometry": {"coordinates": [55.43921, 33.57348], "type": "Point"}, "properties": {"arBW": "Hawd al-Hajib", "arTitle": "\u062d\u0648\u0636 \ufb50\u0644\u062d\u0627\u062c\u0628", "arTitleOther": "\u062d\u0648\u0636 \ufb50\u0644\u062d\u0627\u062c\u0628", "lat": "33.57348", "lon": "55.43921", "region": "Mafaza", "searchNames": "Hawd al-Hajib", "topType": "waystations", "topTypeAlt": "etape", "topURI": "HAWDHAJIB_554E335N_S_MAFA", "translitTitle": "\u1e24aw\u1e0d al-\u1e24\u0101\u01e7ib", "translitTitleOther": "\u1e24aw\u1e0d al-\u1e24\u0101\u01e7ib"}, "type": "Feature"}], "type": "FeatureCollection"}