{"features": [{"geometry": {"coordinates": [61.09517, 41.2861], "type": "Point"}, "properties": {"arBW": "Hazarasb", "arTitle": "\u0647\u0632\u0627\u0631\u0627\u0633\u0628", "arTitleOther": "\u0647\u0632\u0627\u0631\u0627\u0633\u0628", "lat": "41.28610", "lon": "61.09517", "region": "Transoxiana", "searchNames": "Hazarasb", "topType": "towns", "topTypeAlt": "cite", "topURI": "HAZARASB_610E412N_S_TRAN", "translitTitle": "Haz\u0101r\u0101sb", "translitTitleOther": "Haz\u0101r\u0101sb"}, "type": "Feature"}], "type": "FeatureCollection"}