{"features": [{"geometry": {"coordinates": [39.02138, 23.51137], "type": "Point"}, "properties": {"arBW": "al-Hijaz", "arTitle": "\ufb50\u0644\u062d\u062c\u0627\u0632", "arTitleOther": "\ufb50\u0644\u062d\u062c\u0627\u0632", "lat": "23.51137", "lon": "39.02138", "region": "Jazirat al-Arab", "searchNames": "al-Hijaz", "topType": "regions", "topTypeAlt": "region", "topURI": "HIJAZ_390E235N_R_JAZI", "translitTitle": "al-\u1e24i\u01e7\u0101z", "translitTitleOther": "al-\u1e24i\u01e7\u0101z"}, "type": "Feature"}], "type": "FeatureCollection"}