{"features": [{"geometry": {"coordinates": [36.72425, 34.73793], "type": "Point"}, "properties": {"arBW": "Hims", "arTitle": "\u062d\u0645\u0635", "arTitleOther": "\u062d\u0645\u0635", "lat": "34.73793", "lon": "36.72425", "region": "Sham", "searchNames": "Hims", "topType": "capitals", "topTypeAlt": "capitale", "topURI": "HIMS_367E347N_S_SHAM", "translitTitle": "\u1e24im\u1e63", "translitTitleOther": "\u1e24im\u1e63"}, "type": "Feature"}], "type": "FeatureCollection"}