{"features": [{"geometry": {"coordinates": [42.73173, 15.22479], "type": "Point"}, "properties": {"arBW": "al-Hirda", "arTitle": "\ufb50\u0644\u062d\u0631\u062f\u0629", "arTitleOther": "\ufb50\u0644\u062d\u0631\u062f\u0629", "lat": "15.22479", "lon": "42.73173", "region": "Yemen", "searchNames": "al-Hirda", "topType": "towns", "topTypeAlt": "cite", "topURI": "HIRDA_427E152N_S_YEME", "translitTitle": "al-\u1e24irda\u0167", "translitTitleOther": "al-\u1e24irda\u0167"}, "type": "Feature"}], "type": "FeatureCollection"}