{"features": [{"geometry": {"coordinates": [43.29934, 20.06543], "type": "Point"}, "properties": {"arBW": "Hujayra", "arTitle": "\u0647\u062c\u064a\u0631\u0629", "arTitleOther": "\u0647\u062c\u064a\u0631\u0629", "lat": "20.06543", "lon": "43.29934", "region": "Jazirat al-Arab", "searchNames": "Hujayra", "topType": "regions", "topTypeAlt": "region", "topURI": "HUJAYRA_432E200N_R_JAZI", "translitTitle": "Hu\u01e7ayra\u0167", "translitTitleOther": "Hu\u01e7ayra\u0167"}, "type": "Feature"}], "type": "FeatureCollection"}