{"features": [{"geometry": {"coordinates": [44.56313, 13.90626], "type": "Point"}, "properties": {"arBW": "Hujr wa-Badr", "arTitle": "\u0647\u062c\u0631 \u0648\u0628\u062f\u0631", "arTitleOther": "\u0647\u062c\u0631 \u0648\u0628\u062f\u0631", "lat": "13.90626", "lon": "44.56313", "region": "Yemen", "searchNames": "Hujr wa-Badr", "topType": "regions", "topTypeAlt": "region", "topURI": "HUJRWA-BADR_445E139N_R_YEME", "translitTitle": "Hu\u01e7r wa-Badr", "translitTitleOther": "Hu\u01e7r wa-Badr"}, "type": "Feature"}], "type": "FeatureCollection"}