{"features": [{"geometry": {"coordinates": [42.07352, 31.70731], "type": "Point"}, "properties": {"arBW": "al-Husa, al-Jusa", "arTitle": "\ufb50\u0644\u062d\u0633\u0649", "arTitleOther": "\ufb50\u0644\u062d\u0633\u0649\u060c \ufb50\u0644\u062c\u0633\u0649", "lat": "31.70731", "lon": "42.07352", "region": "Badiyat al-Arab", "searchNames": "al-Husa, al-Jusa", "topType": "waystations", "topTypeAlt": "etape", "topURI": "HUSA_420E317N_S_BADI", "translitTitle": "al-\u1e24us\u00e1", "translitTitleOther": "al-\u1e24us\u00e1, al-\u01e6us\u00e1"}, "type": "Feature"}], "type": "FeatureCollection"}