{"features": [{"geometry": {"coordinates": [0.442, 35.55078], "type": "Point"}, "properties": {"arBW": "Huwara", "arTitle": "\u0647\u0648\u0627\u0631\u0629", "arTitleOther": "\u0647\u0648\u0627\u0631\u0629", "lat": "35.55078", "lon": "0.44200", "region": "Maghrib", "searchNames": "Huwara", "topType": "towns", "topTypeAlt": "cite", "topURI": "HUWARA_004E355N_S_MAGH", "translitTitle": "Huw\u0101ra\u0167", "translitTitleOther": "Huw\u0101ra\u0167"}, "type": "Feature"}], "type": "FeatureCollection"}