{"features": [{"geometry": {"coordinates": [51.65, 32.66855], "type": "Point"}, "properties": {"arBW": "Isbahan, Isfahan, al-Yahudiyya", "arTitle": "\u0625\u0635\u0628\u0647\u0627\u0646", "arTitleOther": "\u0625\u0635\u0628\u0647\u0627\u0646\u060c \u0625\u0635\u0641\u0647\u0627\u0646\u060c \ufb50\u0644\u064a\u0647\u0648\u062f\u064a\u0629", "lat": "32.66855", "lon": "51.65000", "region": "Jibal", "searchNames": "Isbahan, Isfahan, al-Yahudiyya", "topType": "capitals", "topTypeAlt": "capitale", "topURI": "ISBAHAN_516E326N_S_JIBA", "translitTitle": "I\u1e63bah\u0101n", "translitTitleOther": "I\u1e63bah\u0101n, I\u1e63fah\u0101n, al-Yah\u016bdiyya\u0167"}, "type": "Feature"}], "type": "FeatureCollection"}