{"features": [{"geometry": {"coordinates": [29.90981, 31.1949], "type": "Point"}, "properties": {"arBW": "al-Iskandariyya", "arTitle": "\ufb50\u0644\u0625\u0633\u0643\u0646\u062f\u0631\u064a\u0629", "arTitleOther": "\ufb50\u0644\u0625\u0633\u0643\u0646\u062f\u0631\u064a\u0629", "lat": "31.19490", "lon": "29.90981", "region": "Egypt", "searchNames": "al-Iskandariyya", "topType": "capitals", "topTypeAlt": "capitale", "topURI": "ISKANDARIYYA_299E311N_S_EGYP", "translitTitle": "al-Iskandariyya\u0167", "translitTitleOther": "al-Iskandariyya\u0167"}, "type": "Feature"}], "type": "FeatureCollection"}