{"features": [{"geometry": {"coordinates": [43.94813, 13.88026], "type": "Point"}, "properties": {"arBW": "Jabal Himyar", "arTitle": "\u062c\u0628\u0644 \u062d\u0645\u064a\u0631", "arTitleOther": "\u062c\u0628\u0644 \u062d\u0645\u064a\u0631", "lat": "13.88026", "lon": "43.94813", "region": "Yemen", "searchNames": "Jabal Himyar", "topType": "sites", "topTypeAlt": "mont", "topURI": "JABALHIMYAR_439E138N_O_YEME", "translitTitle": "\u01e6abal \u1e24imyar", "translitTitleOther": "\u01e6abal \u1e24imyar"}, "type": "Feature"}], "type": "FeatureCollection"}