{"features": [{"geometry": {"coordinates": [36.35891, 34.85533], "type": "Point"}, "properties": {"arBW": "Jabal Jalil", "arTitle": "\u062c\u0628\u0644 \u062c\u0644\u064a\u0644", "arTitleOther": "\u062c\u0628\u0644 \u062c\u0644\u064a\u0644", "lat": "34.85533", "lon": "36.35891", "region": "Sham", "searchNames": "Jabal Jalil", "topType": "sites", "topTypeAlt": "montagne", "topURI": "JABALJALIL_363E348N_O_SHAM", "translitTitle": "\u01e6abal \u01e6al\u012bl", "translitTitleOther": "\u01e6abal \u01e6al\u012bl"}, "type": "Feature"}], "type": "FeatureCollection"}