{"features": [{"geometry": {"coordinates": [39.59145, 24.64886], "type": "Point"}, "properties": {"arBW": "Jabal Uhud", "arTitle": "\u062c\u0628\u0644 \u0623\u062d\u062f", "arTitleOther": "\u062c\u0628\u0644 \u0623\u062d\u062f", "lat": "24.64886", "lon": "39.59145", "region": "Jazirat al-Arab", "searchNames": "Jabal Uhud", "topType": "sites", "topTypeAlt": "mont", "topURI": "JABALUHUD_395E246N_O_JAZI", "translitTitle": "\u01e6abal U\u1e25ud", "translitTitleOther": "\u01e6abal U\u1e25ud"}, "type": "Feature"}], "type": "FeatureCollection"}