{"features": [{"geometry": {"coordinates": [43.72814, 34.62614], "type": "Point"}, "properties": {"arBW": "Jabilta, Jabulta", "arTitle": "\u062c\u0628\u0644\u062a\u0627", "arTitleOther": "\u062c\u0628\u0644\u062a\u0627\u060c \u062c\u0628\u0644\u062a\u0627", "lat": "34.62614", "lon": "43.72814", "region": "Iraq", "searchNames": "Jabilta, Jabulta", "topType": "waystations", "topTypeAlt": "etape", "topURI": "JABILTA_437E346N_S_IRAQ", "translitTitle": "\u01e6abilt\u0101", "translitTitleOther": "\u01e6abilt\u0101, \u01e6abult\u0101"}, "type": "Feature"}], "type": "FeatureCollection"}