{"features": [{"geometry": {"coordinates": [40.41354, 36.65489], "type": "Point"}, "properties": {"arBW": "al-Jahshiyya", "arTitle": "\ufb50\u0644\u062c\u062d\u0634\u064a\u0629", "arTitleOther": "\ufb50\u0644\u062c\u062d\u0634\u064a\u0629", "lat": "36.65489", "lon": "40.41354", "region": "Aqur", "searchNames": "al-Jahshiyya", "topType": "towns", "topTypeAlt": "cite", "topURI": "JAHSHIYYA_404E366N_S_AQUR", "translitTitle": "al-\u01e6a\u1e25\u0161iyya\u0167", "translitTitleOther": "al-\u01e6a\u1e25\u0161iyya\u0167"}, "type": "Feature"}], "type": "FeatureCollection"}