{"features": [{"geometry": {"coordinates": [44.43704, 32.48152], "type": "Point"}, "properties": {"arBW": "al-Jamian, al-Jamiayn", "arTitle": "\ufb50\u0644\u062c\u0627\u0645\u0639\u0627\u0646", "arTitleOther": "\ufb50\u0644\u062c\u0627\u0645\u0639\u0627\u0646\u060c \ufb50\u0644\u062c\u0627\u0645\u0639\u064a\u0646", "lat": "32.48152", "lon": "44.43704", "region": "Iraq", "searchNames": "al-Jamian, al-Jamiayn", "topType": "towns", "topTypeAlt": "cite", "topURI": "JAMIAN_444E324N_S_IRAQ", "translitTitle": "al-\u01e6\u0101mi\u02bf\u0101n", "translitTitleOther": "al-\u01e6\u0101mi\u02bf\u0101n, al-\u01e6\u0101mi\u02bfayn"}, "type": "Feature"}], "type": "FeatureCollection"}