{"features": [{"geometry": {"coordinates": [50.29276, 33.3812], "type": "Point"}, "properties": {"arBW": "Jarbadhaqan, Julbayjan", "arTitle": "\u062c\u0631\u0628\u0627\u0630\u0642\u0627\u0646", "arTitleOther": "\u062c\u0631\u0628\u0627\u0630\u0642\u0627\u0646\u060c \u062c\u0644\u0628\u064a\u062c\u0627\u0646", "lat": "33.38120", "lon": "50.29276", "region": "Jibal", "searchNames": "Jarbadhaqan, Julbayjan", "topType": "waystations", "topTypeAlt": "etape", "topURI": "JARBADHAQAN_502E333N_S_JIBA", "translitTitle": "\u01e6arb\u0101\u1e0faq\u0101n", "translitTitleOther": "\u01e6arb\u0101\u1e0faq\u0101n, \u01e6ulbay\u01e7\u0101n"}, "type": "Feature"}], "type": "FeatureCollection"}