{"features": [{"geometry": {"coordinates": [35.4502, 33.03094], "type": "Point"}, "properties": {"arBW": "al-Jashsh", "arTitle": "\ufb50\u0644\u062c\u0634", "arTitleOther": "\ufb50\u0644\u062c\u0634", "lat": "33.03094", "lon": "35.45020", "region": "Sham", "searchNames": "al-Jashsh", "topType": "villages", "topTypeAlt": "bourgade", "topURI": "JASHSH_354E330N_S_SHAM", "translitTitle": "al-\u01e6a\u0161\u0161", "translitTitleOther": "al-\u01e6a\u0161\u0161"}, "type": "Feature"}], "type": "FeatureCollection"}