{"features": [{"geometry": {"coordinates": [35.79833, 33.09084], "type": "Point"}, "properties": {"arBW": "al-Jawlan", "arTitle": "\ufb50\u0644\u062c\u0648\u0644\u0627\u0646", "arTitleOther": "\ufb50\u0644\u062c\u0648\u0644\u0627\u0646", "lat": "33.09084", "lon": "35.79833", "region": "Sham", "searchNames": "al-Jawlan", "topType": "towns", "topTypeAlt": "canton", "topURI": "JAWLAN_357E330N_S_SHAM", "translitTitle": "al-\u01e6awl\u0101n", "translitTitleOther": "al-\u01e6awl\u0101n"}, "type": "Feature"}], "type": "FeatureCollection"}