{"features": [{"geometry": {"coordinates": [42.55043, 16.89564], "type": "Point"}, "properties": {"arBW": "Jazan", "arTitle": "\u062c\u0627\u0632\u0627\u0646", "arTitleOther": "\u062c\u0627\u0632\u0627\u0646", "lat": "16.89564", "lon": "42.55043", "region": "Yemen", "searchNames": "Jazan", "topType": "towns", "topTypeAlt": "cite", "topURI": "JAZAN_425E168N_S_YEME", "translitTitle": "\u01e6\u0101z\u0101n", "translitTitleOther": "\u01e6\u0101z\u0101n"}, "type": "Feature"}], "type": "FeatureCollection"}