{"features": [{"geometry": {"coordinates": [42.19943, 37.28521], "type": "Point"}, "properties": {"arBW": "Jazira Ibn Umar", "arTitle": "\u062c\u0632\u064a\u0631\u0629 \u0625\u0628\u0646 \u0639\u0645\u0631", "arTitleOther": "\u062c\u0632\u064a\u0631\u0629 \u0625\u0628\u0646 \u0639\u0645\u0631", "lat": "37.28521", "lon": "42.19943", "region": "Aqur", "searchNames": "Jazira Ibn Umar", "topType": "regions", "topTypeAlt": "territoire", "topURI": "JAZIRAIBNUMAR_421E372N_R_AQUR", "translitTitle": "\u01e6az\u012bra\u0167 Ibn \u02bfUmar", "translitTitleOther": "\u01e6az\u012bra\u0167 Ibn \u02bfUmar"}, "type": "Feature"}], "type": "FeatureCollection"}