{"features": [{"geometry": {"coordinates": [-5.33071, 36.16752], "type": "Point"}, "properties": {"arBW": "Jazira Jabal Tariq", "arTitle": "\u062c\u0632\u064a\u0631\u0629 \u062c\u0628\u0644 \u0637\u0627\u0631\u0642", "arTitleOther": "\u062c\u0632\u064a\u0631\u0629 \u062c\u0628\u0644 \u0637\u0627\u0631\u0642", "lat": "36.16752", "lon": "-5.33071", "region": "Andalus", "searchNames": "Jazira Jabal Tariq", "topType": "towns", "topTypeAlt": "cite", "topURI": "JAZIRAJABALTARIQ_053W361N_S_ANDA", "translitTitle": "\u01e6az\u012bra\u0167 \u01e6abal \u1e6c\u0101riq", "translitTitleOther": "\u01e6az\u012bra\u0167 \u01e6abal \u1e6c\u0101riq"}, "type": "Feature"}], "type": "FeatureCollection"}