{"features": [{"geometry": {"coordinates": [41.62102, 36.2374], "type": "Point"}, "properties": {"arBW": "al-Jibal, Ayn al-Jibal", "arTitle": "\ufb50\u0644\u062c\u0628\u0627\u0644", "arTitleOther": "\ufb50\u0644\u062c\u0628\u0627\u0644\u060c \u0639\u064a\u0646 \ufb50\u0644\u062c\u0628\u0627\u0644", "lat": "36.23740", "lon": "41.62102", "region": "Aqur", "searchNames": "al-Jibal, Ayn al-Jibal", "topType": "towns", "topTypeAlt": "cite", "topURI": "JIBAL_416E362N_S_AQUR", "translitTitle": "al-\u01e6ib\u0101l", "translitTitleOther": "al-\u01e6ib\u0101l, \u02bfAyn al-\u01e6ib\u0101l"}, "type": "Feature"}], "type": "FeatureCollection"}