{"features": [{"geometry": {"coordinates": [71.97221, 41.30084], "type": "Point"}, "properties": {"arBW": "Jidghil", "arTitle": "\u062c\u062f\u063a\u0644", "arTitleOther": "\u062c\u062f\u063a\u0644", "lat": "41.30084", "lon": "71.97221", "region": "Transoxiana", "searchNames": "Jidghil", "topType": "regions", "topTypeAlt": "region", "topURI": "JIDGHIL_719E413N_R_TRAN", "translitTitle": "\u01e6id\u0121il", "translitTitleOther": "\u01e6id\u0121il"}, "type": "Feature"}], "type": "FeatureCollection"}