{"features": [{"geometry": {"coordinates": [62.36792, 40.23331], "type": "Point"}, "properties": {"arBW": "Jikarband", "arTitle": "\u062c\u0643\u0631\u0628\u0646\u062f", "arTitleOther": "\u062c\u0643\u0631\u0628\u0646\u062f", "lat": "40.23331", "lon": "62.36792", "region": "Transoxiana", "searchNames": "Jikarband", "topType": "towns", "topTypeAlt": "cite", "topURI": "JIKARBAND_623E402N_S_TRAN", "translitTitle": "\u01e6ikarband", "translitTitleOther": "\u01e6ikarband"}, "type": "Feature"}], "type": "FeatureCollection"}