{"features": [{"geometry": {"coordinates": [44.36973, 32.87594], "type": "Point"}, "properties": {"arBW": "Jisr Kutha", "arTitle": "\u062c\u0633\u0631 \u0643\u0648\u062b\u0649", "arTitleOther": "\u062c\u0633\u0631 \u0643\u0648\u062b\u0649", "lat": "32.87594", "lon": "44.36973", "region": "Iraq", "searchNames": "Jisr Kutha", "topType": "waystations", "topTypeAlt": "etape", "topURI": "JISRKUTHA_443E328N_S_IRAQ", "translitTitle": "\u01e6isr K\u016b\u1e6f\u00e1", "translitTitleOther": "\u01e6isr K\u016b\u1e6f\u00e1"}, "type": "Feature"}], "type": "FeatureCollection"}