{"features": [{"geometry": {"coordinates": [23.96719, 31.99027], "type": "Point"}, "properties": {"arBW": "Jiyad al-Saghir", "arTitle": "\u062c\u064a\u0627\u062f \ufb50\u0644\u0635\u063a\u064a\u0631", "arTitleOther": "\u062c\u064a\u0627\u062f \ufb50\u0644\u0635\u063a\u064a\u0631", "lat": "31.99027", "lon": "23.96719", "region": "Barqa", "searchNames": "Jiyad al-Saghir", "topType": "waystations", "topTypeAlt": "etape", "topURI": "JIYADSAGHIR_239E319N_S_BARQ", "translitTitle": "\u01e6iy\u0101d al-\u1e62a\u0121\u012br", "translitTitleOther": "\u01e6iy\u0101d al-\u1e62a\u0121\u012br"}, "type": "Feature"}], "type": "FeatureCollection"}