{"features": [{"geometry": {"coordinates": [62.3861, 31.9686], "type": "Point"}, "properties": {"arBW": "Jizah, Kizah", "arTitle": "\u062c\u0632\u0647", "arTitleOther": "\u062c\u0632\u0647\u060c \u0643\u0632\u0647", "lat": "31.96860", "lon": "62.38610", "region": "Sijistan", "searchNames": "Jizah, Kizah", "topType": "towns", "topTypeAlt": "cite", "topURI": "JIZAH_623E319N_S_SIJI", "translitTitle": "\u01e6izah", "translitTitleOther": "\u01e6izah, Kizah"}, "type": "Feature"}], "type": "FeatureCollection"}