{"features": [{"geometry": {"coordinates": [56.69972, 36.86045], "type": "Point"}, "properties": {"arBW": "Juwayn, Kuyan", "arTitle": "\u062c\u0648\u064a\u0646", "arTitleOther": "\u062c\u0648\u064a\u0646\u060c \u0643\u0648\u064a\u0627\u0646", "lat": "36.86045", "lon": "56.69972", "region": "Khurasan", "searchNames": "Juwayn, Kuyan", "topType": "regions", "topTypeAlt": "region", "topURI": "JUWAYN_566E368N_R_KHUR", "translitTitle": "\u01e6uwayn", "translitTitleOther": "\u01e6uwayn, K\u016by\u0101n"}, "type": "Feature"}], "type": "FeatureCollection"}