{"features": [{"geometry": {"coordinates": [58.18338, 28.12851], "type": "Point"}, "properties": {"arBW": "Juwi Sulayman", "arTitle": "\u062c\u0648\u064a \u0633\u0644\u064a\u0645\u0627\u0646", "arTitleOther": "\u062c\u0648\u064a \u0633\u0644\u064a\u0645\u0627\u0646", "lat": "28.12851", "lon": "58.18338", "region": "Kirman", "searchNames": "Juwi Sulayman", "topType": "towns", "topTypeAlt": "cite", "topURI": "JUWISULAYMAN_581E281N_S_KIRM", "translitTitle": "\u01e6uw\u012b Sulaym\u0101n", "translitTitleOther": "\u01e6uw\u012b Sulaym\u0101n"}, "type": "Feature"}], "type": "FeatureCollection"}