{"features": [{"geometry": {"coordinates": [66.31581, 37.37958], "type": "Point"}, "properties": {"arBW": "Kalif", "arTitle": "\u0643\u0627\u0644\u0641", "arTitleOther": "\u0643\u0627\u0644\u0641", "lat": "37.37958", "lon": "66.31581", "region": "Transoxiana", "searchNames": "Kalif", "topType": "towns", "topTypeAlt": "cite", "topURI": "KALIF_663E373N_S_TRAN", "translitTitle": "K\u0101lif", "translitTitleOther": "K\u0101lif"}, "type": "Feature"}], "type": "FeatureCollection"}