{"features": [{"geometry": {"coordinates": [44.43153, 33.30144], "type": "Point"}, "properties": {"arBW": "Kalwadha", "arTitle": "\u0643\u0644\u0648\u0627\u0630\u0649", "arTitleOther": "\u0643\u0644\u0648\u0627\u0630\u0649", "lat": "33.30144", "lon": "44.43153", "region": "Iraq", "searchNames": "Kalwadha", "topType": "towns", "topTypeAlt": "canton", "topURI": "KALWADHA_444E333N_S_IRAQ", "translitTitle": "Kalw\u0101\u1e0f\u00e1", "translitTitleOther": "Kalw\u0101\u1e0f\u00e1"}, "type": "Feature"}], "type": "FeatureCollection"}