{"features": [{"geometry": {"coordinates": [72.56065, 22.35228], "type": "Point"}, "properties": {"arBW": "Kanbaya", "arTitle": "\u0643\u0646\u0628\u0627\u064a\u0629", "arTitleOther": "\u0643\u0646\u0628\u0627\u064a\u0629", "lat": "22.35228", "lon": "72.56065", "region": "Sind", "searchNames": "Kanbaya", "topType": "towns", "topTypeAlt": "cite", "topURI": "KANBAYA_725E223N_S_SIND", "translitTitle": "Kanb\u0101ya\u0167", "translitTitleOther": "Kanb\u0101ya\u0167"}, "type": "Feature"}], "type": "FeatureCollection"}