{"features": [{"geometry": {"coordinates": [66.78829, 38.37384], "type": "Point"}, "properties": {"arBW": "Kandak", "arTitle": "\u0643\u0646\u062f\u0643", "arTitleOther": "\u0643\u0646\u062f\u0643", "lat": "38.37384", "lon": "66.78829", "region": "Transoxiana", "searchNames": "Kandak", "topType": "villages", "topTypeAlt": "localite", "topURI": "KANDAK_667E383N_S_TRAN", "translitTitle": "Kandak", "translitTitleOther": "Kandak"}, "type": "Feature"}], "type": "FeatureCollection"}