{"features": [{"geometry": {"coordinates": [44.03706, 32.61792], "type": "Point"}, "properties": {"arBW": "Karbala", "arTitle": "\u0643\u0631\u0628\u0644\u0627\u0621", "arTitleOther": "\u0643\u0631\u0628\u0644\u0627\u0621", "lat": "32.61792", "lon": "44.03706", "region": "Iraq", "searchNames": "Karbala", "topType": "towns", "topTypeAlt": "cite", "topURI": "KARBALA_440E326N_S_IRAQ", "translitTitle": "Karbal\u0101\u02be", "translitTitleOther": "Karbal\u0101\u02be"}, "type": "Feature"}], "type": "FeatureCollection"}