{"features": [{"geometry": {"coordinates": [-4.06918, 38.81784], "type": "Point"}, "properties": {"arBW": "Karkuya", "arTitle": "\u0643\u0631\u0643\u0648\u064a\u0629", "arTitleOther": "\u0643\u0631\u0643\u0648\u064a\u0629", "lat": "38.81784", "lon": "-4.06918", "region": "Andalus", "searchNames": "Karkuya", "topType": "towns", "topTypeAlt": "cite", "topURI": "KARKUYA_040W388N_S_ANDA", "translitTitle": "Kark\u016bya\u0167", "translitTitleOther": "Kark\u016bya\u0167"}, "type": "Feature"}], "type": "FeatureCollection"}