{"features": [{"geometry": {"coordinates": [51.72677, 32.40272], "type": "Point"}, "properties": {"arBW": "Karwan", "arTitle": "\u0643\u0631\u0648\u0627\u0646", "arTitleOther": "\u0643\u0631\u0648\u0627\u0646", "lat": "32.40272", "lon": "51.72677", "region": "Jibal", "searchNames": "Karwan", "topType": "regions", "topTypeAlt": "region", "topURI": "KARWAN_517E324N_R_JIBA", "translitTitle": "Karw\u0101n", "translitTitleOther": "Karw\u0101n"}, "type": "Feature"}], "type": "FeatureCollection"}