{"features": [{"geometry": {"coordinates": [65.5409, 38.9315], "type": "Point"}, "properties": {"arBW": "Kasba", "arTitle": "\u0643\u0633\u0628\u0629", "arTitleOther": "\u0643\u0633\u0628\u0629", "lat": "38.93150", "lon": "65.54090", "region": "Transoxiana", "searchNames": "Kasba", "topType": "towns", "topTypeAlt": "cite", "topURI": "KASBA_655E389N_S_TRAN", "translitTitle": "Kasba\u0167", "translitTitleOther": "Kasba\u0167"}, "type": "Feature"}], "type": "FeatureCollection"}