{"features": [{"geometry": {"coordinates": [62.42996, 35.20428], "type": "Point"}, "properties": {"arBW": "Kayf, Kif", "arTitle": "\u0643\u064a\u0641", "arTitleOther": "\u0643\u064a\u0641\u060c \u0643\u064a\u0641", "lat": "35.20428", "lon": "62.42996", "region": "Khurasan", "searchNames": "Kayf, Kif", "topType": "towns", "topTypeAlt": "cite", "topURI": "KAYF_624E352N_S_KHUR", "translitTitle": "Kayf", "translitTitleOther": "Kayf, K\u012bf"}, "type": "Feature"}], "type": "FeatureCollection"}