{"features": [{"geometry": {"coordinates": [51.68412, 29.60743], "type": "Point"}, "properties": {"arBW": "Kazarun", "arTitle": "\u0643\u0627\u0632\u0631\u0648\u0646", "arTitleOther": "\u0643\u0627\u0632\u0631\u0648\u0646", "lat": "29.60743", "lon": "51.68412", "region": "Faris", "searchNames": "Kazarun", "topType": "towns", "topTypeAlt": "cite", "topURI": "KAZARUN_516E296N_S_FARI", "translitTitle": "K\u0101zar\u016bn", "translitTitleOther": "K\u0101zar\u016bn"}, "type": "Feature"}], "type": "FeatureCollection"}