{"features": [{"geometry": {"coordinates": [59.66585, 36.08], "type": "Point"}, "properties": {"arBW": "Khakisar, Khakisaran, al-Ramada", "arTitle": "\u062e\u0643\u0633\u0627\u0631", "arTitleOther": "\u062e\u0643\u0633\u0627\u0631\u060c \u062e\u0627\u0643\u0633\u0627\u0631\u0627\u0646\u060c \ufb50\u0644\u0631\u0645\u0627\u062f\u0629", "lat": "36.08000", "lon": "59.66585", "region": "Khurasan", "searchNames": "Khakisar, Khakisaran, al-Ramada", "topType": "waystations", "topTypeAlt": "etape", "topURI": "KHAKISAR_596E360N_S_KHUR", "translitTitle": "\u1e2aakis\u0101r", "translitTitleOther": "\u1e2aakis\u0101r, \u1e2a\u0101kis\u0101r\u0101n, al-Ram_ada\u0167"}, "type": "Feature"}], "type": "FeatureCollection"}