{"features": [{"geometry": {"coordinates": [41.37298, 32.07507], "type": "Point"}, "properties": {"arBW": "al-Khalat", "arTitle": "\ufb50\u0644\u062e\u0644\u0627\u0637", "arTitleOther": "\ufb50\u0644\u062e\u0644\u0627\u0637", "lat": "32.07507", "lon": "41.37298", "region": "Badiyat al-Arab", "searchNames": "al-Khalat", "topType": "waystations", "topTypeAlt": "etape", "topURI": "KHALAT_413E320N_S_BADI", "translitTitle": "al-\u1e2aal\u0101\u1e6d", "translitTitleOther": "al-\u1e2aal\u0101\u1e6d"}, "type": "Feature"}], "type": "FeatureCollection"}