{"features": [{"geometry": {"coordinates": [52.02871, 31.25559], "type": "Point"}, "properties": {"arBW": "Khan Rushan, Khan Awis, Khuwarish", "arTitle": "\u062e\u0627\u0646 \u0631\u0648\u0634\u0646", "arTitleOther": "\u062e\u0627\u0646 \u0631\u0648\u0634\u0646\u060c \u062e\u0627\u0646 \u0623\u0648\u064a\u0633\u060c \u062e\u0648\u0627\u0631\u0634", "lat": "31.25559", "lon": "52.02871", "region": "Faris", "searchNames": "Khan Rushan, Khan Awis, Khuwarish", "topType": "waystations", "topTypeAlt": "etape", "topURI": "KHANRUSHAN_520E312N_S_FARI", "translitTitle": "\u1e2a\u0101n R\u016b\u0161an", "translitTitleOther": "\u1e2a\u0101n R\u016b\u0161an, \u1e2a\u0101n Aw\u012bs, \u1e2auw\u0101ri\u0161"}, "type": "Feature"}], "type": "FeatureCollection"}