{"features": [{"geometry": {"coordinates": [69.69791, 41.59198], "type": "Point"}, "properties": {"arBW": "Kharghankath", "arTitle": "\u062e\u0631\u063a\u0627\u0646\u0643\u062b", "arTitleOther": "\u062e\u0631\u063a\u0627\u0646\u0643\u062b", "lat": "41.59198", "lon": "69.69791", "region": "Transoxiana", "searchNames": "Kharghankath", "topType": "towns", "topTypeAlt": "cite", "topURI": "KHARGHANKATH_696E415N_S_TRAN", "translitTitle": "\u1e2aar\u0121\u0101nka\u1e6f", "translitTitleOther": "\u1e2aar\u0121\u0101nka\u1e6f"}, "type": "Feature"}], "type": "FeatureCollection"}