{"features": [{"geometry": {"coordinates": [74.54582, 42.83233], "type": "Point"}, "properties": {"arBW": "Kharanjawan", "arTitle": "\u062e\u0631\u0646\u062c\u0648\u0627\u0646", "arTitleOther": "\u062e\u0631\u0646\u062c\u0648\u0627\u0646", "lat": "42.83233", "lon": "74.54582", "region": "Transoxiana", "searchNames": "Kharanjawan", "topType": "towns", "topTypeAlt": "canton", "topURI": "KHARANJAWAN_745E428N_S_TRAN", "translitTitle": "\u1e2aaran\u01e7aw\u0101n", "translitTitleOther": "\u1e2aaran\u01e7aw\u0101n"}, "type": "Feature"}], "type": "FeatureCollection"}