{"features": [{"geometry": {"coordinates": [60.33577, 41.38465], "type": "Point"}, "properties": {"arBW": "Khiwah", "arTitle": "\u062e\u064a\u0648\u0647", "arTitleOther": "\u062e\u064a\u0648\u0647", "lat": "41.38465", "lon": "60.33577", "region": "Transoxiana", "searchNames": "Khiwah", "topType": "towns", "topTypeAlt": "cite", "topURI": "KHIWAH_603E413N_S_TRAN", "translitTitle": "\u1e2a\u012bwah", "translitTitleOther": "\u1e2a\u012bwah"}, "type": "Feature"}], "type": "FeatureCollection"}