{"features": [{"geometry": {"coordinates": [42.50069, 33.9843], "type": "Point"}, "properties": {"arBW": "al-Khizana", "arTitle": "\ufb50\u0644\u062e\u0632\u0627\u0646\u0629", "arTitleOther": "\ufb50\u0644\u062e\u0632\u0627\u0646\u0629", "lat": "33.98430", "lon": "42.50069", "region": "Aqur", "searchNames": "al-Khizana", "topType": "waystations", "topTypeAlt": "etape?", "topURI": "KHIZANA_425E339N_S_AQUR", "translitTitle": "al-\u1e2aiz\u0101na\u0167", "translitTitleOther": "al-\u1e2aiz\u0101na\u0167"}, "type": "Feature"}], "type": "FeatureCollection"}