{"features": [{"geometry": {"coordinates": [58.45153, 32.93881], "type": "Point"}, "properties": {"arBW": "Khur", "arTitle": "\u062e\u0648\u0631", "arTitleOther": "\u062e\u0648\u0631", "lat": "32.93881", "lon": "58.45153", "region": "Mafaza", "searchNames": "Khur", "topType": "towns", "topTypeAlt": "ville", "topURI": "KHUR_584E329N_S_MAFA", "translitTitle": "\u1e2a\u016br", "translitTitleOther": "\u1e2a\u016br"}, "type": "Feature"}], "type": "FeatureCollection"}