{"features": [{"geometry": {"coordinates": [66.84071, 39.03102], "type": "Point"}, "properties": {"arBW": "Kishsh, Kashsh", "arTitle": "\u0643\u0634", "arTitleOther": "\u0643\u0634\u060c \u0643\u0634", "lat": "39.03102", "lon": "66.84071", "region": "Transoxiana", "searchNames": "Kishsh, Kashsh", "topType": "regions", "topTypeAlt": "territoire", "topURI": "KISHSH_668E390N_R_TRAN", "translitTitle": "Ki\u0161\u0161", "translitTitleOther": "Ki\u0161\u0161, Ka\u0161\u0161"}, "type": "Feature"}], "type": "FeatureCollection"}