{"features": [{"geometry": {"coordinates": [62.37889, 30.15265], "type": "Point"}, "properties": {"arBW": "Kishsh, Kiss", "arTitle": "\u0643\u0634", "arTitleOther": "\u0643\u0634\u060c \u0643\u0633", "lat": "30.15265", "lon": "62.37889", "region": "Sijistan", "searchNames": "Kishsh, Kiss", "topType": "towns", "topTypeAlt": "cite", "topURI": "KISHSH_623E301N_S_SIJI", "translitTitle": "Ki\u0161\u0161", "translitTitleOther": "Ki\u0161\u0161, Kiss"}, "type": "Feature"}], "type": "FeatureCollection"}