{"features": [{"geometry": {"coordinates": [59.02814, 42.09511], "type": "Point"}, "properties": {"arBW": "Kit, Jit", "arTitle": "\u0643\u064a\u062a", "arTitleOther": "\u0643\u064a\u062a\u060c \u062c\u064a\u062a", "lat": "42.09511", "lon": "59.02814", "region": "Transoxiana", "searchNames": "Kit, Jit", "topType": "towns", "topTypeAlt": "cite", "topURI": "KIT_590E420N_S_TRAN", "translitTitle": "K\u012bt", "translitTitleOther": "K\u012bt, \u01e6\u012bt"}, "type": "Feature"}], "type": "FeatureCollection"}