{"features": [{"geometry": {"coordinates": [57.18746, 33.37701], "type": "Point"}, "properties": {"arBW": "Kuri, Kurin", "arTitle": "\u0643\u0631\u064a", "arTitleOther": "\u0643\u0631\u064a\u060c \u0643\u0631\u064a\u0646", "lat": "33.37701", "lon": "57.18746", "region": "Mafaza", "searchNames": "Kuri, Kurin", "topType": "villages", "topTypeAlt": "localite", "topURI": "KURI_571E333N_S_MAFA", "translitTitle": "Kur\u012b", "translitTitleOther": "Kur\u012b, Kur\u012bn"}, "type": "Feature"}], "type": "FeatureCollection"}