{"features": [{"geometry": {"coordinates": [66.49906, 40.00888], "type": "Point"}, "properties": {"arBW": "Kushani, Kushaniya", "arTitle": "\u0643\u0634\u0627\u0646\u064a", "arTitleOther": "\u0643\u0634\u0627\u0646\u064a\u060c \u0643\u0634\u0627\u0646\u064a\u064a", "lat": "40.00888", "lon": "66.49906", "region": "Transoxiana", "searchNames": "Kushani, Kushaniya", "topType": "towns", "topTypeAlt": "canton/cheflieu", "topURI": "KUSHANI_664E400N_S_TRAN", "translitTitle": "Ku\u0161\u0101n\u012b", "translitTitleOther": "Ku\u0161\u0101n\u012b, Ku\u0161\u0101n\u012bya"}, "type": "Feature"}], "type": "FeatureCollection"}