{"features": [{"geometry": {"coordinates": [53.32456, 32.70128], "type": "Point"}, "properties": {"arBW": "Kushkan", "arTitle": "\u0643\u0634\u0643\u0627\u0646", "arTitleOther": "\u0643\u0634\u0643\u0627\u0646", "lat": "32.70128", "lon": "53.32456", "region": "Mafaza", "searchNames": "Kushkan", "topType": "waystations", "topTypeAlt": "etape", "topURI": "KUSHKAN_533E327N_S_MAFA", "translitTitle": "Ku\u0161k\u0101n", "translitTitleOther": "Ku\u0161k\u0101n"}, "type": "Feature"}], "type": "FeatureCollection"}