{"features": [{"geometry": {"coordinates": [35.27017, 32.60823], "type": "Point"}, "properties": {"arBW": "al-Lajjun", "arTitle": "\ufb50\u0644\u0644\u062c\u0648\u0646", "arTitleOther": "\ufb50\u0644\u0644\u062c\u0648\u0646", "lat": "32.60823", "lon": "35.27017", "region": "Sham", "searchNames": "al-Lajjun", "topType": "towns", "topTypeAlt": "cite", "topURI": "LAJJUN_352E326N_S_SHAM", "translitTitle": "al-La\u01e7\u01e7\u016bn", "translitTitleOther": "al-La\u01e7\u01e7\u016bn"}, "type": "Feature"}], "type": "FeatureCollection"}