{"features": [{"geometry": {"coordinates": [40.33707, 20.18053], "type": "Point"}, "properties": {"arBW": "al-Lith", "arTitle": "\ufb50\u0644\u0644\u064a\u062b", "arTitleOther": "\ufb50\u0644\u0644\u064a\u062b", "lat": "20.18053", "lon": "40.33707", "region": "Jazirat al-Arab", "searchNames": "al-Lith", "topType": "waystations", "topTypeAlt": "etape", "topURI": "LITH_403E201N_S_JAZI", "translitTitle": "al-L\u012b\u1e6f", "translitTitleOther": "al-L\u012b\u1e6f"}, "type": "Feature"}], "type": "FeatureCollection"}