{"features": [{"geometry": {"coordinates": [33.35835, 22.61001], "type": "Point"}, "properties": {"arBW": "Maadin al-Tibr", "arTitle": "\u0645\u0639\u0627\u062f\u0646 \ufb50\u0644\u062a\u0628\u0631", "arTitleOther": "\u0645\u0639\u0627\u062f\u0646 \ufb50\u0644\u062a\u0628\u0631", "lat": "22.61001", "lon": "33.35835", "region": "Egypt", "searchNames": "Maadin al-Tibr", "topType": "sites", "topTypeAlt": "mines", "topURI": "MAADINTIBR_333E226N_O_EGYP", "translitTitle": "Ma\u02bf\u0101din al-Tibr", "translitTitleOther": "Ma\u02bf\u0101din al-Tibr"}, "type": "Feature"}], "type": "FeatureCollection"}