{"features": [{"geometry": {"coordinates": [-9.19189, 38.64984], "type": "Point"}, "properties": {"arBW": "al-Madan", "arTitle": "\ufb50\u0644\u0645\u0639\u062f\u0646", "arTitleOther": "\ufb50\u0644\u0645\u0639\u062f\u0646", "lat": "38.64984", "lon": "-9.19189", "region": "Andalus", "searchNames": "al-Madan", "topType": "towns", "topTypeAlt": "cite", "topURI": "MADAN_091W386N_S_ANDA", "translitTitle": "al-Ma\u02bfdan", "translitTitleOther": "al-Ma\u02bfdan"}, "type": "Feature"}], "type": "FeatureCollection"}