{"features": [{"geometry": {"coordinates": [-8.42308, 37.22519], "type": "Point"}, "properties": {"arBW": "Madina Shalab, Shilb", "arTitle": "\u0645\u062f\u064a\u0646\u0629 \u0634\u0644\u0628", "arTitleOther": "\u0645\u062f\u064a\u0646\u0629 \u0634\u0644\u0628\u060c \u0634\u0644\u0628", "lat": "37.22519", "lon": "-8.42308", "region": "Andalus", "searchNames": "Madina Shalab, Shilb", "topType": "towns", "topTypeAlt": "cite", "topURI": "MADINASHALAB_084W372N_S_ANDA", "translitTitle": "Mad\u012bna\u0167 \u0160alab", "translitTitleOther": "Mad\u012bna\u0167 \u0160alab, \u0160ilb"}, "type": "Feature"}], "type": "FeatureCollection"}