{"features": [{"geometry": {"coordinates": [43.54039, 17.60657], "type": "Point"}, "properties": {"arBW": "al-Mahjara", "arTitle": "\ufb50\u0644\u0645\u0647\u062c\u0631\u0629", "arTitleOther": "\ufb50\u0644\u0645\u0647\u062c\u0631\u0629", "lat": "17.60657", "lon": "43.54039", "region": "Jazirat al-Arab", "searchNames": "al-Mahjara", "topType": "villages", "topTypeAlt": "localite", "topURI": "MAHJARA_435E176N_S_JAZI", "translitTitle": "al-Mah\u01e7ara\u0167", "translitTitleOther": "al-Mah\u01e7ara\u0167"}, "type": "Feature"}], "type": "FeatureCollection"}