{"features": [{"geometry": {"coordinates": [34.63712, 31.81276], "type": "Point"}, "properties": {"arBW": "Mahuz Azdud", "arTitle": "\u0645\u0627\u062d\u0648\u0632 \u0623\u0632\u062f\u0648\u062f", "arTitleOther": "\u0645\u0627\u062d\u0648\u0632 \u0623\u0632\u062f\u0648\u062f", "lat": "31.81276", "lon": "34.63712", "region": "Sham", "searchNames": "Mahuz Azdud", "topType": "towns", "topTypeAlt": "port", "topURI": "MAHUZAZDUD_346E318N_S_SHAM", "translitTitle": "M\u0101\u1e25\u016bz Azd\u016bd", "translitTitleOther": "M\u0101\u1e25\u016bz Azd\u016bd"}, "type": "Feature"}], "type": "FeatureCollection"}