{"features": [{"geometry": {"coordinates": [40.55153, 36.53446], "type": "Point"}, "properties": {"arBW": "al-Majdal", "arTitle": "\ufb50\u0644\u0645\u062c\u062f\u0644", "arTitleOther": "\ufb50\u0644\u0645\u062c\u062f\u0644", "lat": "36.53446", "lon": "40.55153", "region": "Aqur", "searchNames": "al-Majdal", "topType": "towns", "topTypeAlt": "cite", "topURI": "MAJDAL_405E365N_S_AQUR", "translitTitle": "al-Ma\u01e7dal", "translitTitleOther": "al-Ma\u01e7dal"}, "type": "Feature"}], "type": "FeatureCollection"}