{"features": [{"geometry": {"coordinates": [44.60835, 12.8341], "type": "Point"}, "properties": {"arBW": "al-Makhnaq", "arTitle": "\ufb50\u0644\u0645\u062e\u0646\u0642", "arTitleOther": "\ufb50\u0644\u0645\u062e\u0646\u0642", "lat": "12.83410", "lon": "44.60835", "region": "Yemen", "searchNames": "al-Makhnaq", "topType": "villages", "topTypeAlt": "localite", "topURI": "MAKHNAQ_446E128N_S_YEME", "translitTitle": "al-Ma\u1e2bnaq", "translitTitleOther": "al-Ma\u1e2bnaq"}, "type": "Feature"}], "type": "FeatureCollection"}