{"features": [{"geometry": {"coordinates": [9.11248, 36.81309], "type": "Point"}, "properties": {"arBW": "Makna Abu Mansur", "arTitle": "\u0645\u0643\u0646\u0629 \u0623\u0628\u0648 \u0645\u0646\u0635\u0648\u0631", "arTitleOther": "\u0645\u0643\u0646\u0629 \u0623\u0628\u0648 \u0645\u0646\u0635\u0648\u0631", "lat": "36.81309", "lon": "9.11248", "region": "Maghrib", "searchNames": "Makna Abu Mansur", "topType": "regions", "topTypeAlt": "region", "topURI": "MAKNAABUMANSUR_091E368N_R_MAGH", "translitTitle": "Makna\u0167 Ab\u016b Man\u1e63\u016br", "translitTitleOther": "Makna\u0167 Ab\u016b Man\u1e63\u016br"}, "type": "Feature"}], "type": "FeatureCollection"}