{"features": [{"geometry": {"coordinates": [60.29878, 35.4167], "type": "Point"}, "properties": {"arBW": "Malayakird", "arTitle": "\u0645\u0627\u0644\u0627\u064a\u0643\u0631\u062f", "arTitleOther": "\u0645\u0627\u0644\u0627\u064a\u0643\u0631\u062f", "lat": "35.41670", "lon": "60.29878", "region": "Khurasan", "searchNames": "Malayakird", "topType": "waystations", "topTypeAlt": "etape", "topURI": "MALAYAKIRD_602E354N_S_KHUR", "translitTitle": "M\u0101l\u0101yakird", "translitTitleOther": "M\u0101l\u0101yakird"}, "type": "Feature"}], "type": "FeatureCollection"}