{"features": [{"geometry": {"coordinates": [-3.62588, 39.81332], "type": "Point"}, "properties": {"arBW": "Mantisha", "arTitle": "\u0645\u0646\u062a\u064a\u0634\u0629", "arTitleOther": "\u0645\u0646\u062a\u064a\u0634\u0629", "lat": "39.81332", "lon": "-3.62588", "region": "Andalus", "searchNames": "Mantisha", "topType": "towns", "topTypeAlt": "cite", "topURI": "MANTISHA_036W398N_S_ANDA", "translitTitle": "Mant\u012b\u0161a\u0167", "translitTitleOther": "Mant\u012b\u0161a\u0167"}, "type": "Feature"}], "type": "FeatureCollection"}