{"features": [{"geometry": {"coordinates": [45.439, 15.55742], "type": "Point"}, "properties": {"arBW": "Marib", "arTitle": "\u0645\u0623\u0631\u0628", "arTitleOther": "\u0645\u0623\u0631\u0628", "lat": "15.55742", "lon": "45.43900", "region": "Yemen", "searchNames": "Marib", "topType": "regions", "topTypeAlt": "mikhlaf", "topURI": "MARIB_454E155N_R_YEME", "translitTitle": "Ma\u02berib", "translitTitleOther": "Ma\u02berib"}, "type": "Feature"}], "type": "FeatureCollection"}