{"features": [{"geometry": {"coordinates": [63.3667, 35.5925], "type": "Point"}, "properties": {"arBW": "Marw al-Rudh", "arTitle": "\u0645\u0631\u0648 \ufb50\u0644\u0631\u0648\u0630", "arTitleOther": "\u0645\u0631\u0648 \ufb50\u0644\u0631\u0648\u0630", "lat": "35.59250", "lon": "63.36670", "region": "Khurasan", "searchNames": "Marw al-Rudh", "topType": "regions", "topTypeAlt": "territoire", "topURI": "MARWRUDH_633E355N_R_KHUR", "translitTitle": "Marw al-R\u016b\u1e0f", "translitTitleOther": "Marw al-R\u016b\u1e0f"}, "type": "Feature"}], "type": "FeatureCollection"}