{"features": [{"geometry": {"coordinates": [1.90701, 35.9541], "type": "Point"}, "properties": {"arBW": "Matmata", "arTitle": "\u0645\u0637\u0645\u0627\u0637\u0629", "arTitleOther": "\u0645\u0637\u0645\u0627\u0637\u0629", "lat": "35.95410", "lon": "1.90701", "region": "Maghrib", "searchNames": "Matmata", "topType": "regions", "topTypeAlt": "region", "topURI": "MATMATA_019E359N_R_MAGH", "translitTitle": "Ma\u1e6dm\u0101\u1e6da\u0167", "translitTitleOther": "Ma\u1e6dm\u0101\u1e6da\u0167"}, "type": "Feature"}], "type": "FeatureCollection"}