{"features": [{"geometry": {"coordinates": [52.55267, 36.4708], "type": "Point"}, "properties": {"arBW": "Mila", "arTitle": "\u0645\u064a\u0644\u0629", "arTitleOther": "\u0645\u064a\u0644\u0629", "lat": "36.47080", "lon": "52.55267", "region": "Daylam", "searchNames": "Mila", "topType": "towns", "topTypeAlt": "cite", "topURI": "MILA_525E364N_S_DAYL", "translitTitle": "M\u012bla\u0167", "translitTitleOther": "M\u012bla\u0167"}, "type": "Feature"}], "type": "FeatureCollection"}