{"features": [{"geometry": {"coordinates": [69.69102, 38.32824], "type": "Point"}, "properties": {"arBW": "Munk", "arTitle": "\u0645\u0646\u0643", "arTitleOther": "\u0645\u0646\u0643", "lat": "38.32824", "lon": "69.69102", "region": "Transoxiana", "searchNames": "Munk", "topType": "towns", "topTypeAlt": "cite", "topURI": "MUNK_696E383N_S_TRAN", "translitTitle": "Munk", "translitTitleOther": "Munk"}, "type": "Feature"}], "type": "FeatureCollection"}