{"features": [{"geometry": {"coordinates": [38.52691, 37.28854], "type": "Point"}, "properties": {"arBW": "al-Muzaniyya", "arTitle": "\ufb50\u0644\u0645\u0632\u0627\u0646\u064a\u0629", "arTitleOther": "\ufb50\u0644\u0645\u0632\u0627\u0646\u064a\u0629", "lat": "37.28854", "lon": "38.52691", "region": "Aqur", "searchNames": "al-Muzaniyya", "topType": "waystations", "topTypeAlt": "etape", "topURI": "MUZANIYYA_385E372N_S_AQUR", "translitTitle": "al-Muz\u0101niyya\u0167", "translitTitleOther": "al-Muz\u0101niyya\u0167"}, "type": "Feature"}], "type": "FeatureCollection"}