{"features": [{"geometry": {"coordinates": [35.24238, 32.22047], "type": "Point"}, "properties": {"arBW": "Nabulus", "arTitle": "\u0646\u0627\u0628\u0644\u0633", "arTitleOther": "\u0646\u0627\u0628\u0644\u0633", "lat": "32.22047", "lon": "35.24238", "region": "Sham", "searchNames": "Nabulus", "topType": "towns", "topTypeAlt": "cite", "topURI": "NABULUS_352E322N_S_SHAM", "translitTitle": "N\u0101bulus", "translitTitleOther": "N\u0101bulus"}, "type": "Feature"}], "type": "FeatureCollection"}