{"features": [{"geometry": {"coordinates": [-5.84677, 31.13962], "type": "Point"}, "properties": {"arBW": "al-Nahhasin", "arTitle": "\ufb50\u0644\u0646\u062d\u0627\u0633\u064a\u0646", "arTitleOther": "\ufb50\u0644\u0646\u062d\u0627\u0633\u064a\u0646", "lat": "31.13962", "lon": "-5.84677", "region": "Maghrib", "searchNames": "al-Nahhasin", "topType": "villages", "topTypeAlt": "localite", "topURI": "NAHHASIN_058W311N_S_MAGH", "translitTitle": "al-Na\u1e25\u1e25\u0101s\u012bn", "translitTitleOther": "al-Na\u1e25\u1e25\u0101s\u012bn"}, "type": "Feature"}], "type": "FeatureCollection"}