{"features": [{"geometry": {"coordinates": [55.38357, 37.06455], "type": "Point"}, "properties": {"arBW": "Nahr Khurmarudh", "arTitle": "\u0646\u0647\u0631 \u062e\u0631\u0645\u0627\u0631\u0648\u0630", "arTitleOther": "\u0646\u0647\u0631 \u062e\u0631\u0645\u0627\u0631\u0648\u0630", "lat": "37.06455", "lon": "55.38357", "region": "Daylam", "searchNames": "Nahr Khurmarudh", "topType": "waters", "topTypeAlt": "riviere", "topURI": "NAHRKHURMARUDH_553E370N_W_DAYL", "translitTitle": "Nahr \u1e2aurm\u0101r\u016b\u1e0f", "translitTitleOther": "Nahr \u1e2aurm\u0101r\u016b\u1e0f"}, "type": "Feature"}], "type": "FeatureCollection"}