{"features": [{"geometry": {"coordinates": [44.72053, 32.7443], "type": "Point"}, "properties": {"arBW": "Nahr Kutha", "arTitle": "\u0646\u0647\u0631 \u0643\u0648\u062b\u0649", "arTitleOther": "\u0646\u0647\u0631 \u0643\u0648\u062b\u0649", "lat": "32.74430", "lon": "44.72053", "region": "Iraq", "searchNames": "Nahr Kutha", "topType": "waters", "topTypeAlt": "canal", "topURI": "NAHRKUTHA_447E327N_W_IRAQ", "translitTitle": "Nahr K\u016b\u1e6f\u00e1", "translitTitleOther": "Nahr K\u016b\u1e6f\u00e1"}, "type": "Feature"}], "type": "FeatureCollection"}