{"features": [{"geometry": {"coordinates": [69.09689, 37.5901], "type": "Point"}, "properties": {"arBW": "Nahr Andijaragh", "arTitle": "\u0646\u0647\u0631 \u0623\u0646\u062f\u064a\u062c\u0627\u0631\u0627\u063a", "arTitleOther": "\u0646\u0647\u0631 \u0623\u0646\u062f\u064a\u062c\u0627\u0631\u0627\u063a", "lat": "37.59010", "lon": "69.09689", "region": "Transoxiana", "searchNames": "Nahr Andijaragh", "topType": "waters", "topTypeAlt": "riviere", "topURI": "NAHRANDIJARAGH_690E375N_W_TRAN", "translitTitle": "Nahr And\u012b\u01e7\u0101r\u0101\u0121", "translitTitleOther": "Nahr And\u012b\u01e7\u0101r\u0101\u0121"}, "type": "Feature"}], "type": "FeatureCollection"}