{"features": [{"geometry": {"coordinates": [45.10369, 32.53829], "type": "Point"}, "properties": {"arBW": "Nahr al-Nil", "arTitle": "\u0646\u0647\u0631 \ufb50\u0644\u0646\u064a\u0644", "arTitleOther": "\u0646\u0647\u0631 \ufb50\u0644\u0646\u064a\u0644", "lat": "32.53829", "lon": "45.10369", "region": "Iraq", "searchNames": "Nahr al-Nil", "topType": "waters", "topTypeAlt": "canal", "topURI": "NAHRNIL_451E325N_W_IRAQ", "translitTitle": "Nahr al-N\u012bl", "translitTitleOther": "Nahr al-N\u012bl"}, "type": "Feature"}], "type": "FeatureCollection"}