{"features": [{"geometry": {"coordinates": [44.50953, 32.94875], "type": "Point"}, "properties": {"arBW": "Nahr al-Malik", "arTitle": "\u0646\u0647\u0631 \ufb50\u0644\u0645\u0644\u0643", "arTitleOther": "\u0646\u0647\u0631 \ufb50\u0644\u0645\u0644\u0643", "lat": "32.94875", "lon": "44.50953", "region": "Iraq", "searchNames": "Nahr al-Malik", "topType": "waters", "topTypeAlt": "canal", "topURI": "NAHRMALIK_445E329N_W_IRAQ", "translitTitle": "Nahr al-Malik", "translitTitleOther": "Nahr al-Malik"}, "type": "Feature"}], "type": "FeatureCollection"}