{"features": [{"geometry": {"coordinates": [71.29976, 32.14532], "type": "Point"}, "properties": {"arBW": "Nahr Mihran", "arTitle": "\u0646\u0647\u0631 \u0645\u0647\u0631\u0627\u0646", "arTitleOther": "\u0646\u0647\u0631 \u0645\u0647\u0631\u0627\u0646", "lat": "32.14532", "lon": "71.29976", "region": "Sind", "searchNames": "Nahr Mihran", "topType": "waters", "topTypeAlt": "riviere", "topURI": "NAHRMIHRAN_712E321N_W_SIND", "translitTitle": "Nahr Mihr\u0101n", "translitTitleOther": "Nahr Mihr\u0101n"}, "type": "Feature"}], "type": "FeatureCollection"}