{"features": [{"geometry": {"coordinates": [49.01519, 31.76776], "type": "Point"}, "properties": {"arBW": "Nahr Mashruqan, Masruqan", "arTitle": "\u0646\u0647\u0631 \u0645\u0634\u0631\u0642\u0627\u0646", "arTitleOther": "\u0646\u0647\u0631 \u0645\u0634\u0631\u0642\u0627\u0646\u060c \u0645\u0633\u0631\u0648\u0642\u0627\u0646", "lat": "31.76776", "lon": "49.01519", "region": "Khuzistan", "searchNames": "Nahr Mashruqan, Masruqan", "topType": "waters", "topTypeAlt": "riviere", "topURI": "NAHRMASHRUQAN_490E317N_W_KHUZ", "translitTitle": "Nahr Ma\u0161ruq\u0101n", "translitTitleOther": "Nahr Ma\u0161ruq\u0101n, Masr\u016bq\u0101n"}, "type": "Feature"}], "type": "FeatureCollection"}