{"features": [{"geometry": {"coordinates": [45.13019, 49.20301], "type": "Point"}, "properties": {"arBW": "Nahr Itil", "arTitle": "\u0646\u0647\u0631 \u0625\u062a\u0644", "arTitleOther": "\u0646\u0647\u0631 \u0625\u062a\u0644", "lat": "49.20301", "lon": "45.13019", "region": "Khazar", "searchNames": "Nahr Itil", "topType": "waters", "topTypeAlt": "riviere", "topURI": "NAHRITIL_451E492N_W_KHAZ", "translitTitle": "Nahr Itil", "translitTitleOther": "Nahr Itil"}, "type": "Feature"}], "type": "FeatureCollection"}