{"features": [{"geometry": {"coordinates": [44.44611, 32.54156], "type": "Point"}, "properties": {"arBW": "Nahr Sura", "arTitle": "\u0646\u0647\u0631 \u0633\u0648\u0631\u0627", "arTitleOther": "\u0646\u0647\u0631 \u0633\u0648\u0631\u0627", "lat": "32.54156", "lon": "44.44611", "region": "Iraq", "searchNames": "Nahr Sura", "topType": "waters", "topTypeAlt": "canal", "topURI": "NAHRSURA_444E325N_W_IRAQ", "translitTitle": "Nahr S\u016br\u0101", "translitTitleOther": "Nahr S\u016br\u0101"}, "type": "Feature"}], "type": "FeatureCollection"}