{"features": [{"geometry": {"coordinates": [68.5599, 37.4415], "type": "Point"}, "properties": {"arBW": "Nahr Wakhshab", "arTitle": "\u0646\u0647\u0631 \u0648\u062e\u0634\u0627\u0628", "arTitleOther": "\u0646\u0647\u0631 \u0648\u062e\u0634\u0627\u0628", "lat": "37.44150", "lon": "68.55990", "region": "Transoxiana", "searchNames": "Nahr Wakhshab", "topType": "regions", "topTypeAlt": "region", "topURI": "NAHRWAKHSHAB_685E374N_R_TRAN", "translitTitle": "Nahr Wa\u1e2b\u0161\u0101b", "translitTitleOther": "Nahr Wa\u1e2b\u0161\u0101b"}, "type": "Feature"}], "type": "FeatureCollection"}