{"features": [{"geometry": {"coordinates": [33.26692, 44.13579], "type": "Point"}, "properties": {"arBW": "Nahr Isa", "arTitle": "\u0646\u0647\u0631 \u0639\u0633\u0649", "arTitleOther": "\u0646\u0647\u0631 \u0639\u0633\u0649", "lat": "33.26692", "lon": "44.13579", "region": "Iraq", "searchNames": "Nahr Isa", "topType": "waters", "topTypeAlt": "canal", "topURI": "NAHRISA_441E332N_W_IRAQ", "translitTitle": "Nahr \u02bfIs\u00e1", "translitTitleOther": "Nahr \u02bfIs\u00e1"}, "type": "Feature"}], "type": "FeatureCollection"}