{"features": [{"geometry": {"coordinates": [44.14391, 15.83563], "type": "Point"}, "properties": {"arBW": "Nait", "arTitle": "\u0646\u0627\u0639\u0637", "arTitleOther": "\u0646\u0627\u0639\u0637", "lat": "15.83563", "lon": "44.14391", "region": "Yemen", "searchNames": "Nait", "topType": "waystations", "topTypeAlt": "chateau", "topURI": "NAIT_441E158N_S_YEME", "translitTitle": "N\u0101\u02bfi\u1e6d", "translitTitleOther": "N\u0101\u02bfi\u1e6d"}, "type": "Feature"}], "type": "FeatureCollection"}