{"features": [{"geometry": {"coordinates": [58.64795, 28.98436], "type": "Point"}, "properties": {"arBW": "Narmasir", "arTitle": "\u0646\u0631\u0645\u0627\u0633\u064a\u0631", "arTitleOther": "\u0646\u0631\u0645\u0627\u0633\u064a\u0631", "lat": "28.98436", "lon": "58.64795", "region": "Kirman", "searchNames": "Narmasir", "topType": "capitals", "topTypeAlt": "capitale", "topURI": "NARMASIR_586E289N_S_KIRM", "translitTitle": "Narm\u0101s\u012br", "translitTitleOther": "Narm\u0101s\u012br"}, "type": "Feature"}], "type": "FeatureCollection"}