{"features": [{"geometry": {"coordinates": [65.8104, 38.86245], "type": "Point"}, "properties": {"arBW": "Nasaf", "arTitle": "\u0646\u0633\u0641", "arTitleOther": "\u0646\u0633\u0641", "lat": "38.86245", "lon": "65.81040", "region": "Transoxiana", "searchNames": "Nasaf", "topType": "capitals", "topTypeAlt": "capitale", "topURI": "NASAF_658E388N_S_TRAN", "translitTitle": "Nasaf", "translitTitleOther": "Nasaf"}, "type": "Feature"}], "type": "FeatureCollection"}