{"features": [{"geometry": {"coordinates": [58.79841, 36.12138], "type": "Point"}, "properties": {"arBW": "Naysabur", "arTitle": "\u0646\u064a\u0633\u0627\u0628\u0648\u0631", "arTitleOther": "\u0646\u064a\u0633\u0627\u0628\u0648\u0631", "lat": "36.12138", "lon": "58.79841", "region": "Khurasan", "searchNames": "Naysabur", "topType": "regions", "topTypeAlt": "circon", "topURI": "NAYSABUR_587E361N_R_KHUR", "translitTitle": "Nays\u0101b\u016br", "translitTitleOther": "Nays\u0101b\u016br"}, "type": "Feature"}], "type": "FeatureCollection"}