{"features": [{"geometry": {"coordinates": [43.175, 36.35104], "type": "Point"}, "properties": {"arBW": "Ninawa, Nunawa", "arTitle": "\u0646\u064a\u0646\u0648\u0649", "arTitleOther": "\u0646\u064a\u0646\u0648\u0649\u060c \u0646\u0648\u0646\u0648\u0627", "lat": "36.35104", "lon": "43.17500", "region": "Aqur", "searchNames": "Ninawa, Nunawa", "topType": "towns", "topTypeAlt": "cite", "topURI": "NINAWA_431E363N_S_AQUR", "translitTitle": "N\u012bnaw\u00e1", "translitTitleOther": "N\u012bnaw\u00e1, N\u016bnaw\u0101"}, "type": "Feature"}], "type": "FeatureCollection"}