{"features": [{"geometry": {"coordinates": [69.50903, 41.40191], "type": "Point"}, "properties": {"arBW": "Nujakath", "arTitle": "\u0646\u0648\u062c\u0627\u0643\u062b", "arTitleOther": "\u0646\u0648\u062c\u0627\u0643\u062b", "lat": "41.40191", "lon": "69.50903", "region": "Transoxiana", "searchNames": "Nujakath", "topType": "towns", "topTypeAlt": "cite", "topURI": "NUJAKATH_695E414N_S_TRAN", "translitTitle": "N\u016b\u01e7\u0101ka\u1e6f", "translitTitleOther": "N\u016b\u01e7\u0101ka\u1e6f"}, "type": "Feature"}], "type": "FeatureCollection"}