{"features": [{"geometry": {"coordinates": [72.7626, 40.34137], "type": "Point"}, "properties": {"arBW": "Nuqad, Naqad", "arTitle": "\u0646\u0642\u0627\u062f", "arTitleOther": "\u0646\u0642\u0627\u062f\u060c \u0646\u0642\u0627\u062f", "lat": "40.34137", "lon": "72.76260", "region": "Transoxiana", "searchNames": "Nuqad, Naqad", "topType": "regions", "topTypeAlt": "region", "topURI": "NUQAD_727E403N_R_TRAN", "translitTitle": "Nuq\u0101d", "translitTitleOther": "Nuq\u0101d, Naq\u0101d"}, "type": "Feature"}], "type": "FeatureCollection"}