{"features": [{"geometry": {"coordinates": [66.57989, 25.49111], "type": "Point"}, "properties": {"arBW": "Qanbali, Qanbala", "arTitle": "\u0642\u0646\u0628\u0644\u064a", "arTitleOther": "\u0642\u0646\u0628\u0644\u064a\u060c \u0642\u0646\u0628\u0644\u0649", "lat": "25.49111", "lon": "66.57989", "region": "Sind", "searchNames": "Qanbali, Qanbala", "topType": "towns", "topTypeAlt": "cite", "topURI": "QANBALI_665E254N_S_SIND", "translitTitle": "Qanbal\u012b", "translitTitleOther": "Qanbal\u012b, Qanbal\u00e1"}, "type": "Feature"}], "type": "FeatureCollection"}