{"features": [{"geometry": {"coordinates": [-0.47061, 38.34618], "type": "Point"}, "properties": {"arBW": "Qant", "arTitle": "\u0642\u0627\u0646\u062a", "arTitleOther": "\u0642\u0627\u0646\u062a", "lat": "38.34618", "lon": "-0.47061", "region": "Andalus", "searchNames": "Qant", "topType": "towns", "topTypeAlt": "cite", "topURI": "QANT_004W383N_S_ANDA", "translitTitle": "Q\u0101nt", "translitTitleOther": "Q\u0101nt"}, "type": "Feature"}], "type": "FeatureCollection"}