{"features": [{"geometry": {"coordinates": [32.32461, 30.85902], "type": "Point"}, "properties": {"arBW": "al-Qantara", "arTitle": "\ufb50\u0644\u0642\u0646\u0637\u0631\u0629", "arTitleOther": "\ufb50\u0644\u0642\u0646\u0637\u0631\u0629", "lat": "30.85902", "lon": "32.32461", "region": "Egypt", "searchNames": "al-Qantara", "topType": "villages", "topTypeAlt": "localite", "topURI": "QANTARA_323E308N_S_EGYP", "translitTitle": "al-Qan\u1e6dara\u0167", "translitTitleOther": "al-Qan\u1e6dara\u0167"}, "type": "Feature"}], "type": "FeatureCollection"}