{"features": [{"geometry": {"coordinates": [50.65469, 33.23683], "type": "Point"}, "properties": {"arBW": "Qanuwan", "arTitle": "\u0642\u0646\u0648\u0648\u0627\u0646", "arTitleOther": "\u0642\u0646\u0648\u0648\u0627\u0646", "lat": "33.23683", "lon": "50.65469", "region": "Jibal", "searchNames": "Qanuwan", "topType": "waystations", "topTypeAlt": "etape", "topURI": "QANUWAN_506E332N_S_JIBA", "translitTitle": "Qan\u016bw\u0101n", "translitTitleOther": "Qan\u016bw\u0101n"}, "type": "Feature"}], "type": "FeatureCollection"}