{"features": [{"geometry": {"coordinates": [47.09845, 34.32388], "type": "Point"}, "properties": {"arBW": "Qarmasin, Qarmisin", "arTitle": "\u0642\u0631\u0645\u0627\u0633\u064a\u0646", "arTitleOther": "\u0642\u0631\u0645\u0627\u0633\u064a\u0646\u060c \u0642\u0631\u0645\u064a\u0633\u064a\u0646", "lat": "34.32388", "lon": "47.09845", "region": "Jibal", "searchNames": "Qarmasin, Qarmisin", "topType": "towns", "topTypeAlt": "cite", "topURI": "QARMASIN_470E343N_S_JIBA", "translitTitle": "Qarm\u0101s\u012bn", "translitTitleOther": "Qarm\u0101s\u012bn, Qarm\u012bs\u012bn"}, "type": "Feature"}], "type": "FeatureCollection"}