{"features": [{"geometry": {"coordinates": [40.21296, 21.46576], "type": "Point"}, "properties": {"arBW": "Qarn, Qarn al-Manazil", "arTitle": "\u0642\u0631\u0646", "arTitleOther": "\u0642\u0631\u0646\u060c \u0642\u0631\u0646 \ufb50\u0644\u0645\u0646\u0627\u0632\u0644", "lat": "21.46576", "lon": "40.21296", "region": "Jazirat al-Arab", "searchNames": "Qarn, Qarn al-Manazil", "topType": "towns", "topTypeAlt": "cite", "topURI": "QARN_402E214N_S_JAZI", "translitTitle": "Qarn", "translitTitleOther": "Qarn, Qarn al-Man\u0101zil"}, "type": "Feature"}], "type": "FeatureCollection"}