{"features": [{"geometry": {"coordinates": [47.90457, 34.4958], "type": "Point"}, "properties": {"arBW": "Qasr al-Lusus", "arTitle": "\u0642\u0635\u0631 \ufb50\u0644\u0644\u0635\u0648\u0635", "arTitleOther": "\u0642\u0635\u0631 \ufb50\u0644\u0644\u0635\u0648\u0635", "lat": "34.49580", "lon": "47.90457", "region": "Jibal", "searchNames": "Qasr al-Lusus", "topType": "towns", "topTypeAlt": "cite", "topURI": "QASRLUSUS_479E344N_S_JIBA", "translitTitle": "Qa\u1e63r al-Lu\u1e63\u016b\u1e63", "translitTitleOther": "Qa\u1e63r al-Lu\u1e63\u016b\u1e63"}, "type": "Feature"}], "type": "FeatureCollection"}