{"features": [{"geometry": {"coordinates": [17.29329, 30.94914], "type": "Point"}, "properties": {"arBW": "Qasr al-Ibadi, Qabr al-Ibadi", "arTitle": "\u0642\u0635\u0631 \ufb50\u0644\u0639\u0628\u0627\u062f\u064a", "arTitleOther": "\u0642\u0635\u0631 \ufb50\u0644\u0639\u0628\u0627\u062f\u064a\u060c \u0642\u0628\u0631 \ufb50\u0644\u0639\u0628\u0627\u062f\u064a", "lat": "30.94914", "lon": "17.29329", "region": "Barqa", "searchNames": "Qasr al-Ibadi, Qabr al-Ibadi", "topType": "waystations", "topTypeAlt": "etape", "topURI": "QASRIBADI_172E309N_S_BARQ", "translitTitle": "Qa\u1e63r al-\u02bfIb\u0101d\u012b", "translitTitleOther": "Qa\u1e63r al-\u02bfIb\u0101d\u012b, Qabr al-\u02bfIb\u0101d\u012b"}, "type": "Feature"}], "type": "FeatureCollection"}