{"features": [{"geometry": {"coordinates": [-8.48333, 38.36698], "type": "Point"}, "properties": {"arBW": "Qasr Banu Wardas", "arTitle": "\u0642\u0635\u0631 \u0628\u0646\u0648 \u0648\u0631\u062f\u0627\u0633", "arTitleOther": "\u0642\u0635\u0631 \u0628\u0646\u0648 \u0648\u0631\u062f\u0627\u0633", "lat": "38.36698", "lon": "-8.48333", "region": "Andalus", "searchNames": "Qasr Banu Wardas", "topType": "towns", "topTypeAlt": "cite", "topURI": "QASRBANUWARDAS_084W383N_S_ANDA", "translitTitle": "Qa\u1e63r Ban\u016b Ward\u0101s", "translitTitleOther": "Qa\u1e63r Ban\u016b Ward\u0101s"}, "type": "Feature"}], "type": "FeatureCollection"}