{"features": [{"geometry": {"coordinates": [45.62659, 34.49996], "type": "Point"}, "properties": {"arBW": "Qasr Shirin", "arTitle": "\u0642\u0635\u0631 \u0634\u064a\u0631\u064a\u0646", "arTitleOther": "\u0642\u0635\u0631 \u0634\u064a\u0631\u064a\u0646", "lat": "34.49996", "lon": "45.62659", "region": "Iraq", "searchNames": "Qasr Shirin", "topType": "villages", "topTypeAlt": "localite", "topURI": "QASRSHIRIN_456E344N_S_IRAQ", "translitTitle": "Qa\u1e63r \u0160\u012br\u012bn", "translitTitleOther": "Qa\u1e63r \u0160\u012br\u012bn"}, "type": "Feature"}], "type": "FeatureCollection"}