{"features": [{"geometry": {"coordinates": [-3.87676, 37.98847], "type": "Point"}, "properties": {"arBW": "Qastalla", "arTitle": "\u0642\u0633\u0637\u0644\u0629", "arTitleOther": "\u0642\u0633\u0637\u0644\u0629", "lat": "37.98847", "lon": "-3.87676", "region": "Andalus", "searchNames": "Qastalla", "topType": "towns", "topTypeAlt": "cite", "topURI": "QASTALLA_038W379N_S_ANDA", "translitTitle": "Qas\u1e6dalla\u0167", "translitTitleOther": "Qas\u1e6dalla\u0167"}, "type": "Feature"}], "type": "FeatureCollection"}