{"features": [{"geometry": {"coordinates": [51.21928, 24.95829], "type": "Point"}, "properties": {"arBW": "Qatar", "arTitle": "\u0642\u0637\u0631", "arTitleOther": "\u0642\u0637\u0631", "lat": "24.95829", "lon": "51.21928", "region": "Jazirat al-Arab", "searchNames": "Qatar", "topType": "regions", "topTypeAlt": "region", "topURI": "QATAR_512E249N_R_JAZI", "translitTitle": "Qa\u1e6dar", "translitTitleOther": "Qa\u1e6dar"}, "type": "Feature"}], "type": "FeatureCollection"}