{"features": [{"geometry": {"coordinates": [41.65725, 22.78726], "type": "Point"}, "properties": {"arBW": "Quba", "arTitle": "\u0642\u0628\u0627\u0621", "arTitleOther": "\u0642\u0628\u0627\u0621", "lat": "22.78726", "lon": "41.65725", "region": "Jazirat al-Arab", "searchNames": "Quba", "topType": "villages", "topTypeAlt": "village", "topURI": "QUBA_416E227N_S_JAZI", "translitTitle": "Qub\u0101\u02be", "translitTitleOther": "Qub\u0101\u02be"}, "type": "Feature"}], "type": "FeatureCollection"}