{"features": [{"geometry": {"coordinates": [30.82245, 30.86818], "type": "Point"}, "properties": {"arBW": "Qulayb al-Ummal", "arTitle": "\u0642\u0644\u064a\u0628 \ufb50\u0644\u0639\u0645\u0627\u0644", "arTitleOther": "\u0642\u0644\u064a\u0628 \ufb50\u0644\u0639\u0645\u0627\u0644", "lat": "30.86818", "lon": "30.82245", "region": "Egypt", "searchNames": "Qulayb al-Ummal", "topType": "villages", "topTypeAlt": "localite", "topURI": "QULAYBUMMAL_308E308N_S_EGYP", "translitTitle": "Qulayb al-`Umm\u0101l", "translitTitleOther": "Qulayb al-`Umm\u0101l"}, "type": "Feature"}], "type": "FeatureCollection"}