{"features": [{"geometry": {"coordinates": [34.63354, 50.90695], "type": "Point"}, "properties": {"arBW": "Qumm", "arTitle": "\u0642\u0645", "arTitleOther": "\u0642\u0645", "lat": "34.63354", "lon": "50.90695", "region": "Jibal", "searchNames": "Qumm", "topType": "capitals", "topTypeAlt": "cheflieu", "topURI": "QUMM_509E346N_S_JIBA", "translitTitle": "Qumm", "translitTitleOther": "Qumm"}, "type": "Feature"}], "type": "FeatureCollection"}