{"features": [{"geometry": {"coordinates": [53.78841, 30.00577], "type": "Point"}, "properties": {"arBW": "Ras al-Dunya", "arTitle": "\u0631\u0623\u0633 \ufb50\u0644\u062f\u0646\u064a\u0627", "arTitleOther": "\u0631\u0623\u0633 \ufb50\u0644\u062f\u0646\u064a\u0627", "lat": "30.00577", "lon": "53.78841", "region": "Faris", "searchNames": "Ras al-Dunya", "topType": "waystations", "topTypeAlt": "etape", "topURI": "RASDUNYA_537E300N_S_FARI", "translitTitle": "Ra\u02bes al-Duny\u0101", "translitTitleOther": "Ra\u02bes al-Duny\u0101"}, "type": "Feature"}], "type": "FeatureCollection"}