{"features": [{"geometry": {"coordinates": [38.64087, 32.03911], "type": "Point"}, "properties": {"arBW": "al-Rawara, al-Dawara", "arTitle": "\ufb50\u0644\u0631\u0648\u0627\u0631\u0649", "arTitleOther": "\ufb50\u0644\u0631\u0648\u0627\u0631\u0649\u060c \ufb50\u0644\u062f\u0648\u0627\u0631\u0649", "lat": "32.03911", "lon": "38.64087", "region": "Badiyat al-Arab", "searchNames": "al-Rawara, al-Dawara", "topType": "waystations", "topTypeAlt": "etape", "topURI": "RAWARA_386E320N_S_BADI", "translitTitle": "al-Raw\u0101r\u00e1", "translitTitleOther": "al-Raw\u0101r\u00e1, al-Daw\u0101r\u00e1"}, "type": "Feature"}], "type": "FeatureCollection"}