{"features": [{"geometry": {"coordinates": [51.77613, 33.08075], "type": "Point"}, "properties": {"arBW": "Ribat Wazz", "arTitle": "\u0631\u0628\u0627\u0637 \u0648\u0632", "arTitleOther": "\u0631\u0628\u0627\u0637 \u0648\u0632", "lat": "33.08075", "lon": "51.77613", "region": "Jibal", "searchNames": "Ribat Wazz", "topType": "waystations", "topTypeAlt": "etape", "topURI": "RIBATWAZZ_517E330N_S_JIBA", "translitTitle": "Rib\u0101\u1e6d Wazz", "translitTitleOther": "Rib\u0101\u1e6d Wazz"}, "type": "Feature"}], "type": "FeatureCollection"}