{"features": [{"geometry": {"coordinates": [65.02339, 39.44667], "type": "Point"}, "properties": {"arBW": "Ribat Atiq", "arTitle": "\u0631\u0628\u0627\u0637 \u0639\u062a\u064a\u0642", "arTitleOther": "\u0631\u0628\u0627\u0637 \u0639\u062a\u064a\u0642", "lat": "39.44667", "lon": "65.02339", "region": "Transoxiana", "searchNames": "Ribat Atiq", "topType": "waystations", "topTypeAlt": "ribat", "topURI": "RIBATATIQ_650E394N_S_TRAN", "translitTitle": "Rib\u0101\u1e6d \u02bfAt\u012bq", "translitTitleOther": "Rib\u0101\u1e6d \u02bfAt\u012bq"}, "type": "Feature"}], "type": "FeatureCollection"}