{"features": [{"geometry": {"coordinates": [65.33793, 38.54277], "type": "Point"}, "properties": {"arBW": "Ribat Khuwaran", "arTitle": "\u0631\u0628\u0627\u0637 \u062e\u0648\u0627\u0631\u0627\u0646", "arTitleOther": "\u0631\u0628\u0627\u0637 \u062e\u0648\u0627\u0631\u0627\u0646", "lat": "38.54277", "lon": "65.33793", "region": "Transoxiana", "searchNames": "Ribat Khuwaran", "topType": "waystations", "topTypeAlt": "ribat", "topURI": "RIBATKHUWARAN_653E385N_S_TRAN", "translitTitle": "Rib\u0101\u1e6d \u1e2auw\u0101r\u0101n", "translitTitleOther": "Rib\u0101\u1e6d \u1e2auw\u0101r\u0101n"}, "type": "Feature"}], "type": "FeatureCollection"}