{"features": [{"geometry": {"coordinates": [56.45466, 33.73469], "type": "Point"}, "properties": {"arBW": "Ribat Khuran, Ribat Kuran", "arTitle": "\u0631\u0628\u0627\u0637 \u062e\u0648\u0631\u0627\u0646", "arTitleOther": "\u0631\u0628\u0627\u0637 \u062e\u0648\u0631\u0627\u0646\u060c \u0631\u0628\u0627\u0637 \u0643\u0648\u0631\u0627\u0646", "lat": "33.73469", "lon": "56.45466", "region": "Mafaza", "searchNames": "Ribat Khuran, Ribat Kuran", "topType": "waystations", "topTypeAlt": "etape", "topURI": "RIBATKHURAN_564E337N_S_MAFA", "translitTitle": "Rib\u0101\u1e6d \u1e2a\u016br\u0101n", "translitTitleOther": "Rib\u0101\u1e6d \u1e2a\u016br\u0101n, Rib\u0101\u1e6d K\u016br\u0101n"}, "type": "Feature"}], "type": "FeatureCollection"}