{"features": [{"geometry": {"coordinates": [62.82511, 40.18541], "type": "Point"}, "properties": {"arBW": "Ribat Tughan", "arTitle": "\u0631\u0628\u0627\u0637 \u0637\u063a\u0627\u0646", "arTitleOther": "\u0631\u0628\u0627\u0637 \u0637\u063a\u0627\u0646", "lat": "40.18541", "lon": "62.82511", "region": "Transoxiana", "searchNames": "Ribat Tughan", "topType": "waystations", "topTypeAlt": "ribat", "topURI": "RIBATTUGHAN_628E401N_S_TRAN", "translitTitle": "Rib\u0101\u1e6d \u1e6cu\u0121\u0101n", "translitTitleOther": "Rib\u0101\u1e6d \u1e6cu\u0121\u0101n"}, "type": "Feature"}], "type": "FeatureCollection"}