{"features": [{"geometry": {"coordinates": [35.07899, 31.57487], "type": "Point"}, "properties": {"arBW": "RoutPoint0103", "arTitle": "RoutPoint0103", "arTitleOther": "RoutPoint0103", "lat": "31.57487", "lon": "35.07899", "region": "noData", "searchNames": "RoutPoint0103", "topType": "xroads", "topTypeAlt": "rPoint", "topURI": "ROUTPOINT0103_350E315N_O_NODA", "translitTitle": "RoutPoint0103", "translitTitleOther": "RoutPoint0103"}, "type": "Feature"}], "type": "FeatureCollection"}