{"features": [{"geometry": {"coordinates": [15.30735, 31.26948], "type": "Point"}, "properties": {"arBW": "RoutPoint1301", "arTitle": "RoutPoint1301", "arTitleOther": "RoutPoint1301", "lat": "31.26948", "lon": "15.30735", "region": "noData", "searchNames": "RoutPoint1301", "topType": "xroads", "topTypeAlt": "rPoint", "topURI": "ROUTPOINT1301_153E312N_O_NODA", "translitTitle": "RoutPoint1301", "translitTitleOther": "RoutPoint1301"}, "type": "Feature"}], "type": "FeatureCollection"}