{"features": [{"geometry": {"coordinates": [-5.18598, 37.50854], "type": "Point"}, "properties": {"arBW": "RoutPoint1405", "arTitle": "RoutPoint1405", "arTitleOther": "RoutPoint1405", "lat": "37.50854", "lon": "-5.18598", "region": "noData", "searchNames": "RoutPoint1405", "topType": "xroads", "topTypeAlt": "rPoint", "topURI": "ROUTPOINT1405_051W375N_O_NODA", "translitTitle": "RoutPoint1405", "translitTitleOther": "RoutPoint1405"}, "type": "Feature"}], "type": "FeatureCollection"}