{"features": [{"geometry": {"coordinates": [43.12845, 16.10818], "type": "Point"}, "properties": {"arBW": "RoutPoint0803", "arTitle": "RoutPoint0803", "arTitleOther": "RoutPoint0803", "lat": "16.10818", "lon": "43.12845", "region": "noData", "searchNames": "RoutPoint0803", "topType": "xroads", "topTypeAlt": "rPoint", "topURI": "ROUTPOINT0803_431E161N_O_NODA", "translitTitle": "RoutPoint0803", "translitTitleOther": "RoutPoint0803"}, "type": "Feature"}], "type": "FeatureCollection"}