{"features": [{"geometry": {"coordinates": [69.25665, 38.13029], "type": "Point"}, "properties": {"arBW": "RoutPoint1710", "arTitle": "RoutPoint1710", "arTitleOther": "RoutPoint1710", "lat": "38.13029", "lon": "69.25665", "region": "noData", "searchNames": "RoutPoint1710", "topType": "xroads", "topTypeAlt": "rPoint", "topURI": "ROUTPOINT1710_692E381N_O_NODA", "translitTitle": "RoutPoint1710", "translitTitleOther": "RoutPoint1710"}, "type": "Feature"}], "type": "FeatureCollection"}