{"features": [{"geometry": {"coordinates": [63.9644, 39.96155], "type": "Point"}, "properties": {"arBW": "RoutPoint1722", "arTitle": "RoutPoint1722", "arTitleOther": "RoutPoint1722", "lat": "39.96155", "lon": "63.96440", "region": "noData", "searchNames": "RoutPoint1722", "topType": "xroads", "topTypeAlt": "rPoint", "topURI": "ROUTPOINT1722_639E399N_O_NODA", "translitTitle": "RoutPoint1722", "translitTitleOther": "RoutPoint1722"}, "type": "Feature"}], "type": "FeatureCollection"}