{"features": [{"geometry": {"coordinates": [47.61548, 40.73903], "type": "Point"}, "properties": {"arBW": "RoutPoint1613", "arTitle": "RoutPoint1613", "arTitleOther": "RoutPoint1613", "lat": "40.73903", "lon": "47.61548", "region": "noData", "searchNames": "RoutPoint1613", "topType": "xroads", "topTypeAlt": "rPoint", "topURI": "ROUTPOINT1613_476E407N_O_NODA", "translitTitle": "RoutPoint1613", "translitTitleOther": "RoutPoint1613"}, "type": "Feature"}], "type": "FeatureCollection"}