{"features": [{"geometry": {"coordinates": [69.80863, 30.08179], "type": "Point"}, "properties": {"arBW": "RoutPoint1904", "arTitle": "RoutPoint1904", "arTitleOther": "RoutPoint1904", "lat": "30.08179", "lon": "69.80863", "region": "noData", "searchNames": "RoutPoint1904", "topType": "xroads", "topTypeAlt": "rPoint", "topURI": "ROUTPOINT1904_698E300N_O_NODA", "translitTitle": "RoutPoint1904", "translitTitleOther": "RoutPoint1904"}, "type": "Feature"}], "type": "FeatureCollection"}