{"features": [{"geometry": {"coordinates": [57.9121, 32.63282], "type": "Point"}, "properties": {"arBW": "RoutPoint0606", "arTitle": "RoutPoint0606", "arTitleOther": "RoutPoint0606", "lat": "32.63282", "lon": "57.91210", "region": "noData", "searchNames": "RoutPoint0606", "topType": "xroads", "topTypeAlt": "rPoint", "topURI": "ROUTPOINT0606_579E326N_O_NODA", "translitTitle": "RoutPoint0606", "translitTitleOther": "RoutPoint0606"}, "type": "Feature"}], "type": "FeatureCollection"}