{"features": [{"geometry": {"coordinates": [30.91381, 30.3215], "type": "Point"}, "properties": {"arBW": "RoutPoint1004", "arTitle": "RoutPoint1004", "arTitleOther": "RoutPoint1004", "lat": "30.32150", "lon": "30.91381", "region": "noData", "searchNames": "RoutPoint1004", "topType": "xroads", "topTypeAlt": "rPoint", "topURI": "ROUTPOINT1004_309E303N_O_NODA", "translitTitle": "RoutPoint1004", "translitTitleOther": "RoutPoint1004"}, "type": "Feature"}], "type": "FeatureCollection"}