{"features": [{"geometry": {"coordinates": [27.19216, 61.5595], "type": "Point"}, "properties": {"arBW": "RoutPoint1910", "arTitle": "RoutPoint1910", "arTitleOther": "RoutPoint1910", "lat": "27.19216", "lon": "61.55950", "region": "noData", "searchNames": "RoutPoint1910", "topType": "xroads", "topTypeAlt": "rPoint", "topURI": "ROUTPOINT1910_615E271N_O_NODA", "translitTitle": "RoutPoint1910", "translitTitleOther": "RoutPoint1910"}, "type": "Feature"}], "type": "FeatureCollection"}