{"features": [{"geometry": {"coordinates": [69.66363, 40.26668], "type": "Point"}, "properties": {"arBW": "RoutPoint1726", "arTitle": "RoutPoint1726", "arTitleOther": "RoutPoint1726", "lat": "40.26668", "lon": "69.66363", "region": "noData", "searchNames": "RoutPoint1726", "topType": "xroads", "topTypeAlt": "rPoint", "topURI": "ROUTPOINT1726_696E402N_O_NODA", "translitTitle": "RoutPoint1726", "translitTitleOther": "RoutPoint1726"}, "type": "Feature"}], "type": "FeatureCollection"}