{"features": [{"geometry": {"coordinates": [35.3527, 31.33329], "type": "Point"}, "properties": {"arBW": "RoutPoint0102", "arTitle": "RoutPoint0102", "arTitleOther": "RoutPoint0102", "lat": "31.33329", "lon": "35.35270", "region": "noData", "searchNames": "RoutPoint0102", "topType": "xroads", "topTypeAlt": "rPoint", "topURI": "ROUTPOINT0102_353E313N_O_NODA", "translitTitle": "RoutPoint0102", "translitTitleOther": "RoutPoint0102"}, "type": "Feature"}], "type": "FeatureCollection"}