{"features": [{"geometry": {"coordinates": [39.28285, 36.4229], "type": "Point"}, "properties": {"arBW": "RoutPoint0203", "arTitle": "RoutPoint0203", "arTitleOther": "RoutPoint0203", "lat": "36.42290", "lon": "39.28285", "region": "noData", "searchNames": "RoutPoint0203", "topType": "xroads", "topTypeAlt": "rPoint", "topURI": "ROUTPOINT0203_392E364N_O_NODA", "translitTitle": "RoutPoint0203", "translitTitleOther": "RoutPoint0203"}, "type": "Feature"}], "type": "FeatureCollection"}