{"features": [{"geometry": {"coordinates": [66.785, 27.77717], "type": "Point"}, "properties": {"arBW": "RoutPoint1912", "arTitle": "RoutPoint1912", "arTitleOther": "RoutPoint1912", "lat": "27.77717", "lon": "66.78500", "region": "noData", "searchNames": "RoutPoint1912", "topType": "xroads", "topTypeAlt": "rPoint", "topURI": "ROUTPOINT1912_667E277N_O_NODA", "translitTitle": "RoutPoint1912", "translitTitleOther": "RoutPoint1912"}, "type": "Feature"}], "type": "FeatureCollection"}