{"features": [{"geometry": {"coordinates": [57.72912, 22.84241], "type": "Point"}, "properties": {"arBW": "RoutPoint0707", "arTitle": "RoutPoint0707", "arTitleOther": "RoutPoint0707", "lat": "22.84241", "lon": "57.72912", "region": "noData", "searchNames": "RoutPoint0707", "topType": "xroads", "topTypeAlt": "rPoint", "topURI": "ROUTPOINT0707_577E228N_O_NODA", "translitTitle": "RoutPoint0707", "translitTitleOther": "RoutPoint0707"}, "type": "Feature"}], "type": "FeatureCollection"}