{"features": [{"geometry": {"coordinates": [35.39121, 31.83503], "type": "Point"}, "properties": {"arBW": "RoutPoint0114", "arTitle": "RoutPoint0114", "arTitleOther": "RoutPoint0114", "lat": "31.83503", "lon": "35.39121", "region": "noData", "searchNames": "RoutPoint0114", "topType": "xroads", "topTypeAlt": "rPoint", "topURI": "ROUTPOINT0114_353E318N_O_NODA", "translitTitle": "RoutPoint0114", "translitTitleOther": "RoutPoint0114"}, "type": "Feature"}], "type": "FeatureCollection"}