{"features": [{"geometry": {"coordinates": [47.11116, 43.32408], "type": "Point"}, "properties": {"arBW": "RoutPoint1801", "arTitle": "RoutPoint1801", "arTitleOther": "RoutPoint1801", "lat": "43.32408", "lon": "47.11116", "region": "noData", "searchNames": "RoutPoint1801", "topType": "xroads", "topTypeAlt": "rPoint", "topURI": "ROUTPOINT1801_471E433N_O_NODA", "translitTitle": "RoutPoint1801", "translitTitleOther": "RoutPoint1801"}, "type": "Feature"}], "type": "FeatureCollection"}