{"features": [{"geometry": {"coordinates": [39.00238, 36.11144], "type": "Point"}, "properties": {"arBW": "RoutPoint0204", "arTitle": "RoutPoint0204", "arTitleOther": "RoutPoint0204", "lat": "36.11144", "lon": "39.00238", "region": "noData", "searchNames": "RoutPoint0204", "topType": "xroads", "topTypeAlt": "rPoint", "topURI": "ROUTPOINT0204_390E361N_O_NODA", "translitTitle": "RoutPoint0204", "translitTitleOther": "RoutPoint0204"}, "type": "Feature"}], "type": "FeatureCollection"}