{"features": [{"geometry": {"coordinates": [51.10802, 35.28295], "type": "Point"}, "properties": {"arBW": "RoutPoint0504", "arTitle": "RoutPoint0504", "arTitleOther": "RoutPoint0504", "lat": "35.28295", "lon": "51.10802", "region": "noData", "searchNames": "RoutPoint0504", "topType": "xroads", "topTypeAlt": "rPoint", "topURI": "ROUTPOINT0504_511E352N_O_NODA", "translitTitle": "RoutPoint0504", "translitTitleOther": "RoutPoint0504"}, "type": "Feature"}], "type": "FeatureCollection"}