{"features": [{"geometry": {"coordinates": [49.1718, 34.04348], "type": "Point"}, "properties": {"arBW": "RoutPoint0510", "arTitle": "RoutPoint0510", "arTitleOther": "RoutPoint0510", "lat": "34.04348", "lon": "49.17180", "region": "noData", "searchNames": "RoutPoint0510", "topType": "xroads", "topTypeAlt": "rPoint", "topURI": "ROUTPOINT0510_491E340N_O_NODA", "translitTitle": "RoutPoint0510", "translitTitleOther": "RoutPoint0510"}, "type": "Feature"}], "type": "FeatureCollection"}