{"features": [{"geometry": {"coordinates": [-0.59001, 32.74875], "type": "Point"}, "properties": {"arBW": "RoutPoint1202", "arTitle": "RoutPoint1202", "arTitleOther": "RoutPoint1202", "lat": "32.74875", "lon": "-0.59001", "region": "noData", "searchNames": "RoutPoint1202", "topType": "xroads", "topTypeAlt": "rPoint", "topURI": "ROUTPOINT1202_005W327N_O_NODA", "translitTitle": "RoutPoint1202", "translitTitleOther": "RoutPoint1202"}, "type": "Feature"}], "type": "FeatureCollection"}