{"features": [{"geometry": {"coordinates": [56.3654, 27.24617], "type": "Point"}, "properties": {"arBW": "RoutPoint0604", "arTitle": "RoutPoint0604", "arTitleOther": "RoutPoint0604", "lat": "27.24617", "lon": "56.36540", "region": "noData", "searchNames": "RoutPoint0604", "topType": "xroads", "topTypeAlt": "rPoint", "topURI": "ROUTPOINT0604_563E272N_O_NODA", "translitTitle": "RoutPoint0604", "translitTitleOther": "RoutPoint0604"}, "type": "Feature"}], "type": "FeatureCollection"}