{"features": [{"geometry": {"coordinates": [47.45392, 30.90107], "type": "Point"}, "properties": {"arBW": "RoutPoint0302", "arTitle": "RoutPoint0302", "arTitleOther": "RoutPoint0302", "lat": "30.90107", "lon": "47.45392", "region": "noData", "searchNames": "RoutPoint0302", "topType": "xroads", "topTypeAlt": "rPoint", "topURI": "ROUTPOINT0302_474E309N_O_NODA", "translitTitle": "RoutPoint0302", "translitTitleOther": "RoutPoint0302"}, "type": "Feature"}], "type": "FeatureCollection"}