{"features": [{"geometry": {"coordinates": [44.37876, 14.31533], "type": "Point"}, "properties": {"arBW": "RoutPoint0801", "arTitle": "RoutPoint0801", "arTitleOther": "RoutPoint0801", "lat": "14.31533", "lon": "44.37876", "region": "noData", "searchNames": "RoutPoint0801", "topType": "xroads", "topTypeAlt": "rPoint", "topURI": "ROUTPOINT0801_443E143N_O_NODA", "translitTitle": "RoutPoint0801", "translitTitleOther": "RoutPoint0801"}, "type": "Feature"}], "type": "FeatureCollection"}