{"features": [{"geometry": {"coordinates": [34.67797, 31.83292], "type": "Point"}, "properties": {"arBW": "RoutPoint0111", "arTitle": "RoutPoint0111", "arTitleOther": "RoutPoint0111", "lat": "31.83292", "lon": "34.67797", "region": "noData", "searchNames": "RoutPoint0111", "topType": "xroads", "topTypeAlt": "rPoint", "topURI": "ROUTPOINT0111_346E318N_O_NODA", "translitTitle": "RoutPoint0111", "translitTitleOther": "RoutPoint0111"}, "type": "Feature"}], "type": "FeatureCollection"}