{"features": [{"geometry": {"coordinates": [48.39263, 34.62225], "type": "Point"}, "properties": {"arBW": "Rudhrawar", "arTitle": "\u0631\u0630\u0631\u0627\u0648\u0631", "arTitleOther": "\u0631\u0630\u0631\u0627\u0648\u0631", "lat": "34.62225", "lon": "48.39263", "region": "Jibal", "searchNames": "Rudhrawar", "topType": "towns", "topTypeAlt": "cite", "topURI": "RUDHRAWAR_483E346N_S_JIBA", "translitTitle": "Ru\u1e0fr\u0101war", "translitTitleOther": "Ru\u1e0fr\u0101war"}, "type": "Feature"}], "type": "FeatureCollection"}