{"features": [{"geometry": {"coordinates": [39.23589, 24.01966], "type": "Point"}, "properties": {"arBW": "Ruwaytha", "arTitle": "\u0631\u0648\u064a\u062b\u0629", "arTitleOther": "\u0631\u0648\u064a\u062b\u0629", "lat": "24.01966", "lon": "39.23589", "region": "Jazirat al-Arab", "searchNames": "Ruwaytha", "topType": "waystations", "topTypeAlt": "etape", "topURI": "RUWAYTHA_392E240N_S_JAZI", "translitTitle": "Ruway\u1e6fa\u0167", "translitTitleOther": "Ruway\u1e6fa\u0167"}, "type": "Feature"}], "type": "FeatureCollection"}