{"features": [{"geometry": {"coordinates": [12.48146, 32.78822], "type": "Point"}, "properties": {"arBW": "Sabra", "arTitle": "\u0635\u0628\u0631\u0629", "arTitleOther": "\u0635\u0628\u0631\u0629", "lat": "32.78822", "lon": "12.48146", "region": "Barqa", "searchNames": "Sabra", "topType": "towns", "topTypeAlt": "cite", "topURI": "SABRA_124E327N_S_BARQ", "translitTitle": "\u1e62abra\u0167", "translitTitleOther": "\u1e62abra\u0167"}, "type": "Feature"}], "type": "FeatureCollection"}