{"features": [{"geometry": {"coordinates": [43.76442, 16.9453], "type": "Point"}, "properties": {"arBW": "Sada", "arTitle": "\u0635\u0639\u062f\u0629", "arTitleOther": "\u0635\u0639\u062f\u0629", "lat": "16.94530", "lon": "43.76442", "region": "Yemen", "searchNames": "Sada", "topType": "towns", "topTypeAlt": "cite", "topURI": "SADA_437E169N_S_YEME", "translitTitle": "\u1e62a\u02bfda\u0167", "translitTitleOther": "\u1e62a\u02bfda\u0167"}, "type": "Feature"}], "type": "FeatureCollection"}