{"features": [{"geometry": {"coordinates": [50.4613, 29.96408], "type": "Point"}, "properties": {"arBW": "Sahik", "arTitle": "\u0635\u0627\u062d\u0643", "arTitleOther": "\u0635\u0627\u062d\u0643", "lat": "29.96408", "lon": "50.46130", "region": "Faris", "searchNames": "Sahik", "topType": "waystations", "topTypeAlt": "etape?", "topURI": "SAHIK_504E299N_S_FARI", "translitTitle": "\u1e62\u0101\u1e25ik", "translitTitleOther": "\u1e62\u0101\u1e25ik"}, "type": "Feature"}], "type": "FeatureCollection"}