{"features": [{"geometry": {"coordinates": [50.42781, 30.9971], "type": "Point"}, "properties": {"arBW": "Sardan", "arTitle": "\u0633\u0631\u062f\u0627\u0646", "arTitleOther": "\u0633\u0631\u062f\u0627\u0646", "lat": "30.99710", "lon": "50.42781", "region": "Faris", "searchNames": "Sardan", "topType": "regions", "topTypeAlt": "region", "topURI": "SARDAN_504E309N_R_FARI", "translitTitle": "Sard\u0101n", "translitTitleOther": "Sard\u0101n"}, "type": "Feature"}], "type": "FeatureCollection"}