{"features": [{"geometry": {"coordinates": [75.26356, 42.80107], "type": "Point"}, "properties": {"arBW": "Sarigh", "arTitle": "\u0633\u0627\u0631\u063a", "arTitleOther": "\u0633\u0627\u0631\u063a", "lat": "42.80107", "lon": "75.26356", "region": "Transoxiana", "searchNames": "Sarigh", "topType": "waystations", "topTypeAlt": "etape", "topURI": "SARIGH_752E428N_S_TRAN", "translitTitle": "S\u0101ri\u0121", "translitTitleOther": "S\u0101ri\u0121"}, "type": "Feature"}], "type": "FeatureCollection"}