{"features": [{"geometry": {"coordinates": [44.66088, 42.2133], "type": "Point"}, "properties": {"arBW": "al-Sarir", "arTitle": "\ufb50\u0644\u0633\u0631\u064a\u0631", "arTitleOther": "\ufb50\u0644\u0633\u0631\u064a\u0631", "lat": "42.21330", "lon": "44.66088", "region": "Khazar", "searchNames": "al-Sarir", "topType": "regions", "topTypeAlt": "region", "topURI": "SARIR_446E422N_R_KHAZ", "translitTitle": "al-Sar\u012br", "translitTitleOther": "al-Sar\u012br"}, "type": "Feature"}], "type": "FeatureCollection"}