{"features": [{"geometry": {"coordinates": [45.58857, 13.98039], "type": "Point"}, "properties": {"arBW": "al-Sarw", "arTitle": "\ufb50\u0644\u0633\u0631\u0648", "arTitleOther": "\ufb50\u0644\u0633\u0631\u0648", "lat": "13.98039", "lon": "45.58857", "region": "Yemen", "searchNames": "al-Sarw", "topType": "regions", "topTypeAlt": "region", "topURI": "SARW_455E139N_R_YEME", "translitTitle": "al-Sarw", "translitTitleOther": "al-Sarw"}, "type": "Feature"}], "type": "FeatureCollection"}