{"features": [{"geometry": {"coordinates": [30.72312, 31.08986], "type": "Point"}, "properties": {"arBW": "Shabas", "arTitle": "\u0634\u0628\u0627\u0633", "arTitleOther": "\u0634\u0628\u0627\u0633", "lat": "31.08986", "lon": "30.72312", "region": "Egypt", "searchNames": "Shabas", "topType": "regions", "topTypeAlt": "district", "topURI": "SHABAS_307E310N_R_EGYP", "translitTitle": "\u0160ab\u0101s", "translitTitleOther": "\u0160ab\u0101s"}, "type": "Feature"}], "type": "FeatureCollection"}