{"features": [{"geometry": {"coordinates": [51.51624, 29.83157], "type": "Point"}, "properties": {"arBW": "Shahrastan, Sabur", "arTitle": "\u0634\u0647\u0631\u0633\u062a\u0627\u0646", "arTitleOther": "\u0634\u0647\u0631\u0633\u062a\u0627\u0646\u060c \u0633\u0627\u0628\u0648\u0631", "lat": "29.83157", "lon": "51.51624", "region": "Faris", "searchNames": "Shahrastan, Sabur", "topType": "capitals", "topTypeAlt": "capitale", "topURI": "SHAHRASTAN_515E298N_S_FARI", "translitTitle": "\u0160ahrast\u0101n", "translitTitleOther": "\u0160ahrast\u0101n, S\u0101b\u016br"}, "type": "Feature"}], "type": "FeatureCollection"}