{"features": [{"geometry": {"coordinates": [46.06157, 40.99521], "type": "Point"}, "properties": {"arBW": "Shamkur", "arTitle": "\u0634\u0645\u0643\u0648\u0631", "arTitleOther": "\u0634\u0645\u0643\u0648\u0631", "lat": "40.99521", "lon": "46.06157", "region": "Rihab", "searchNames": "Shamkur", "topType": "towns", "topTypeAlt": "cite", "topURI": "SHAMKUR_460E409N_S_RIHA", "translitTitle": "\u0160amk\u016br", "translitTitleOther": "\u0160amk\u016br"}, "type": "Feature"}], "type": "FeatureCollection"}