{"features": [{"geometry": {"coordinates": [-0.43734, 39.16483], "type": "Point"}, "properties": {"arBW": "al-Shaqr", "arTitle": "\ufb50\u0644\u0634\u0642\u0631", "arTitleOther": "\ufb50\u0644\u0634\u0642\u0631", "lat": "39.16483", "lon": "-0.43734", "region": "Andalus", "searchNames": "al-Shaqr", "topType": "villages", "topTypeAlt": "localite", "topURI": "SHAQR_004W391N_S_ANDA", "translitTitle": "al-\u0160aqr", "translitTitleOther": "al-\u0160aqr"}, "type": "Feature"}], "type": "FeatureCollection"}