{"features": [{"geometry": {"coordinates": [43.95691, 13.61931], "type": "Point"}, "properties": {"arBW": "Sharab", "arTitle": "\u0634\u0631\u0639\u0628", "arTitleOther": "\u0634\u0631\u0639\u0628", "lat": "13.61931", "lon": "43.95691", "region": "Yemen", "searchNames": "Sharab", "topType": "regions", "topTypeAlt": "region", "topURI": "SHARAB_439E136N_R_YEME", "translitTitle": "\u0160ar\u02bfab", "translitTitleOther": "\u0160ar\u02bfab"}, "type": "Feature"}], "type": "FeatureCollection"}