{"features": [{"geometry": {"coordinates": [69.18357, 41.27136], "type": "Point"}, "properties": {"arBW": "al-Shash, Bilad al-Shash", "arTitle": "\ufb50\u0644\u0634\u0627\u0634", "arTitleOther": "\ufb50\u0644\u0634\u0627\u0634\u060c \u0628\u0644\u0627\u062f \ufb50\u0644\u0634\u0627\u0634", "lat": "41.27136", "lon": "69.18357", "region": "Transoxiana", "searchNames": "al-Shash, Bilad al-Shash", "topType": "regions", "topTypeAlt": "region", "topURI": "SHASH_691E412N_R_TRAN", "translitTitle": "al-\u0160\u0101\u0161", "translitTitleOther": "al-\u0160\u0101\u0161, Bil\u0101d al-\u0160\u0101\u0161"}, "type": "Feature"}], "type": "FeatureCollection"}