{"features": [{"geometry": {"coordinates": [31.87094, 31.40557], "type": "Point"}, "properties": {"arBW": "Shata", "arTitle": "\u0634\u0637\u0627", "arTitleOther": "\u0634\u0637\u0627", "lat": "31.40557", "lon": "31.87094", "region": "Egypt", "searchNames": "Shata", "topType": "towns", "topTypeAlt": "cite", "topURI": "SHATA_318E314N_S_EGYP", "translitTitle": "\u0160a\u1e6d\u0101", "translitTitleOther": "\u0160a\u1e6d\u0101"}, "type": "Feature"}], "type": "FeatureCollection"}