{"features": [{"geometry": {"coordinates": [38.96551, -0.52276], "type": "Point"}, "properties": {"arBW": "Shatiba", "arTitle": "\u0634\u0627\u062a\u0628\u0629", "arTitleOther": "\u0634\u0627\u062a\u0628\u0629", "lat": "38.96551", "lon": "-0.52276", "region": "Andalus", "searchNames": "Shatiba", "topType": "towns", "topTypeAlt": "cite", "topURI": "SHATIBA_005W389N_S_ANDA", "translitTitle": "\u0160\u0101tiba\u0167", "translitTitleOther": "\u0160\u0101tiba\u0167"}, "type": "Feature"}], "type": "FeatureCollection"}