{"features": [{"geometry": {"coordinates": [67.09946, 37.02037], "type": "Point"}, "properties": {"arBW": "Shawkard, Siyahjird", "arTitle": "\u0634\u0648\u0643\u0631\u062f", "arTitleOther": "\u0634\u0648\u0643\u0631\u062f\u060c \u0633\u064a\u0627\u0647\u062c\u0631\u062f", "lat": "37.02037", "lon": "67.09946", "region": "Khurasan", "searchNames": "Shawkard, Siyahjird", "topType": "villages", "topTypeAlt": "localite", "topURI": "SHAWKARD_670E370N_S_KHUR", "translitTitle": "\u0160awkard", "translitTitleOther": "\u0160awkard, Siy\u0101h\u01e7ird"}, "type": "Feature"}], "type": "FeatureCollection"}