{"features": [{"geometry": {"coordinates": [67.21506, 39.33812], "type": "Point"}, "properties": {"arBW": "al-Shawdhar", "arTitle": "\ufb50\u0644\u0634\u0627\u0648\u0630\u0627\u0631", "arTitleOther": "\ufb50\u0644\u0634\u0627\u0648\u0630\u0627\u0631", "lat": "39.33812", "lon": "67.21506", "region": "Transoxiana", "searchNames": "al-Shawdhar", "topType": "regions", "topTypeAlt": "region", "topURI": "SHAWDHAR_672E393N_R_TRAN", "translitTitle": "al-\u0160\u0101w\u1e0f\u0101r", "translitTitleOther": "al-\u0160\u0101w\u1e0f\u0101r"}, "type": "Feature"}], "type": "FeatureCollection"}