{"features": [{"geometry": {"coordinates": [48.57208, 15.92483], "type": "Point"}, "properties": {"arBW": "Shibam", "arTitle": "\u0634\u0628\u0627\u0645", "arTitleOther": "\u0634\u0628\u0627\u0645", "lat": "15.92483", "lon": "48.57208", "region": "Yemen", "searchNames": "Shibam", "topType": "towns", "topTypeAlt": "cite", "topURI": "SHIBAM_485E159N_S_YEME", "translitTitle": "\u0160ib\u0101m", "translitTitleOther": "\u0160ib\u0101m"}, "type": "Feature"}], "type": "FeatureCollection"}