{"features": [{"geometry": {"coordinates": [48.75339, 41.11585], "type": "Point"}, "properties": {"arBW": "Shirwan, Sharwan", "arTitle": "\u0634\u0631\u0648\u0627\u0646", "arTitleOther": "\u0634\u0631\u0648\u0627\u0646\u060c \u0634\u0631\u0648\u0627\u0646", "lat": "41.11585", "lon": "48.75339", "region": "Rihab", "searchNames": "Shirwan, Sharwan", "topType": "towns", "topTypeAlt": "cite", "topURI": "SHIRWAN_487E411N_S_RIHA", "translitTitle": "\u0160irw\u0101n", "translitTitleOther": "\u0160irw\u0101n, \u0160arw\u0101n"}, "type": "Feature"}], "type": "FeatureCollection"}