{"features": [{"geometry": {"coordinates": [41.51032, 22.44819], "type": "Point"}, "properties": {"arBW": "al-Shubayka", "arTitle": "\ufb50\u0644\u0634\u0628\u064a\u0643\u0629", "arTitleOther": "\ufb50\u0644\u0634\u0628\u064a\u0643\u0629", "lat": "22.44819", "lon": "41.51032", "region": "Jazirat al-Arab", "searchNames": "al-Shubayka", "topType": "waystations", "topTypeAlt": "etape", "topURI": "SHUBAYKA_415E224N_S_JAZI", "translitTitle": "al-\u0160ubayka\u0167", "translitTitleOther": "al-\u0160ubayka\u0167"}, "type": "Feature"}], "type": "FeatureCollection"}