{"features": [{"geometry": {"coordinates": [68.82268, 38.58166], "type": "Point"}, "properties": {"arBW": "Shuman", "arTitle": "\u0634\u0648\u0645\u0627\u0646", "arTitleOther": "\u0634\u0648\u0645\u0627\u0646", "lat": "38.58166", "lon": "68.82268", "region": "Transoxiana", "searchNames": "Shuman", "topType": "towns", "topTypeAlt": "cite", "topURI": "SHUMAN_688E385N_S_TRAN", "translitTitle": "\u0160\u016bm\u0101n", "translitTitleOther": "\u0160\u016bm\u0101n"}, "type": "Feature"}], "type": "FeatureCollection"}