{"features": [{"geometry": {"coordinates": [57.78936, 31.27116], "type": "Point"}, "properties": {"arBW": "Shurirudh, Shur Duwazda", "arTitle": "\u0634\u0648\u0631\u0631\u0648\u0630", "arTitleOther": "\u0634\u0648\u0631\u0631\u0648\u0630\u060c \u0634\u0648\u0631 \u062f\u0648\u0627\u0632\u062f\u0629", "lat": "31.27116", "lon": "57.78936", "region": "Mafaza", "searchNames": "Shurirudh, Shur Duwazda", "topType": "waystations", "topTypeAlt": "etape", "topURI": "SHURIRUDH_577E312N_S_MAFA", "translitTitle": "\u0160\u016brir\u016b\u1e0f", "translitTitleOther": "\u0160\u016brir\u016b\u1e0f, \u0160\u016br Duw\u0101zda\u0167"}, "type": "Feature"}], "type": "FeatureCollection"}