{"features": [{"geometry": {"coordinates": [63.3995, 40.05505], "type": "Point"}, "properties": {"arBW": "Shurukh", "arTitle": "\u0634\u0631\u0648\u062e", "arTitleOther": "\u0634\u0631\u0648\u062e", "lat": "40.05505", "lon": "63.39950", "region": "Transoxiana", "searchNames": "Shurukh", "topType": "waystations", "topTypeAlt": "etape", "topURI": "SHURUKH_633E400N_S_TRAN", "translitTitle": "\u0160ur\u016b\u1e2b", "translitTitleOther": "\u0160ur\u016b\u1e2b"}, "type": "Feature"}], "type": "FeatureCollection"}