{"features": [{"geometry": {"coordinates": [71.21396, 39.97506], "type": "Point"}, "properties": {"arBW": "Sukh, Suj", "arTitle": "\u0633\u0648\u062e", "arTitleOther": "\u0633\u0648\u062e\u060c \u0633\u0648\u062c", "lat": "39.97506", "lon": "71.21396", "region": "Transoxiana", "searchNames": "Sukh, Suj", "topType": "towns", "topTypeAlt": "cite", "topURI": "SUKH_712E399N_S_TRAN", "translitTitle": "S\u016b\u1e2b", "translitTitleOther": "S\u016b\u1e2b, S\u016b\u01e7"}, "type": "Feature"}], "type": "FeatureCollection"}