{"features": [{"geometry": {"coordinates": [48.5239, 30.94139], "type": "Point"}, "properties": {"arBW": "Suq al-Arbaa", "arTitle": "\u0633\u0648\u0642 \ufb50\u0644\u0623\u0631\u0628\u0639\u0627\u0621", "arTitleOther": "\u0633\u0648\u0642 \ufb50\u0644\u0623\u0631\u0628\u0639\u0627\u0621", "lat": "30.94139", "lon": "48.52390", "region": "Khuzistan", "searchNames": "Suq al-Arbaa", "topType": "towns", "topTypeAlt": "cite", "topURI": "SUQARBAA_485E309N_S_KHUZ", "translitTitle": "S\u016bq al-Arba\u02bf\u0101\u02be", "translitTitleOther": "S\u016bq al-Arba\u02bf\u0101\u02be"}, "type": "Feature"}], "type": "FeatureCollection"}