{"features": [{"geometry": {"coordinates": [44.29724, 32.48043], "type": "Point"}, "properties": {"arBW": "Suq Asad", "arTitle": "\u0633\u0648\u0642 \u0623\u0633\u062f", "arTitleOther": "\u0633\u0648\u0642 \u0623\u0633\u062f", "lat": "32.48043", "lon": "44.29724", "region": "Iraq", "searchNames": "Suq Asad", "topType": "villages", "topTypeAlt": "localite", "topURI": "SUQASAD_442E324N_S_IRAQ", "translitTitle": "S\u016bq Asad", "translitTitleOther": "S\u016bq Asad"}, "type": "Feature"}], "type": "FeatureCollection"}