{"features": [{"geometry": {"coordinates": [38.35433, 26.15916], "type": "Point"}, "properties": {"arBW": "Suqya Yazid, al-Suqya", "arTitle": "\u0633\u0642\u064a\u0627\u0621 \u064a\u0632\u064a\u062f", "arTitleOther": "\u0633\u0642\u064a\u0627\u0621 \u064a\u0632\u064a\u062f\u060c \ufb50\u0644\u0633\u0642\u064a\u0627\u0621", "lat": "26.15916", "lon": "38.35433", "region": "Jazirat al-Arab", "searchNames": "Suqya Yazid, al-Suqya", "topType": "towns", "topTypeAlt": "cite", "topURI": "SUQYAYAZID_383E261N_S_JAZI", "translitTitle": "Suqy\u0101\u02be Yaz\u012bd", "translitTitleOther": "Suqy\u0101\u02be Yaz\u012bd, al-Suqy\u0101\u02be"}, "type": "Feature"}], "type": "FeatureCollection"}