{"features": [{"geometry": {"coordinates": [50.02954, 35.0274], "type": "Point"}, "properties": {"arBW": "Susanqin, Susnaqin, Sunaqin", "arTitle": "\u0633\u0648\u0633\u0646\u0642\u064a\u0646", "arTitleOther": "\u0633\u0648\u0633\u0646\u0642\u064a\u0646\u060c \u0633\u0648\u0633\u0646\u0642\u064a\u0646\u060c \u0633\u0648\u0646\u0642\u064a\u0646", "lat": "35.02740", "lon": "50.02954", "region": "Jibal", "searchNames": "Susanqin, Susnaqin, Sunaqin", "topType": "waystations", "topTypeAlt": "etape", "topURI": "SUSANQIN_500E350N_S_JIBA", "translitTitle": "S\u016bsanq\u012bn", "translitTitleOther": "S\u016bsanq\u012bn, S\u016bsnaq\u012bn, S\u016bnaq\u012bn"}, "type": "Feature"}], "type": "FeatureCollection"}