{"features": [{"geometry": {"coordinates": [39.03019, 25.04884], "type": "Point"}, "properties": {"arBW": "al-Suwayda, al-Suwaydiyya", "arTitle": "\ufb50\u0644\u0633\u0648\u064a\u062f\u0627\u0621", "arTitleOther": "\ufb50\u0644\u0633\u0648\u064a\u062f\u0627\u0621\u060c \ufb50\u0644\u0633\u0648\u064a\u062f\u064a\u0629", "lat": "25.04884", "lon": "39.03019", "region": "Jazirat al-Arab", "searchNames": "al-Suwayda, al-Suwaydiyya", "topType": "villages", "topTypeAlt": "localite", "topURI": "SUWAYDA_390E250N_S_JAZI", "translitTitle": "al-Suwayd\u0101\u02be", "translitTitleOther": "al-Suwayd\u0101\u02be, al-Suwaydiyya\u0167"}, "type": "Feature"}], "type": "FeatureCollection"}