{"features": [{"geometry": {"coordinates": [46.33121, 38.06387], "type": "Point"}, "properties": {"arBW": "Tabriz", "arTitle": "\u062a\u0628\u0631\u064a\u0632", "arTitleOther": "\u062a\u0628\u0631\u064a\u0632", "lat": "38.06387", "lon": "46.33121", "region": "Rihab", "searchNames": "Tabriz", "topType": "towns", "topTypeAlt": "cite", "topURI": "TABRIZ_463E380N_S_RIHA", "translitTitle": "Tabr\u012bz", "translitTitleOther": "Tabr\u012bz"}, "type": "Feature"}], "type": "FeatureCollection"}