{"features": [{"geometry": {"coordinates": [38.28754, 34.54735], "type": "Point"}, "properties": {"arBW": "Tadmur", "arTitle": "\u062a\u062f\u0645\u0631", "arTitleOther": "\u062a\u062f\u0645\u0631", "lat": "34.54735", "lon": "38.28754", "region": "Sham", "searchNames": "Tadmur", "topType": "towns", "topTypeAlt": "cite", "topURI": "TADMUR_382E345N_S_SHAM", "translitTitle": "Tadmur", "translitTitleOther": "Tadmur"}, "type": "Feature"}], "type": "FeatureCollection"}