{"features": [{"geometry": {"coordinates": [42.49401, 36.36312], "type": "Point"}, "properties": {"arBW": "Tall Afar", "arTitle": "\u062a\u0644 \u0623\u0639\u0641\u0631", "arTitleOther": "\u062a\u0644 \u0623\u0639\u0641\u0631", "lat": "36.36312", "lon": "42.49401", "region": "Aqur", "searchNames": "Tall Afar", "topType": "towns", "topTypeAlt": "cite", "topURI": "TALLAFAR_424E363N_S_AQUR", "translitTitle": "Tall A\u02bffar", "translitTitleOther": "Tall A\u02bffar"}, "type": "Feature"}], "type": "FeatureCollection"}