{"features": [{"geometry": {"coordinates": [41.78238, 37.72559], "type": "Point"}, "properties": {"arBW": "Tall Fafan, Ayn Tall Fafan", "arTitle": "\u062a\u0644 \u0641\u0627\u0641\u0627\u0646", "arTitleOther": "\u062a\u0644 \u0641\u0627\u0641\u0627\u0646\u060c \u0639\u064a\u0646 \u062a\u0644 \u0641\u0627\u0641\u0627\u0646", "lat": "37.72559", "lon": "41.78238", "region": "Aqur", "searchNames": "Tall Fafan, Ayn Tall Fafan", "topType": "towns", "topTypeAlt": "cite", "topURI": "TALLFAFAN_417E377N_S_AQUR", "translitTitle": "Tall F\u0101f\u0101n", "translitTitleOther": "Tall F\u0101f\u0101n, \u02bfAyn Tall F\u0101f\u0101n"}, "type": "Feature"}], "type": "FeatureCollection"}