{"features": [{"geometry": {"coordinates": [54.05573, 36.7312], "type": "Point"}, "properties": {"arBW": "Tamisha, Tamisa", "arTitle": "\u0637\u0645\u064a\u0634\u0629", "arTitleOther": "\u0637\u0645\u064a\u0634\u0629\u060c \u0637\u0645\u064a\u0633\u0629", "lat": "36.73120", "lon": "54.05573", "region": "Daylam", "searchNames": "Tamisha, Tamisa", "topType": "towns", "topTypeAlt": "cite", "topURI": "TAMISHA_540E367N_S_DAYL", "translitTitle": "\u1e6cam\u012b\u0161a\u0167", "translitTitleOther": "\u1e6cam\u012b\u0161a\u0167, \u1e6cam\u012bsa\u0167"}, "type": "Feature"}], "type": "FeatureCollection"}