{"features": [{"geometry": {"coordinates": [31.54194, 31.04233], "type": "Point"}, "properties": {"arBW": "Tana", "arTitle": "\u062a\u0646\u0627", "arTitleOther": "\u062a\u0646\u0627", "lat": "31.04233", "lon": "31.54194", "region": "Egypt", "searchNames": "Tana", "topType": "towns", "topTypeAlt": "cite", "topURI": "TANA_315E310N_S_EGYP", "translitTitle": "Tan\u0101", "translitTitleOther": "Tan\u0101"}, "type": "Feature"}], "type": "FeatureCollection"}