{"features": [{"geometry": {"coordinates": [64.78279, 40.01136], "type": "Point"}, "properties": {"arBW": "al-Tawawis", "arTitle": "\ufb50\u0644\u0637\u0648\u0627\u0648\u064a\u0633", "arTitleOther": "\ufb50\u0644\u0637\u0648\u0627\u0648\u064a\u0633", "lat": "40.01136", "lon": "64.78279", "region": "Transoxiana", "searchNames": "al-Tawawis", "topType": "towns", "topTypeAlt": "canton", "topURI": "TAWAWIS_647E400N_S_TRAN", "translitTitle": "al-\u1e6caw\u0101w\u012bs", "translitTitleOther": "al-\u1e6caw\u0101w\u012bs"}, "type": "Feature"}], "type": "FeatureCollection"}