{"features": [{"geometry": {"coordinates": [44.17683, 13.97911], "type": "Point"}, "properties": {"arBW": "al-Thujja", "arTitle": "\ufb50\u0644\u062b\u062c\u0629", "arTitleOther": "\ufb50\u0644\u062b\u062c\u0629", "lat": "13.97911", "lon": "44.17683", "region": "Yemen", "searchNames": "al-Thujja", "topType": "regions", "topTypeAlt": "mikhlaf", "topURI": "THUJJA_441E139N_R_YEME", "translitTitle": "al-\u1e6eu\u01e7\u01e7a\u0167", "translitTitleOther": "al-\u1e6eu\u01e7\u01e7a\u0167"}, "type": "Feature"}], "type": "FeatureCollection"}