{"features": [{"geometry": {"coordinates": [43.19302, 18.1711], "type": "Point"}, "properties": {"arBW": "al-Thujja", "arTitle": "\ufb50\u0644\u062b\u062c\u0629", "arTitleOther": "\ufb50\u0644\u062b\u062c\u0629", "lat": "18.17110", "lon": "43.19302", "region": "Jazirat al-Arab", "searchNames": "al-Thujja", "topType": "waystations", "topTypeAlt": "etape", "topURI": "THUJJA_431E181N_S_JAZI", "translitTitle": "al-\u1e6eu\u01e7\u01e7a\u0167", "translitTitleOther": "al-\u1e6eu\u01e7\u01e7a\u0167"}, "type": "Feature"}], "type": "FeatureCollection"}