{"features": [{"geometry": {"coordinates": [40.86321, 37.40165], "type": "Point"}, "properties": {"arBW": "Thur Abdin", "arTitle": "\u062b\u0648\u0631 \u0639\u0628\u062f\u064a\u0646", "arTitleOther": "\u062b\u0648\u0631 \u0639\u0628\u062f\u064a\u0646", "lat": "37.40165", "lon": "40.86321", "region": "Aqur", "searchNames": "Thur Abdin", "topType": "towns", "topTypeAlt": "canton", "topURI": "THURABDIN_408E374N_S_AQUR", "translitTitle": "\u1e6e\u016br \u02bfAbd\u012bn", "translitTitleOther": "\u1e6e\u016br \u02bfAbd\u012bn"}, "type": "Feature"}], "type": "FeatureCollection"}