{"features": [{"geometry": {"coordinates": [32.22755, 31.21262], "type": "Point"}, "properties": {"arBW": "Tinnis", "arTitle": "\u062a\u0646\u064a\u0633", "arTitleOther": "\u062a\u0646\u064a\u0633", "lat": "31.21262", "lon": "32.22755", "region": "Egypt", "searchNames": "Tinnis", "topType": "towns", "topTypeAlt": "cite", "topURI": "TINNIS_322E312N_S_EGYP", "translitTitle": "Tinn\u012bs", "translitTitleOther": "Tinn\u012bs"}, "type": "Feature"}], "type": "FeatureCollection"}