{"features": [{"geometry": {"coordinates": [58.11679, 33.92591], "type": "Point"}, "properties": {"arBW": "Tun", "arTitle": "\u062a\u0648\u0646", "arTitleOther": "\u062a\u0648\u0646", "lat": "33.92591", "lon": "58.11679", "region": "Khurasan", "searchNames": "Tun", "topType": "towns", "topTypeAlt": "cite", "topURI": "TUN_581E339N_S_KHUR", "translitTitle": "T\u016bn", "translitTitleOther": "T\u016bn"}, "type": "Feature"}], "type": "FeatureCollection"}