{"features": [{"geometry": {"coordinates": [32.98745, 24.46534], "type": "Point"}, "properties": {"arBW": "Unbuwa, Unbuw", "arTitle": "\u0623\u0646\u0628\u0648\u0627", "arTitleOther": "\u0623\u0646\u0628\u0648\u0627\u060c \u0623\u0646\u0628\u0648", "lat": "24.46534", "lon": "32.98745", "region": "Egypt", "searchNames": "Unbuwa, Unbuw", "topType": "towns", "topTypeAlt": "cite", "topURI": "UNBUWA_329E244N_S_EGYP", "translitTitle": "Unbuw\u0101", "translitTitleOther": "Unbuw\u0101, Unbuw"}, "type": "Feature"}], "type": "FeatureCollection"}