{"features": [{"geometry": {"coordinates": [53.66217, 32.40568], "type": "Point"}, "properties": {"arBW": "Uqda", "arTitle": "\u0639\u0642\u062f\u0629", "arTitleOther": "\u0639\u0642\u062f\u0629", "lat": "32.40568", "lon": "53.66217", "region": "Faris", "searchNames": "Uqda", "topType": "towns", "topTypeAlt": "ville", "topURI": "UQDA_536E324N_S_FARI", "translitTitle": "\u02bfUqda\u0167", "translitTitleOther": "\u02bfUqda\u0167"}, "type": "Feature"}], "type": "FeatureCollection"}