{"features": [{"geometry": {"coordinates": [-5.98544, 34.45352], "type": "Point"}, "properties": {"arBW": "Wadi Sabu", "arTitle": "\u0648\u0627\u062f\u064a \u0633\u0628\u0648", "arTitleOther": "\u0648\u0627\u062f\u064a \u0633\u0628\u0648", "lat": "34.45352", "lon": "-5.98544", "region": "Maghrib", "searchNames": "Wadi Sabu", "topType": "waters", "topTypeAlt": "wadi", "topURI": "WADISABU_059W344N_W_MAGH", "translitTitle": "W\u0101d\u012b Sab\u016b", "translitTitleOther": "W\u0101d\u012b Sab\u016b"}, "type": "Feature"}], "type": "FeatureCollection"}