{"features": [{"geometry": {"coordinates": [35.47226, 30.33334], "type": "Point"}, "properties": {"arBW": "Wadi Musa", "arTitle": "\u0648\u0627\u062f\u064a \u0645\u0648\u0633\u0649", "arTitleOther": "\u0648\u0627\u062f\u064a \u0645\u0648\u0633\u0649", "lat": "30.33334", "lon": "35.47226", "region": "Sham", "searchNames": "Wadi Musa", "topType": "villages", "topTypeAlt": "village", "topURI": "WADIMUSA_354E303N_S_SHAM", "translitTitle": "W\u0101d\u012b M\u016bs\u00e1", "translitTitleOther": "W\u0101d\u012b M\u016bs\u00e1"}, "type": "Feature"}], "type": "FeatureCollection"}