{"features": [{"geometry": {"coordinates": [43.06403, 16.05227], "type": "Point"}, "properties": {"arBW": "Wadi Hayran", "arTitle": "\u0648\u0627\u062f\u064a \u062d\u064a\u0631\u0627\u0646", "arTitleOther": "\u0648\u0627\u062f\u064a \u062d\u064a\u0631\u0627\u0646", "lat": "16.05227", "lon": "43.06403", "region": "Yemen", "searchNames": "Wadi Hayran", "topType": "waters", "topTypeAlt": "wadi", "topURI": "WADIHAYRAN_430E160N_W_YEME", "translitTitle": "W\u0101d\u012b \u1e24ayr\u0101n", "translitTitleOther": "W\u0101d\u012b \u1e24ayr\u0101n"}, "type": "Feature"}], "type": "FeatureCollection"}