{"features": [{"geometry": {"coordinates": [-5.76527, 34.9938], "type": "Point"}, "properties": {"arBW": "Wadi Safdad", "arTitle": "\u0648\u0627\u062f\u064a \u0633\u0641\u062f\u062f", "arTitleOther": "\u0648\u0627\u062f\u064a \u0633\u0641\u062f\u062f", "lat": "34.99380", "lon": "-5.76527", "region": "Maghrib", "searchNames": "Wadi Safdad", "topType": "waters", "topTypeAlt": "wadi", "topURI": "WADISAFDAD_057W349N_W_MAGH", "translitTitle": "W\u0101d\u012b Safdad", "translitTitleOther": "W\u0101d\u012b Safdad"}, "type": "Feature"}], "type": "FeatureCollection"}