{"features": [{"geometry": {"coordinates": [-3.15111, 40.6491], "type": "Point"}, "properties": {"arBW": "Wadi al-Hijara", "arTitle": "\u0648\u0627\u062f\u064a \ufb50\u0644\u062d\u062c\u0627\u0631\u0629", "arTitleOther": "\u0648\u0627\u062f\u064a \ufb50\u0644\u062d\u062c\u0627\u0631\u0629", "lat": "40.64910", "lon": "-3.15111", "region": "Andalus", "searchNames": "Wadi al-Hijara", "topType": "towns", "topTypeAlt": "cite?", "topURI": "WADIHIJARA_031W406N_S_ANDA", "translitTitle": "W\u0101d\u012b al-\u1e24ij\u0101ra\u0167", "translitTitleOther": "W\u0101d\u012b al-\u1e24ij\u0101ra\u0167"}, "type": "Feature"}], "type": "FeatureCollection"}