{"features": [{"geometry": {"coordinates": [40.98726, 22.03204], "type": "Point"}, "properties": {"arBW": "al-Wajra", "arTitle": "\ufb50\u0644\u0648\u062c\u0631\u0629", "arTitleOther": "\ufb50\u0644\u0648\u062c\u0631\u0629", "lat": "22.03204", "lon": "40.98726", "region": "Jazirat al-Arab", "searchNames": "al-Wajra", "topType": "waystations", "topTypeAlt": "etape", "topURI": "WAJRA_409E220N_S_JAZI", "translitTitle": "al-Wa\u01e7ra\u0167", "translitTitleOther": "al-Wa\u01e7ra\u0167"}, "type": "Feature"}], "type": "FeatureCollection"}