{"features": [{"geometry": {"coordinates": [33.54242, 31.06734], "type": "Point"}, "properties": {"arBW": "al-Warrada", "arTitle": "\ufb50\u0644\u0648\u0631\u0627\u062f\u0629", "arTitleOther": "\ufb50\u0644\u0648\u0631\u0627\u062f\u0629", "lat": "31.06734", "lon": "33.54242", "region": "Egypt", "searchNames": "al-Warrada", "topType": "towns", "topTypeAlt": "cite", "topURI": "WARRADA_335E310N_S_EGYP", "translitTitle": "al-Warr\u0101da\u0167", "translitTitleOther": "al-Warr\u0101da\u0167"}, "type": "Feature"}], "type": "FeatureCollection"}