{"features": [{"geometry": {"coordinates": [15.1673, 37.62947], "type": "Point"}, "properties": {"arBW": "al-Yaj", "arTitle": "\ufb50\u0644\u064a\u0627\u062c", "arTitleOther": "\ufb50\u0644\u064a\u0627\u062c", "lat": "37.62947", "lon": "15.16730", "region": "Sicile", "searchNames": "al-Yaj", "topType": "towns", "topTypeAlt": "cite", "topURI": "YAJ_151E376N_S_SICI", "translitTitle": "al-Y\u0101\u01e7", "translitTitleOther": "al-Y\u0101\u01e7"}, "type": "Feature"}], "type": "FeatureCollection"}