{"features": [{"geometry": {"coordinates": [44.67244, 15.92968], "type": "Point"}, "properties": {"arBW": "Yam", "arTitle": "\u064a\u0627\u0645", "arTitleOther": "\u064a\u0627\u0645", "lat": "15.92968", "lon": "44.67244", "region": "Yemen", "searchNames": "Yam", "topType": "regions", "topTypeAlt": "region", "topURI": "YAM_446E159N_R_YEME", "translitTitle": "Y\u0101m", "translitTitleOther": "Y\u0101m"}, "type": "Feature"}], "type": "FeatureCollection"}