{"features": [{"geometry": {"coordinates": [59.71005, 42.21861], "type": "Point"}, "properties": {"arBW": "Zamakhshar", "arTitle": "\u0632\u0645\u062e\u0634\u0631", "arTitleOther": "\u0632\u0645\u062e\u0634\u0631", "lat": "42.21861", "lon": "59.71005", "region": "Transoxiana", "searchNames": "Zamakhshar", "topType": "towns", "topTypeAlt": "cite", "topURI": "ZAMAKHSHAR_597E422N_S_TRAN", "translitTitle": "Zama\u1e2b\u0161ar", "translitTitleOther": "Zama\u1e2b\u0161ar"}, "type": "Feature"}], "type": "FeatureCollection"}