{"features": [{"geometry": {"coordinates": [65.19679, 37.86572], "type": "Point"}, "properties": {"arBW": "Zamm, Karkuh", "arTitle": "\u0632\u0645", "arTitleOther": "\u0632\u0645\u060c \u0643\u0631\u0643\u0647", "lat": "37.86572", "lon": "65.19679", "region": "Khurasan", "searchNames": "Zamm, Karkuh", "topType": "towns", "topTypeAlt": "cite", "topURI": "ZAMM_651E378N_S_KHUR", "translitTitle": "Zamm", "translitTitleOther": "Zamm, Karkuh"}, "type": "Feature"}], "type": "FeatureCollection"}