{"features": [{"geometry": {"coordinates": [72.08263, 40.24237], "type": "Point"}, "properties": {"arBW": "Zandaramash", "arTitle": "\u0632\u0646\u062f\u0631\u0627\u0645\u0634", "arTitleOther": "\u0632\u0646\u062f\u0631\u0627\u0645\u0634", "lat": "40.24237", "lon": "72.08263", "region": "Transoxiana", "searchNames": "Zandaramash", "topType": "towns", "topTypeAlt": "cite", "topURI": "ZANDARAMASH_720E402N_S_TRAN", "translitTitle": "Zandar\u0101ma\u0161", "translitTitleOther": "Zandar\u0101ma\u0161"}, "type": "Feature"}], "type": "FeatureCollection"}