{"features": [{"geometry": {"coordinates": [56.59714, 30.82737], "type": "Point"}, "properties": {"arBW": "Zarand", "arTitle": "\u0632\u0631\u0646\u062f", "arTitleOther": "\u0632\u0631\u0646\u062f", "lat": "30.82737", "lon": "56.59714", "region": "Kirman", "searchNames": "Zarand", "topType": "towns", "topTypeAlt": "cite", "topURI": "ZARAND_565E308N_S_KIRM", "translitTitle": "Zarand", "translitTitleOther": "Zarand"}, "type": "Feature"}], "type": "FeatureCollection"}